Workbook

Sheet Tabela de ingredientes
A4: Ingredientes | B4: Custo Kg | C4: Açúcares | D4: Gorduras | E4: SNGL | F4: Outros Sólidos | G4: Sólidos Totais | H4: Água | I4: POD | J4: PAC | K4: Proteína | L4: Alergênico
A5: Abacate | B5: 0 | C5: 0.02 | D5: 0.23 | E5: 0 | F5: 0.11 | G5: 0.36 | H5: 0.64 | I5: 0.072 | J5: 0.087 | K5: 0.04 | L5: Não | N5: Parâmetros de tolerância para cada receita:
A6: Abacaxi | B6: 0 | C6: 0.1 | D6: 0 | E6: 0 | F6: 0.04 | G6: 0.14 | H6: 0.86 | I6: 0.16 | J6: 0.2 | K6: 0.01 | L6: Não | N6: Gelato de leite | O6: Açúcares | P6: Gorduras | Q6: SLNG | R6: OS | S6: ST | T6: Água | U6: POD | V6: PAC | X6: Status | Z6: Combinação do Rótulo (Anvisa)
A7: Acerola | B7: 0 | C7: 0.07 | D7: 0 | E7: 0 | F7: 0.01 | G7: 0.08 | H7: 0.92 | I7: 0.08 | J7: 0.1 | K7: 0.006 | L7: Não | N7: Mínimo | O7: 0.14 | P7: 0.05 | Q7: 0.08 | R7: 0 | S7: 0.34 | T7: 0.58 | U7: 135 | V7: 220 | X7: Ok | Z7: Alto em Açúcar Adicionado
A8: Açúcar - Dextrose | B8: 32 | C8: 0.92 | D8: 0 | E8: 0 | F8: 0 | G8: 0.92 | H8: 0.08 | I8: 0.74 | J8: 1.8 | K8: 0 | L8: Não | N8: Máximo | O8: 0.22 | P8: 0.12 | Q8: 0.12 | R8: 0.08 | S8: 0.42 | T8: 0.66 | U8: 200 | V8: 300 | X8: Baixo | Z8: Alto em Gordura Saturada
A9: Açúcar - Frutose | B9: 38 | C9: 1 | D9: 0 | E9: 0 | F9: 0 | G9: 1 | H9: 0 | I9: 1.45 | J9: 1.9 | K9: 0 | L9: Não | N9: Sorbet | O9: Açúcares | P9: Gorduras | Q9: SLNG | R9: OS | S9: ST | T9: Água | U9: POD | V9: PAC | X9: Alto | Z9: Alto em Sódio
A10: Açúcar - Glucose em pó | B10: 38 | C10: 0.95 | D10: 0 | E10: 0 | F10: 0 | G10: 0.95 | H10: 0.05 | I10: 0.4 | J10: 0.7 | K10: 0 | L10: Não | N10: Mínimo | O10: 0.23 | P10: 0 | Q10: 0 | R10: 0.01 | S10: 0.27 | T10: 0.65 | U10: 175 | V10: 275 | Z10: Alto em Açúcar Adicionado e Gordura Saturada
A11: Açúcar - Glucose Líquida | B11: 18 | C11: 0.8 | D11: 0 | E11: 0 | F11: 0 | G11: 0.8 | H11: 0.2 | I11: 0.45 | J11: 0.75 | K11: 0 | L11: Não | N11: Máximo | O11: 0.32 | P11: 0.02 | Q11: 0 | R11: 0.18 | S11: 0.35 | T11: 0.73 | U11: 240 | V11: 375 | Z11: Alto em Açúcar Adicionado e Sódio
A12: Açúcar - Lactose | B12: 45 | C12: 1 | D12: 0 | E12: 0 | F12: 0 | G12: 1 | H12: 0 | I12: 0.16 | J12: 1 | K12: 0 | L12: Sim | N12: Gelato de leite com fruta | O12: Açúcares | P12: Gorduras | Q12: SLNG | R12: OS | S12: ST | T12: Água | U12: POD | V12: PAC | Z12: Alto em Gordura Saturada e Sódio
A13: Açúcar - Maltodextrina | B13: 28 | C13: 0.95 | D13: 0 | E13: 0 | F13: 0 | G13: 0.95 | H13: 0.05 | I13: 0.02 | J13: 0.25 | K13: 0 | L13: Não | N13: Mínimo | O13: 0.17 | P13: 0.04 | Q13: 0.06 | R13: 0.01 | S13: 0.33 | T13: 0.57 | U13: 140 | V13: 220 | Z13: Alto em Açúcar Adicionado, Gordura Saturada e Sódio
A14: Açúcar de maçã(66% açúcar) | B14: 40 | C14: 0.66 | D14: 0 | E14: 0 | F14: 0.33 | G14: 0.99 | H14: 0.01 | I14: 0.85 | J14: =C14*1.9 -> 1.254 | K14: 0.005 | L14: Não | N14: Máximo | O14: 0.22 | P14: 0.08 | Q14: 0.1 | R14: 0.08 | S14: 0.42 | T14: 0.67 | U14: 200 | V14: 300
A15: Açúcar Invertido | B15: 16 | C15: 0.7 | D15: 0 | E15: 0 | F15: 0 | G15: 0.7 | H15: 0.3 | I15: 1.27 | J15: 1.9 | K15: 0 | L15: Não | N15: Base de Água com Chocolate | O15: Açúcares | P15: Gorduras | Q15: SLNG | R15: Os | S15: St | T15: Água | U15: Pod | V15: Pac
A16: Açúcar Sacarose | B16: 4 | C16: 1 | D16: 0 | E16: 0 | F16: 0 | G16: 1 | H16: 0 | I16: 1 | J16: 1 | K16: 0 | L16: Não | N16: Mínimo | O16: 0.18 | P16: 0.01 | Q16: 0 | R16: 0.04 | S16: 0.34 | T16: 0.56 | U16: 140 | V16: 220
A17: Água | B17: 0 | C17: 0 | D17: 0 | E17: 0 | F17: 0 | G17: 0 | H17: 1 | I17: 0 | J17: 0 | K17: 0 | L17: Não | N17: Máximo | O17: 0.24 | P17: 0.1 | Q17: 0.01 | R17: 0.12 | S17: 0.44 | T17: 0.66 | U17: 260 | V17: 300
A18: Álcool 96° | B18: 22 | C18: 0 | D18: 0 | E18: 0 | F18: 0 | G18: 0 | H18: 1 | I18: 0 | J18: 3.5 | K18: 0 | L18: Não | N18: Base Vegana | O18: Açúcares | P18: Gorduras | Q18: SLNG | R18: OS | S18: ST | T18: Água | U18: POD | V18: PAC
A19: Ameixa Vermelha | B19: 0 | C19: 0.11 | D19: 0 | E19: 0 | F19: 0.02 | G19: 0.13 | H19: 0.87 | I19: 0.13 | J19: 0.15 | K19: 0.01 | L19: Não | N19: Mínimo | O19: 0.18 | P19: 0.08 | Q19: 0 | R19: 0.03 | S19: 0.35 | T19: 0.58 | U19: 129 | V19: 210
A20: Amendoim Torrado | B20: 22 | C20: 0.03 | D20: 0.5 | E20: 0 | F20: 0.44 | G20: 0.97 | H20: 0.03 | I20: 0.252 | J20: 0.3045 | K20: 0 | L20: Sim | N20: Máximo | O20: 0.24 | P20: 0.13 | Q20: 0.01 | R20: 0.15 | S20: 0.42 | T20: 0.65 | U20: 195 | V20: 300
A21: Amora | B21: 35 | C21: 0.08 | D21: 0 | E21: 0 | F21: 0.07 | G21: 0.15 | H21: 0.85 | I21: 0.095 | J21: 0.115 | K21: 0.01 | L21: Não | N21: Alcoólicos | O21: Açúcares | P21: Gorduras | Q21: SLNG | R21: OS | S21: ST | T21: Água | U21: POD | V21: PAC
A22: Atemoia | B22: 0 | C22: 0.21 | D22: 0.003 | E22: 0 | F22: 0.035 | G22: 0.248 | H22: 0.752 | I22: 0.22 | J22: 0.24 | K22: 0.019 | L22: Não | N22: Mínimo | O22: 0.16 | P22: 0.05 | Q22: 0.06 | R22: 0 | S22: 0.32 | T22: 0.54 | U22: 120 | V22: 250
A23: Banana | B23: 0 | C23: 0.16 | D23: 0 | E23: 0 | F23: 0.07 | G23: 0.23 | H23: 0.77 | I23: 0.19 | J23: 0.23 | K23: 0.01 | L23: Não | N23: Máximo | O23: 0.22 | P23: 0.16 | Q23: 0.12 | R23: 0.14 | S23: 0.46 | T23: 0.68 | U23: 210 | V23: 380
A24: Base de água | B24: {=IFERROR(SUMPRODUCT(('Pré-preparos e Variegatos'!$A$2:$A$1000=$A24)*'Pré-preparos e Variegatos'!$C$2:$C$1000*IFERROR(VLOOKUP('Pré-preparos e Variegatos'!$B$2:$B$1000, VSTACK($A$5:$K$23, $A$28:$K$31, $A$33:$K$58, $A$60:$K$96, $A$99:$K$137, $A$139:$K$140, $A$142:$K$151, $A$153:$K$168, $A$170:$K$188, $A$194:$K$500), 2, 0), 0))/SUMIF('Pré-preparos e Variegatos'!$A$2:$A$1000, $A24, 'Pré-preparos e Variegatos'!$C$2:$C$1000) * IFERROR(VLOOKUP($A24, 'Pré-preparos e Variegatos'!$M$2:$Q$100, 5, FALSE), 1), 0)} -> 9.8304743 | C24: {=IFERROR(SUMPRODUCT(('Pré-preparos e Variegatos'!$A$2:$A$1000=$A24)*'Pré-preparos e Variegatos'!$C$2:$C$1000*IFERROR(VLOOKUP('Pré-preparos e Variegatos'!$B$2:$B$1000, VSTACK($A$5:$K$23, $A$28:$K$31, $A$33:$K$58, $A$60:$K$96, $A$99:$K$137, $A$139:$K$140, $A$142:$K$151, $A$153:$K$168, $A$170:$K$188, $A$194:$K$500), 3, 0), 0))/SUMIF('Pré-preparos e Variegatos'!$A$2:$A$1000, $A24, 'Pré-preparos e Variegatos'!$C$2:$C$1000) * IFERROR(VLOOKUP($A24, 'Pré-preparos e Variegatos'!$M$2:$Q$100, 5, FALSE), 1), 0)} -> 0.47467205 | D24: {=IFERROR(SUMPRODUCT(('Pré-preparos e Variegatos'!$A$2:$A$1000=$A24)*'Pré-preparos e Variegatos'!$C$2:$C$1000*IFERROR(VLOOKUP('Pré-preparos e Variegatos'!$B$2:$B$1000, VSTACK($A$5:$K$23, $A$28:$K$31, $A$33:$K$58, $A$60:$K$96, $A$99:$K$137, $A$139:$K$140, $A$142:$K$151, $A$153:$K$168, $A$170:$K$188, $A$194:$K$500), 4, 0), 0))/SUMIF('Pré-preparos e Variegatos'!$A$2:$A$1000, $A24, 'Pré-preparos e Variegatos'!$C$2:$C$1000) * IFERROR(VLOOKUP($A24, 'Pré-preparos e Variegatos'!$M$2:$Q$100, 5, FALSE), 1), 0)} -> 0 | E24: {=IFERROR(SUMPRODUCT(('Pré-preparos e Variegatos'!$A$2:$A$1000=$A24)*'Pré-preparos e Variegatos'!$C$2:$C$1000*IFERROR(VLOOKUP('Pré-preparos e Variegatos'!$B$2:$B$1000, VSTACK($A$5:$K$23, $A$28:$K$31, $A$33:$K$58, $A$60:$K$96, $A$99:$K$137, $A$139:$K$140, $A$142:$K$151, $A$153:$K$168, $A$170:$K$188, $A$194:$K$500), 5, 0), 0))/SUMIF('Pré-preparos e Variegatos'!$A$2:$A$1000, $A24, 'Pré-preparos e Variegatos'!$C$2:$C$1000) * IFERROR(VLOOKUP($A24, 'Pré-preparos e Variegatos'!$M$2:$Q$100, 5, FALSE), 1), 0)} -> 0 | F24: {=IFERROR(SUMPRODUCT(('Pré-preparos e Variegatos'!$A$2:$A$1000=$A24)*'Pré-preparos e Variegatos'!$C$2:$C$1000*IFERROR(VLOOKUP('Pré-preparos e Variegatos'!$B$2:$B$1000, VSTACK($A$5:$K$23, $A$28:$K$31, $A$33:$K$58, $A$60:$K$96, $A$99:$K$137, $A$139:$K$140, $A$142:$K$151, $A$153:$K$168, $A$170:$K$188, $A$194:$K$500), 6, 0), 0))/SUMIF('Pré-preparos e Variegatos'!$A$2:$A$1000, $A24, 'Pré-preparos e Variegatos'!$C$2:$C$1000) * IFERROR(VLOOKUP($A24, 'Pré-preparos e Variegatos'!$M$2:$Q$100, 5, FALSE), 1), 0)} -> 0.016649849 | G24: =MIN(1, SUM(C24:F24)) -> 0.4913219 | H24: =1-G24 -> 0.5086781 | I24: {=IFERROR(SUMPRODUCT(('Pré-preparos e Variegatos'!$A$2:$A$1000=$A24)*'Pré-preparos e Variegatos'!$C$2:$C$1000*IFERROR(VLOOKUP('Pré-preparos e Variegatos'!$B$2:$B$1000, VSTACK($A$5:$K$23, $A$28:$K$31, $A$33:$K$58, $A$60:$K$96, $A$99:$K$137, $A$139:$K$140, $A$142:$K$151, $A$153:$K$168, $A$170:$K$188, $A$194:$K$500), 9, 0), 0))/SUMIF('Pré-preparos e Variegatos'!$A$2:$A$1000, $A24, 'Pré-preparos e Variegatos'!$C$2:$C$1000) * IFERROR(VLOOKUP($A24, 'Pré-preparos e Variegatos'!$M$2:$Q$100, 5, FALSE), 1), 0)} -> 0.42421796 | J24: {=IFERROR(SUMPRODUCT(('Pré-preparos e Variegatos'!$A$2:$A$1000=$A24)*'Pré-preparos e Variegatos'!$C$2:$C$1000*IFERROR(VLOOKUP('Pré-preparos e Variegatos'!$B$2:$B$1000, VSTACK($A$5:$K$23, $A$28:$K$31, $A$33:$K$58, $A$60:$K$96, $A$99:$K$137, $A$139:$K$140, $A$142:$K$151, $A$153:$K$168, $A$170:$K$188, $A$194:$K$500), 10, 0), 0))/SUMIF('Pré-preparos e Variegatos'!$A$2:$A$1000, $A24, 'Pré-preparos e Variegatos'!$C$2:$C$1000) * IFERROR(VLOOKUP($A24, 'Pré-preparos e Variegatos'!$M$2:$Q$100, 5, FALSE), 1), 0)} -> 0.53562059 | K24: {=IFERROR(SUMPRODUCT(('Pré-preparos e Variegatos'!$A$2:$A$1000=$A24)*'Pré-preparos e Variegatos'!$C$2:$C$1000*IFERROR(VLOOKUP('Pré-preparos e Variegatos'!$B$2:$B$1000, VSTACK($A$5:$K$23, $A$28:$K$31, $A$33:$K$58, $A$60:$K$96, $A$99:$K$137, $A$139:$K$140, $A$142:$K$151, $A$153:$K$168, $A$170:$K$188, $A$194:$K$500), 11, 0), 0))/SUMIF('Pré-preparos e Variegatos'!$A$2:$A$1000, $A24, 'Pré-preparos e Variegatos'!$C$2:$C$1000) * IFERROR(VLOOKUP($A24, 'Pré-preparos e Variegatos'!$M$2:$Q$100, 5, FALSE), 1), 0)} -> 0 | L24: {=IF(SUMPRODUCT(('Pré-preparos e Variegatos'!$A$2:$A$1000=$A24)*(IFERROR(VLOOKUP('Pré-preparos e Variegatos'!$B$2:$B$1000, VSTACK($A$5:$L$23, $A$28:$L$31, $A$33:$L$58, $A$60:$L$96, $A$99:$L$137, $A$139:$L$140, $A$142:$L$151, $A$153:$L$168, $A$170:$L$188, $A$194:$L$500), 12, 0), "Não")="Sim"))>0, "Sim", "Não")} -> Não | N24: Zero | O24: Açúcares | P24: Gorduras | Q24: SLNG | R24: OS | S24: ST | T24: Água | U24: POD | V24: PAC
A25: Base de leite | B25: {=IFERROR(SUMPRODUCT(('Pré-preparos e Variegatos'!$A$2:$A$1000=$A25)*'Pré-preparos e Variegatos'!$C$2:$C$1000*IFERROR(VLOOKUP('Pré-preparos e Variegatos'!$B$2:$B$1000, VSTACK($A$5:$K$23, $A$28:$K$31, $A$33:$K$58, $A$60:$K$96, $A$99:$K$137, $A$139:$K$140, $A$142:$K$151, $A$153:$K$168, $A$170:$K$188, $A$194:$K$500), 2, 0), 0))/SUMIF('Pré-preparos e Variegatos'!$A$2:$A$1000, $A25, 'Pré-preparos e Variegatos'!$C$2:$C$1000) * IFERROR(VLOOKUP($A25, 'Pré-preparos e Variegatos'!$M$2:$Q$100, 5, FALSE), 1), 0)} -> 14.838323 | C25: {=IFERROR(SUMPRODUCT(('Pré-preparos e Variegatos'!$A$2:$A$1000=$A25)*'Pré-preparos e Variegatos'!$C$2:$C$1000*IFERROR(VLOOKUP('Pré-preparos e Variegatos'!$B$2:$B$1000, VSTACK($A$5:$K$23, $A$28:$K$31, $A$33:$K$58, $A$60:$K$96, $A$99:$K$137, $A$139:$K$140, $A$142:$K$151, $A$153:$K$168, $A$170:$K$188, $A$194:$K$500), 3, 0), 0))/SUMIF('Pré-preparos e Variegatos'!$A$2:$A$1000, $A25, 'Pré-preparos e Variegatos'!$C$2:$C$1000) * IFERROR(VLOOKUP($A25, 'Pré-preparos e Variegatos'!$M$2:$Q$100, 5, FALSE), 1), 0)} -> 0.17035928 | D25: {=IFERROR(SUMPRODUCT(('Pré-preparos e Variegatos'!$A$2:$A$1000=$A25)*'Pré-preparos e Variegatos'!$C$2:$C$1000*IFERROR(VLOOKUP('Pré-preparos e Variegatos'!$B$2:$B$1000, VSTACK($A$5:$K$23, $A$28:$K$31, $A$33:$K$58, $A$60:$K$96, $A$99:$K$137, $A$139:$K$140, $A$142:$K$151, $A$153:$K$168, $A$170:$K$188, $A$194:$K$500), 4, 0), 0))/SUMIF('Pré-preparos e Variegatos'!$A$2:$A$1000, $A25, 'Pré-preparos e Variegatos'!$C$2:$C$1000) * IFERROR(VLOOKUP($A25, 'Pré-preparos e Variegatos'!$M$2:$Q$100, 5, FALSE), 1), 0)} -> 0.077894212 | E25: {=IFERROR(SUMPRODUCT(('Pré-preparos e Variegatos'!$A$2:$A$1000=$A25)*'Pré-preparos e Variegatos'!$C$2:$C$1000*IFERROR(VLOOKUP('Pré-preparos e Variegatos'!$B$2:$B$1000, VSTACK($A$5:$K$23, $A$28:$K$31, $A$33:$K$58, $A$60:$K$96, $A$99:$K$137, $A$139:$K$140, $A$142:$K$151, $A$153:$K$168, $A$170:$K$188, $A$194:$K$500), 5, 0), 0))/SUMIF('Pré-preparos e Variegatos'!$A$2:$A$1000, $A25, 'Pré-preparos e Variegatos'!$C$2:$C$1000) * IFERROR(VLOOKUP($A25, 'Pré-preparos e Variegatos'!$M$2:$Q$100, 5, FALSE), 1), 0)} -> 0.10553892 | F25: {=IFERROR(SUMPRODUCT(('Pré-preparos e Variegatos'!$A$2:$A$1000=$A25)*'Pré-preparos e Variegatos'!$C$2:$C$1000*IFERROR(VLOOKUP('Pré-preparos e Variegatos'!$B$2:$B$1000, VSTACK($A$5:$K$23, $A$28:$K$31, $A$33:$K$58, $A$60:$K$96, $A$99:$K$137, $A$139:$K$140, $A$142:$K$151, $A$153:$K$168, $A$170:$K$188, $A$194:$K$500), 6, 0), 0))/SUMIF('Pré-preparos e Variegatos'!$A$2:$A$1000, $A25, 'Pré-preparos e Variegatos'!$C$2:$C$1000) * IFERROR(VLOOKUP($A25, 'Pré-preparos e Variegatos'!$M$2:$Q$100, 5, FALSE), 1), 0)} -> 0.035279441 | G25: =MIN(1, SUM(C25:F25)) -> 0.38907186 | H25: =1-G25 -> 0.61092814 | I25: {=IFERROR(SUMPRODUCT(('Pré-preparos e Variegatos'!$A$2:$A$1000=$A25)*'Pré-preparos e Variegatos'!$C$2:$C$1000*IFERROR(VLOOKUP('Pré-preparos e Variegatos'!$B$2:$B$1000, VSTACK($A$5:$K$23, $A$28:$K$31, $A$33:$K$58, $A$60:$K$96, $A$99:$K$137, $A$139:$K$140, $A$142:$K$151, $A$153:$K$168, $A$170:$K$188, $A$194:$K$500), 9, 0), 0))/SUMIF('Pré-preparos e Variegatos'!$A$2:$A$1000, $A25, 'Pré-preparos e Variegatos'!$C$2:$C$1000) * IFERROR(VLOOKUP($A25, 'Pré-preparos e Variegatos'!$M$2:$Q$100, 5, FALSE), 1), 0)} -> 0.1566018 | J25: {=IFERROR(SUMPRODUCT(('Pré-preparos e Variegatos'!$A$2:$A$1000=$A25)*'Pré-preparos e Variegatos'!$C$2:$C$1000*IFERROR(VLOOKUP('Pré-preparos e Variegatos'!$B$2:$B$1000, VSTACK($A$5:$K$23, $A$28:$K$31, $A$33:$K$58, $A$60:$K$96, $A$99:$K$137, $A$139:$K$140, $A$142:$K$151, $A$153:$K$168, $A$170:$K$188, $A$194:$K$500), 10, 0), 0))/SUMIF('Pré-preparos e Variegatos'!$A$2:$A$1000, $A25, 'Pré-preparos e Variegatos'!$C$2:$C$1000) * IFERROR(VLOOKUP($A25, 'Pré-preparos e Variegatos'!$M$2:$Q$100, 5, FALSE), 1), 0)} -> 0.2507485 | K25: {=IFERROR(SUMPRODUCT(('Pré-preparos e Variegatos'!$A$2:$A$1000=$A25)*'Pré-preparos e Variegatos'!$C$2:$C$1000*IFERROR(VLOOKUP('Pré-preparos e Variegatos'!$B$2:$B$1000, VSTACK($A$5:$K$23, $A$28:$K$31, $A$33:$K$58, $A$60:$K$96, $A$99:$K$137, $A$139:$K$140, $A$142:$K$151, $A$153:$K$168, $A$170:$K$188, $A$194:$K$500), 11, 0), 0))/SUMIF('Pré-preparos e Variegatos'!$A$2:$A$1000, $A25, 'Pré-preparos e Variegatos'!$C$2:$C$1000) * IFERROR(VLOOKUP($A25, 'Pré-preparos e Variegatos'!$M$2:$Q$100, 5, FALSE), 1), 0)} -> 0.040379242 | L25: {=IF(SUMPRODUCT(('Pré-preparos e Variegatos'!$A$2:$A$1000=$A25)*(IFERROR(VLOOKUP('Pré-preparos e Variegatos'!$B$2:$B$1000, VSTACK($A$5:$L$23, $A$28:$L$31, $A$33:$L$58, $A$60:$L$96, $A$99:$L$137, $A$139:$L$140, $A$142:$L$151, $A$153:$L$168, $A$170:$L$188, $A$194:$L$500), 12, 0), "Não")="Sim"))>0, "Sim", "Não")} -> Sim | N25: Mínimo | O25: 0.04 | P25: 0 | Q25: 0 | R25: 0.01 | S25: 0.28 | T25: 0.58 | U25: 95 | V25: 220
A26: Base de Leite (Creme de leite 17% UHT) | B26: {=IFERROR(SUMPRODUCT(('Pré-preparos e Variegatos'!$A$2:$A$1000=$A26)*'Pré-preparos e Variegatos'!$C$2:$C$1000*IFERROR(VLOOKUP('Pré-preparos e Variegatos'!$B$2:$B$1000, VSTACK($A$5:$K$23, $A$28:$K$31, $A$33:$K$58, $A$60:$K$96, $A$99:$K$137, $A$139:$K$140, $A$142:$K$151, $A$153:$K$168, $A$170:$K$188, $A$194:$K$500), 2, 0), 0))/SUMIF('Pré-preparos e Variegatos'!$A$2:$A$1000, $A26, 'Pré-preparos e Variegatos'!$C$2:$C$1000) * IFERROR(VLOOKUP($A26, 'Pré-preparos e Variegatos'!$M$2:$Q$100, 5, FALSE), 1), 0)} -> 15.1429 | C26: {=IFERROR(SUMPRODUCT(('Pré-preparos e Variegatos'!$A$2:$A$1000=$A26)*'Pré-preparos e Variegatos'!$C$2:$C$1000*IFERROR(VLOOKUP('Pré-preparos e Variegatos'!$B$2:$B$1000, VSTACK($A$5:$K$23, $A$28:$K$31, $A$33:$K$58, $A$60:$K$96, $A$99:$K$137, $A$139:$K$140, $A$142:$K$151, $A$153:$K$168, $A$170:$K$188, $A$194:$K$500), 3, 0), 0))/SUMIF('Pré-preparos e Variegatos'!$A$2:$A$1000, $A26, 'Pré-preparos e Variegatos'!$C$2:$C$1000) * IFERROR(VLOOKUP($A26, 'Pré-preparos e Variegatos'!$M$2:$Q$100, 5, FALSE), 1), 0)} -> 0.17135 | D26: {=IFERROR(SUMPRODUCT(('Pré-preparos e Variegatos'!$A$2:$A$1000=$A26)*'Pré-preparos e Variegatos'!$C$2:$C$1000*IFERROR(VLOOKUP('Pré-preparos e Variegatos'!$B$2:$B$1000, VSTACK($A$5:$K$23, $A$28:$K$31, $A$33:$K$58, $A$60:$K$96, $A$99:$K$137, $A$139:$K$140, $A$142:$K$151, $A$153:$K$168, $A$170:$K$188, $A$194:$K$500), 4, 0), 0))/SUMIF('Pré-preparos e Variegatos'!$A$2:$A$1000, $A26, 'Pré-preparos e Variegatos'!$C$2:$C$1000) * IFERROR(VLOOKUP($A26, 'Pré-preparos e Variegatos'!$M$2:$Q$100, 5, FALSE), 1), 0)} -> 0.057915 | E26: {=IFERROR(SUMPRODUCT(('Pré-preparos e Variegatos'!$A$2:$A$1000=$A26)*'Pré-preparos e Variegatos'!$C$2:$C$1000*IFERROR(VLOOKUP('Pré-preparos e Variegatos'!$B$2:$B$1000, VSTACK($A$5:$K$23, $A$28:$K$31, $A$33:$K$58, $A$60:$K$96, $A$99:$K$137, $A$139:$K$140, $A$142:$K$151, $A$153:$K$168, $A$170:$K$188, $A$194:$K$500), 5, 0), 0))/SUMIF('Pré-preparos e Variegatos'!$A$2:$A$1000, $A26, 'Pré-preparos e Variegatos'!$C$2:$C$1000) * IFERROR(VLOOKUP($A26, 'Pré-preparos e Variegatos'!$M$2:$Q$100, 5, FALSE), 1), 0)} -> 0.10931 | F26: {=IFERROR(SUMPRODUCT(('Pré-preparos e Variegatos'!$A$2:$A$1000=$A26)*'Pré-preparos e Variegatos'!$C$2:$C$1000*IFERROR(VLOOKUP('Pré-preparos e Variegatos'!$B$2:$B$1000, VSTACK($A$5:$K$23, $A$28:$K$31, $A$33:$K$58, $A$60:$K$96, $A$99:$K$137, $A$139:$K$140, $A$142:$K$151, $A$153:$K$168, $A$170:$K$188, $A$194:$K$500), 6, 0), 0))/SUMIF('Pré-preparos e Variegatos'!$A$2:$A$1000, $A26, 'Pré-preparos e Variegatos'!$C$2:$C$1000) * IFERROR(VLOOKUP($A26, 'Pré-preparos e Variegatos'!$M$2:$Q$100, 5, FALSE), 1), 0)} -> 0.044 | G26: =MIN(1, SUM(C26:F26)) -> 0.382575 | H26: =1-G26 -> 0.617425 | I26: {=IFERROR(SUMPRODUCT(('Pré-preparos e Variegatos'!$A$2:$A$1000=$A26)*'Pré-preparos e Variegatos'!$C$2:$C$1000*IFERROR(VLOOKUP('Pré-preparos e Variegatos'!$B$2:$B$1000, VSTACK($A$5:$K$23, $A$28:$K$31, $A$33:$K$58, $A$60:$K$96, $A$99:$K$137, $A$139:$K$140, $A$142:$K$151, $A$153:$K$168, $A$170:$K$188, $A$194:$K$500), 9, 0), 0))/SUMIF('Pré-preparos e Variegatos'!$A$2:$A$1000, $A26, 'Pré-preparos e Variegatos'!$C$2:$C$1000) * IFERROR(VLOOKUP($A26, 'Pré-preparos e Variegatos'!$M$2:$Q$100, 5, FALSE), 1), 0)} -> 0.1613102 | J26: {=IFERROR(SUMPRODUCT(('Pré-preparos e Variegatos'!$A$2:$A$1000=$A26)*'Pré-preparos e Variegatos'!$C$2:$C$1000*IFERROR(VLOOKUP('Pré-preparos e Variegatos'!$B$2:$B$1000, VSTACK($A$5:$K$23, $A$28:$K$31, $A$33:$K$58, $A$60:$K$96, $A$99:$K$137, $A$139:$K$140, $A$142:$K$151, $A$153:$K$168, $A$170:$K$188, $A$194:$K$500), 10, 0), 0))/SUMIF('Pré-preparos e Variegatos'!$A$2:$A$1000, $A26, 'Pré-preparos e Variegatos'!$C$2:$C$1000) * IFERROR(VLOOKUP($A26, 'Pré-preparos e Variegatos'!$M$2:$Q$100, 5, FALSE), 1), 0)} -> 0.25426 | K26: {=IFERROR(SUMPRODUCT(('Pré-preparos e Variegatos'!$A$2:$A$1000=$A26)*'Pré-preparos e Variegatos'!$C$2:$C$1000*IFERROR(VLOOKUP('Pré-preparos e Variegatos'!$B$2:$B$1000, VSTACK($A$5:$K$23, $A$28:$K$31, $A$33:$K$58, $A$60:$K$96, $A$99:$K$137, $A$139:$K$140, $A$142:$K$151, $A$153:$K$168, $A$170:$K$188, $A$194:$K$500), 11, 0), 0))/SUMIF('Pré-preparos e Variegatos'!$A$2:$A$1000, $A26, 'Pré-preparos e Variegatos'!$C$2:$C$1000) * IFERROR(VLOOKUP($A26, 'Pré-preparos e Variegatos'!$M$2:$Q$100, 5, FALSE), 1), 0)} -> 0.040875 | L26: {=IF(SUMPRODUCT(('Pré-preparos e Variegatos'!$A$2:$A$1000=$A26)*(IFERROR(VLOOKUP('Pré-preparos e Variegatos'!$B$2:$B$1000, VSTACK($A$5:$L$23, $A$28:$L$31, $A$33:$L$58, $A$60:$L$96, $A$99:$L$137, $A$139:$L$140, $A$142:$L$151, $A$153:$L$168, $A$170:$L$188, $A$194:$L$500), 12, 0), "Não")="Sim"))>0, "Sim", "Não")} -> Sim | N26: Máximo | O26: 0.28 | P26: 0.12 | Q26: 0.13 | R26: 0.23 | S26: 0.42 | T26: 0.72 | U26: 305 | V26: 395
A27: Base de leite(Fior di latte) | B27: {=IFERROR(SUMPRODUCT(('Pré-preparos e Variegatos'!$A$2:$A$1000=$A27)*'Pré-preparos e Variegatos'!$C$2:$C$1000*IFERROR(VLOOKUP('Pré-preparos e Variegatos'!$B$2:$B$1000, VSTACK($A$5:$K$23, $A$28:$K$31, $A$33:$K$58, $A$60:$K$96, $A$99:$K$137, $A$139:$K$140, $A$142:$K$151, $A$153:$K$168, $A$170:$K$188, $A$194:$K$500), 2, 0), 0))/SUMIF('Pré-preparos e Variegatos'!$A$2:$A$1000, $A27, 'Pré-preparos e Variegatos'!$C$2:$C$1000) * IFERROR(VLOOKUP($A27, 'Pré-preparos e Variegatos'!$M$2:$Q$100, 5, FALSE), 1), 0)} -> 11.703796 | C27: {=IFERROR(SUMPRODUCT(('Pré-preparos e Variegatos'!$A$2:$A$1000=$A27)*'Pré-preparos e Variegatos'!$C$2:$C$1000*IFERROR(VLOOKUP('Pré-preparos e Variegatos'!$B$2:$B$1000, VSTACK($A$5:$K$23, $A$28:$K$31, $A$33:$K$58, $A$60:$K$96, $A$99:$K$137, $A$139:$K$140, $A$142:$K$151, $A$153:$K$168, $A$170:$K$188, $A$194:$K$500), 3, 0), 0))/SUMIF('Pré-preparos e Variegatos'!$A$2:$A$1000, $A27, 'Pré-preparos e Variegatos'!$C$2:$C$1000) * IFERROR(VLOOKUP($A27, 'Pré-preparos e Variegatos'!$M$2:$Q$100, 5, FALSE), 1), 0)} -> 0.17592408 | D27: {=IFERROR(SUMPRODUCT(('Pré-preparos e Variegatos'!$A$2:$A$1000=$A27)*'Pré-preparos e Variegatos'!$C$2:$C$1000*IFERROR(VLOOKUP('Pré-preparos e Variegatos'!$B$2:$B$1000, VSTACK($A$5:$K$23, $A$28:$K$31, $A$33:$K$58, $A$60:$K$96, $A$99:$K$137, $A$139:$K$140, $A$142:$K$151, $A$153:$K$168, $A$170:$K$188, $A$194:$K$500), 4, 0), 0))/SUMIF('Pré-preparos e Variegatos'!$A$2:$A$1000, $A27, 'Pré-preparos e Variegatos'!$C$2:$C$1000) * IFERROR(VLOOKUP($A27, 'Pré-preparos e Variegatos'!$M$2:$Q$100, 5, FALSE), 1), 0)} -> 0.074125874 | E27: {=IFERROR(SUMPRODUCT(('Pré-preparos e Variegatos'!$A$2:$A$1000=$A27)*'Pré-preparos e Variegatos'!$C$2:$C$1000*IFERROR(VLOOKUP('Pré-preparos e Variegatos'!$B$2:$B$1000, VSTACK($A$5:$K$23, $A$28:$K$31, $A$33:$K$58, $A$60:$K$96, $A$99:$K$137, $A$139:$K$140, $A$142:$K$151, $A$153:$K$168, $A$170:$K$188, $A$194:$K$500), 5, 0), 0))/SUMIF('Pré-preparos e Variegatos'!$A$2:$A$1000, $A27, 'Pré-preparos e Variegatos'!$C$2:$C$1000) * IFERROR(VLOOKUP($A27, 'Pré-preparos e Variegatos'!$M$2:$Q$100, 5, FALSE), 1), 0)} -> 0.10834166 | F27: {=IFERROR(SUMPRODUCT(('Pré-preparos e Variegatos'!$A$2:$A$1000=$A27)*'Pré-preparos e Variegatos'!$C$2:$C$1000*IFERROR(VLOOKUP('Pré-preparos e Variegatos'!$B$2:$B$1000, VSTACK($A$5:$K$23, $A$28:$K$31, $A$33:$K$58, $A$60:$K$96, $A$99:$K$137, $A$139:$K$140, $A$142:$K$151, $A$153:$K$168, $A$170:$K$188, $A$194:$K$500), 6, 0), 0))/SUMIF('Pré-preparos e Variegatos'!$A$2:$A$1000, $A27, 'Pré-preparos e Variegatos'!$C$2:$C$1000) * IFERROR(VLOOKUP($A27, 'Pré-preparos e Variegatos'!$M$2:$Q$100, 5, FALSE), 1), 0)} -> 0.005994006 | G27: =MIN(1, SUM(C27:F27)) -> 0.36438561 | H27: =1-G27 -> 0.63561439 | I27: {=IFERROR(SUMPRODUCT(('Pré-preparos e Variegatos'!$A$2:$A$1000=$A27)*'Pré-preparos e Variegatos'!$C$2:$C$1000*IFERROR(VLOOKUP('Pré-preparos e Variegatos'!$B$2:$B$1000, VSTACK($A$5:$K$23, $A$28:$K$31, $A$33:$K$58, $A$60:$K$96, $A$99:$K$137, $A$139:$K$140, $A$142:$K$151, $A$153:$K$168, $A$170:$K$188, $A$194:$K$500), 9, 0), 0))/SUMIF('Pré-preparos e Variegatos'!$A$2:$A$1000, $A27, 'Pré-preparos e Variegatos'!$C$2:$C$1000) * IFERROR(VLOOKUP($A27, 'Pré-preparos e Variegatos'!$M$2:$Q$100, 5, FALSE), 1), 0)} -> 0.16328272 | J27: {=IFERROR(SUMPRODUCT(('Pré-preparos e Variegatos'!$A$2:$A$1000=$A27)*'Pré-preparos e Variegatos'!$C$2:$C$1000*IFERROR(VLOOKUP('Pré-preparos e Variegatos'!$B$2:$B$1000, VSTACK($A$5:$K$23, $A$28:$K$31, $A$33:$K$58, $A$60:$K$96, $A$99:$K$137, $A$139:$K$140, $A$142:$K$151, $A$153:$K$168, $A$170:$K$188, $A$194:$K$500), 10, 0), 0))/SUMIF('Pré-preparos e Variegatos'!$A$2:$A$1000, $A27, 'Pré-preparos e Variegatos'!$C$2:$C$1000) * IFERROR(VLOOKUP($A27, 'Pré-preparos e Variegatos'!$M$2:$Q$100, 5, FALSE), 1), 0)} -> 0.24955045 | K27: {=IFERROR(SUMPRODUCT(('Pré-preparos e Variegatos'!$A$2:$A$1000=$A27)*'Pré-preparos e Variegatos'!$C$2:$C$1000*IFERROR(VLOOKUP('Pré-preparos e Variegatos'!$B$2:$B$1000, VSTACK($A$5:$K$23, $A$28:$K$31, $A$33:$K$58, $A$60:$K$96, $A$99:$K$137, $A$139:$K$140, $A$142:$K$151, $A$153:$K$168, $A$170:$K$188, $A$194:$K$500), 11, 0), 0))/SUMIF('Pré-preparos e Variegatos'!$A$2:$A$1000, $A27, 'Pré-preparos e Variegatos'!$C$2:$C$1000) * IFERROR(VLOOKUP($A27, 'Pré-preparos e Variegatos'!$M$2:$Q$100, 5, FALSE), 1), 0)} -> 0.041458541 | L27: {=IF(SUMPRODUCT(('Pré-preparos e Variegatos'!$A$2:$A$1000=$A27)*(IFERROR(VLOOKUP('Pré-preparos e Variegatos'!$B$2:$B$1000, VSTACK($A$5:$L$23, $A$28:$L$31, $A$33:$L$58, $A$60:$L$96, $A$99:$L$137, $A$139:$L$140, $A$142:$L$151, $A$153:$L$168, $A$170:$L$188, $A$194:$L$500), 12, 0), "Não")="Sim"))>0, "Sim", "Não")} -> Sim | N27: Gelatos Proteicos | O27: Açúcares | P27: Gorduras | Q27: SLNG | R27: OS | S27: ST | T27: Água | U27: POD | V27: PAC | W27: Proteína
A28: Batata doce roxa | B28: 0 | C28: 0.04 | D28: 0.0005 | E28: 0 | F28: =17.4/100 -> 0.174 | G28: =SUM(C28:F28) -> 0.2145 | H28: =1-G28 -> 0.7855 | I28: =C28*1 -> 0.04 | J28: =C28*1 -> 0.04 | K28: 0.016 | L28: Não | N28: Mínimo | O28: 0.05 | P28: 0.04 | Q28: 0.12 | R28: 0 | S28: 0.35 | T28: 0.57 | U28: 110 | V28: 220 | W28: 0.08
A29: Biscoff | B29: 175 | C29: 0.37 | D29: 0.38 | E29: 0 | F29: 0.17 | G29: =SUM(C29:F29) -> 0.92 | H29: =1-G29 -> 0.08 | I29: 0.37 | J29: 0.37 | K29: 0.029 | L29: Sim | N29: Máximo | O29: 0.21 | P29: 0.06 | Q29: 0.17 | R29: 0.14 | S29: 0.43 | T29: 0.65 | U29: 220 | V29: 340 | W29: 0.1
A30: Biscoito Champanhe | B30: 32 | C30: 0.26 | D30: 0.09 | E30: 0 | F30: 0.45 | G30: 0.8 | H30: 0.2 | I30: 0.25 | J30: 0.25 | K30: 0.106 | L30: Sim
A31: Biscoito Chocolate | B31: 38 | C31: 0.24 | D31: 0.078 | E31: 0.035 | F31: 0.647 | G31: 1 | H31: 0 | I31: 0 | J31: 0 | K31: 0.073 | L31: Sim | N31: Redução de Açúcar | O31: Açúcares | P31: Gorduras | Q31: SLNG | R31: OS | S31: ST | T31: Água | U31: POD | V31: PAC
A32: Brigadeiro | B32: {=IFERROR(SUMPRODUCT(('Pré-preparos e Variegatos'!$A$2:$A$1000=$A32)*'Pré-preparos e Variegatos'!$C$2:$C$1000*IFERROR(VLOOKUP('Pré-preparos e Variegatos'!$B$2:$B$1000, VSTACK($A$5:$K$23, $A$28:$K$31, $A$33:$K$58, $A$60:$K$96, $A$99:$K$137, $A$139:$K$140, $A$142:$K$151, $A$153:$K$168, $A$170:$K$188, $A$194:$K$500), 2, 0), 0))/SUMIF('Pré-preparos e Variegatos'!$A$2:$A$1000, $A32, 'Pré-preparos e Variegatos'!$C$2:$C$1000) * IFERROR(VLOOKUP($A32, 'Pré-preparos e Variegatos'!$M$2:$Q$100, 5, FALSE), 1), 0)} -> 46.592033 | C32: {=IFERROR(SUMPRODUCT(('Pré-preparos e Variegatos'!$A$2:$A$1000=$A32)*'Pré-preparos e Variegatos'!$C$2:$C$1000*IFERROR(VLOOKUP('Pré-preparos e Variegatos'!$B$2:$B$1000, VSTACK($A$5:$K$23, $A$28:$K$31, $A$33:$K$58, $A$60:$K$96, $A$99:$K$137, $A$139:$K$140, $A$142:$K$151, $A$153:$K$168, $A$170:$K$188, $A$194:$K$500), 3, 0), 0))/SUMIF('Pré-preparos e Variegatos'!$A$2:$A$1000, $A32, 'Pré-preparos e Variegatos'!$C$2:$C$1000) * IFERROR(VLOOKUP($A32, 'Pré-preparos e Variegatos'!$M$2:$Q$100, 5, FALSE), 1), 0)} -> 0.27010989 | D32: {=IFERROR(SUMPRODUCT(('Pré-preparos e Variegatos'!$A$2:$A$1000=$A32)*'Pré-preparos e Variegatos'!$C$2:$C$1000*IFERROR(VLOOKUP('Pré-preparos e Variegatos'!$B$2:$B$1000, VSTACK($A$5:$K$23, $A$28:$K$31, $A$33:$K$58, $A$60:$K$96, $A$99:$K$137, $A$139:$K$140, $A$142:$K$151, $A$153:$K$168, $A$170:$K$188, $A$194:$K$500), 4, 0), 0))/SUMIF('Pré-preparos e Variegatos'!$A$2:$A$1000, $A32, 'Pré-preparos e Variegatos'!$C$2:$C$1000) * IFERROR(VLOOKUP($A32, 'Pré-preparos e Variegatos'!$M$2:$Q$100, 5, FALSE), 1), 0)} -> 0.15296703 | E32: {=IFERROR(SUMPRODUCT(('Pré-preparos e Variegatos'!$A$2:$A$1000=$A32)*'Pré-preparos e Variegatos'!$C$2:$C$1000*IFERROR(VLOOKUP('Pré-preparos e Variegatos'!$B$2:$B$1000, VSTACK($A$5:$K$23, $A$28:$K$31, $A$33:$K$58, $A$60:$K$96, $A$99:$K$137, $A$139:$K$140, $A$142:$K$151, $A$153:$K$168, $A$170:$K$188, $A$194:$K$500), 5, 0), 0))/SUMIF('Pré-preparos e Variegatos'!$A$2:$A$1000, $A32, 'Pré-preparos e Variegatos'!$C$2:$C$1000) * IFERROR(VLOOKUP($A32, 'Pré-preparos e Variegatos'!$M$2:$Q$100, 5, FALSE), 1), 0)} -> 0.11416484 | F32: {=IFERROR(SUMPRODUCT(('Pré-preparos e Variegatos'!$A$2:$A$1000=$A32)*'Pré-preparos e Variegatos'!$C$2:$C$1000*IFERROR(VLOOKUP('Pré-preparos e Variegatos'!$B$2:$B$1000, VSTACK($A$5:$K$23, $A$28:$K$31, $A$33:$K$58, $A$60:$K$96, $A$99:$K$137, $A$139:$K$140, $A$142:$K$151, $A$153:$K$168, $A$170:$K$188, $A$194:$K$500), 6, 0), 0))/SUMIF('Pré-preparos e Variegatos'!$A$2:$A$1000, $A32, 'Pré-preparos e Variegatos'!$C$2:$C$1000) * IFERROR(VLOOKUP($A32, 'Pré-preparos e Variegatos'!$M$2:$Q$100, 5, FALSE), 1), 0)} -> 0.019241758 | G32: =MIN(1, SUM(C32:F32)) -> 0.55648352 | H32: =1-G32 -> 0.44351648 | I32: {=IFERROR(SUMPRODUCT(('Pré-preparos e Variegatos'!$A$2:$A$1000=$A32)*'Pré-preparos e Variegatos'!$C$2:$C$1000*IFERROR(VLOOKUP('Pré-preparos e Variegatos'!$B$2:$B$1000, VSTACK($A$5:$K$23, $A$28:$K$31, $A$33:$K$58, $A$60:$K$96, $A$99:$K$137, $A$139:$K$140, $A$142:$K$151, $A$153:$K$168, $A$170:$K$188, $A$194:$K$500), 9, 0), 0))/SUMIF('Pré-preparos e Variegatos'!$A$2:$A$1000, $A32, 'Pré-preparos e Variegatos'!$C$2:$C$1000) * IFERROR(VLOOKUP($A32, 'Pré-preparos e Variegatos'!$M$2:$Q$100, 5, FALSE), 1), 0)} -> 0.29508791 | J32: {=IFERROR(SUMPRODUCT(('Pré-preparos e Variegatos'!$A$2:$A$1000=$A32)*'Pré-preparos e Variegatos'!$C$2:$C$1000*IFERROR(VLOOKUP('Pré-preparos e Variegatos'!$B$2:$B$1000, VSTACK($A$5:$K$23, $A$28:$K$31, $A$33:$K$58, $A$60:$K$96, $A$99:$K$137, $A$139:$K$140, $A$142:$K$151, $A$153:$K$168, $A$170:$K$188, $A$194:$K$500), 10, 0), 0))/SUMIF('Pré-preparos e Variegatos'!$A$2:$A$1000, $A32, 'Pré-preparos e Variegatos'!$C$2:$C$1000) * IFERROR(VLOOKUP($A32, 'Pré-preparos e Variegatos'!$M$2:$Q$100, 5, FALSE), 1), 0)} -> 0.335 | K32: {=IFERROR(SUMPRODUCT(('Pré-preparos e Variegatos'!$A$2:$A$1000=$A32)*'Pré-preparos e Variegatos'!$C$2:$C$1000*IFERROR(VLOOKUP('Pré-preparos e Variegatos'!$B$2:$B$1000, VSTACK($A$5:$K$23, $A$28:$K$31, $A$33:$K$58, $A$60:$K$96, $A$99:$K$137, $A$139:$K$140, $A$142:$K$151, $A$153:$K$168, $A$170:$K$188, $A$194:$K$500), 11, 0), 0))/SUMIF('Pré-preparos e Variegatos'!$A$2:$A$1000, $A32, 'Pré-preparos e Variegatos'!$C$2:$C$1000) * IFERROR(VLOOKUP($A32, 'Pré-preparos e Variegatos'!$M$2:$Q$100, 5, FALSE), 1), 0)} -> 0.055824176 | L32: {=IF(SUMPRODUCT(('Pré-preparos e Variegatos'!$A$2:$A$1000=$A32)*(IFERROR(VLOOKUP('Pré-preparos e Variegatos'!$B$2:$B$1000, VSTACK($A$5:$L$23, $A$28:$L$31, $A$33:$L$58, $A$60:$L$96, $A$99:$L$137, $A$139:$L$140, $A$142:$L$151, $A$153:$L$168, $A$170:$L$188, $A$194:$L$500), 12, 0), "Não")="Sim"))>0, "Sim", "Não")} -> Sim | N32: Mínimo | O32: 0.08 | P32: 0 | Q32: 0 | R32: 0 | S32: 0.3 | T32: 0.58 | U32: 110 | V32: 210
A33: Cacau Em Pó 11% gordura | B33: 42 | C33: 0 | D33: 0.11 | E33: 0 | F33: 0.84 | G33: 0.95 | H33: 0.05 | I33: 0 | J33: 0 | K33: 0.18 | L33: Não | N33: Máximo | O33: 0.18 | P33: 0.12 | Q33: 0.12 | R33: 0.16 | S33: 0.42 | T33: 0.7 | U33: 190 | V33: 300
A34: Cacau Em Pó 22% gordura | B34: 215 | C34: 0 | D34: 0.22 | E34: 0 | F34: 0.72 | G34: =SUM(C34:F34) -> 0.94 | H34: =1-G34 -> 0.06 | I34: 0 | J34: 0 | K34: 0.18 | L34: Não
A35: Cachaça | B35: 20 | C35: 0 | D35: 0 | E35: 0 | F35: 0 | G35: 0 | H35: 1 | I35: 0 | J35: =40%*5 -> 2 | K35: 0 | L35: Não
A36: Café Expresso | B36: 0 | C36: 0.01 | D36: 0.03 | E36: 0 | F36: 0.06 | G36: 0.1 | H36: 0.9 | I36: 0.01 | J36: 0.01 | K36: 0 | L36: Não
A37: Café Solúvel | B37: 90 | C37: 0 | D37: 0.15 | E37: 0 | F37: 0.8 | G37: 0.95 | H37: 0.05 | I37: 0 | J37: 0 | K37: 0.01 | L37: Não
A38: Caqui | B38: 0 | C38: 0.16 | D38: 0 | E38: 0 | F38: 0.02 | G38: 0.18 | H38: 0.82 | I38: 0.19 | J38: 0.23 | K38: 0.01 | L38: Não
A39: Cenoura | B39: 0 | C39: 0.08 | D39: 0 | E39: 0 | F39: 0.06 | G39: 0.14 | H39: 0.86 | I39: 0.06 | J39: 0.075 | K39: 0.01 | L39: Não
A40: Cereja | B40: 0 | C40: 0.12 | D40: 0 | E40: 0 | F40: 0.035 | G40: 0.155 | H40: 0.845 | I40: 0.14 | J40: 0.17 | K40: 0 | L40: Não
A41: Cereja Em Calda | B41: 0 | C41: 0.115 | D41: 0.005 | E41: 0 | F41: 0.025 | G41: 0.145 | H41: 0.855 | I41: 0.13 | J41: 0.16 | K41: 0.008 | L41: Não
A42: Chocolate Amargo 60% | B42: 95 | C42: 0.4 | D42: 0.35 | E42: 0 | F42: 0.25 | G42: 1 | H42: 0 | I42: 0.4 | J42: 0.4 | K42: 0.084 | L42: Não
A43: Chocolate Amargo 70% | B43: 175 | C43: 0.3 | D43: 0.38 | E43: 0 | F43: 0.32 | G43: 1 | H43: 0 | I43: 0.58 | J43: 0 | K43: 0.05 | L43: Não
A44: Chocolate Amargo 90% | B44: 0 | C44: 0.3 | D44: 0.38 | E44: 0 | F44: 0.32 | G44: 1 | H44: 0 | I44: 0.58 | J44: 0 | K44: 0.05 | L44: Não
A45: Chocolate Ao Leite 33.7% | B45: 185 | C45: 0.45 | D45: 0.36 | E45: 0.125 | F45: 0.065 | G45: 1 | H45: 0 | I45: 0.61 | J45: 0.51 | K45: 0.09 | L45: Sim
A46: Chocolate ao leite 40% | B46: 0 | C46: 0.4 | D46: 0.35 | E46: 0.18 | F46: 0.07 | G46: 1 | H46: 0 | I46: 0.41584 | J46: 0.499 | K46: 0.0594 | L46: Sim
A47: Chocolate Branco | B47: 160 | C47: 0.55 | D47: 0.2 | E47: 0.15 | F47: 0.1 | G47: 1 | H47: 0 | I47: 0.59 | J47: 0.25 | K47: 0.04 | L47: Sim
... A56: Creme De Leite Fresco 38% | B56: 0 | C56: 0 | D56: 0.38 | E56: 0.06 | F56: 0 | G56: 0.44 | H56: 0.56 | I56: 0.005 | J56: 0.03 | K56: 0.024 | L56: Sim
A57: Creme De Leite UHT 17% - Piracanjuba | B57: 12.5 | C57: 0 | D57: 0.17 | E57: 0.07 | F57: 0 | G57: 0.24 | H57: =1-G57 -> 0.76 | I57: 0.0054 | J57: 0.03 | K57: 0.024 | L57: Sim
A58: Creme De Leite UHT 25% | B58: 24 | C58: 0 | D58: 0.25 | E58: 0.06 | F58: 0 | G58: 0.31 | H58: 0.69 | I58: 0.0054 | J58: 0.03 | K58: 0.024 | L58: Sim
A59: Croissant | B59: {=IFERROR(SUMPRODUCT(('Pré-preparos e Variegatos'!$A$2:$A$1000=$A59)*'Pré-preparos e Variegatos'!$C$2:$C$1000*IFERROR(VLOOKUP('Pré-preparos e Variegatos'!$B$2:$B$1000, VSTACK($A$5:$K$23, $A$28:$K$31, $A$33:$K$58, $A$60:$K$96, $A$99:$K$137, $A$139:$K$140, $A$142:$K$151, $A$153:$K$168, $A$170:$K$188, $A$194:$K$500), 2, 0), 0))/SUMIF('Pré-preparos e Variegatos'!$A$2:$A$1000, $A59, 'Pré-preparos e Variegatos'!$C$2:$C$1000) * IFERROR(VLOOKUP($A59, 'Pré-preparos e Variegatos'!$M$2:$Q$100, 5, FALSE), 1), 0)} -> 16.068645 | C59: {=IFERROR(SUMPRODUCT(('Pré-preparos e Variegatos'!$A$2:$A$1000=$A59)*'Pré-preparos e Variegatos'!$C$2:$C$1000*IFERROR(VLOOKUP('Pré-preparos e Variegatos'!$B$2:$B$1000, VSTACK($A$5:$K$23, $A$28:$K$31, $A$33:$K$58, $A$60:$K$96, $A$99:$K$137, $A$139:$K$140, $A$142:$K$151, $A$153:$K$168, $A$170:$K$188, $A$194:$K$500), 3, 0), 0))/SUMIF('Pré-preparos e Variegatos'!$A$2:$A$1000, $A59, 'Pré-preparos e Variegatos'!$C$2:$C$1000) * IFERROR(VLOOKUP($A59, 'Pré-preparos e Variegatos'!$M$2:$Q$100, 5, FALSE), 1), 0)} -> 0.037470024 | D59: {=IFERROR(SUMPRODUCT(('Pré-preparos e Variegatos'!$A$2:$A$1000=$A59)*'Pré-preparos e Variegatos'!$C$2:$C$1000*IFERROR(VLOOKUP('Pré-preparos e Variegatos'!$B$2:$B$1000, VSTACK($A$5:$K$23, $A$28:$K$31, $A$33:$K$58, $A$60:$K$96, $A$99:$K$137, $A$139:$K$140, $A$142:$K$151, $A$153:$K$168, $A$170:$K$188, $A$194:$K$500), 4, 0), 0))/SUMIF('Pré-preparos e Variegatos'!$A$2:$A$1000, $A59, 'Pré-preparos e Variegatos'!$C$2:$C$1000) * IFERROR(VLOOKUP($A59, 'Pré-preparos e Variegatos'!$M$2:$Q$100, 5, FALSE), 1), 0)} -> 0.16393135 | E59: {=IFERROR(SUMPRODUCT(('Pré-preparos e Variegatos'!$A$2:$A$1000=$A59)*'Pré-preparos e Variegatos'!$C$2:$C$1000*IFERROR(VLOOKUP('Pré-preparos e Variegatos'!$B$2:$B$1000, VSTACK($A$5:$K$23, $A$28:$K$31, $A$33:$K$58, $A$60:$K$96, $A$99:$K$137, $A$139:$K$140, $A$142:$K$151, $A$153:$K$168, $A$170:$K$188, $A$194:$K$500), 5, 0), 0))/SUMIF('Pré-preparos e Variegatos'!$A$2:$A$1000, $A59, 'Pré-preparos e Variegatos'!$C$2:$C$1000) * IFERROR(VLOOKUP($A59, 'Pré-preparos e Variegatos'!$M$2:$Q$100, 5, FALSE), 1), 0)} -> 0.020608513 | F59: {=IFERROR(SUMPRODUCT(('Pré-preparos e Variegatos'!$A$2:$A$1000=$A59)*'Pré-preparos e Variegatos'!$C$2:$C$1000*IFERROR(VLOOKUP('Pré-preparos e Variegatos'!$B$2:$B$1000, VSTACK($A$5:$K$23, $A$28:$K$31, $A$33:$K$58, $A$60:$K$96, $A$99:$K$137, $A$139:$K$140, $A$142:$K$151, $A$153:$K$168, $A$170:$K$188, $A$194:$K$500), 6, 0), 0))/SUMIF('Pré-preparos e Variegatos'!$A$2:$A$1000, $A59, 'Pré-preparos e Variegatos'!$C$2:$C$1000) * IFERROR(VLOOKUP($A59, 'Pré-preparos e Variegatos'!$M$2:$Q$100, 5, FALSE), 1), 0)} -> 0.38931355 | G59: =MIN(1, SUM(C59:F59)) -> 0.61132344 | H59: =1-G59 -> 0.38867656 | I59: {=IFERROR(SUMPRODUCT(('Pré-preparos e Variegatos'!$A$2:$A$1000=$A59)*'Pré-preparos e Variegatos'!$C$2:$C$1000*IFERROR(VLOOKUP('Pré-preparos e Variegatos'!$B$2:$B$1000, VSTACK($A$5:$K$23, $A$28:$K$31, $A$33:$K$58, $A$60:$K$96, $A$99:$K$137, $A$139:$K$140, $A$142:$K$151, $A$153:$K$168, $A$170:$K$188, $A$194:$K$500), 9, 0), 0))/SUMIF('Pré-preparos e Variegatos'!$A$2:$A$1000, $A59, 'Pré-preparos e Variegatos'!$C$2:$C$1000) * IFERROR(VLOOKUP($A59, 'Pré-preparos e Variegatos'!$M$2:$Q$100, 5, FALSE), 1), 0)} -> 0.038931355 | J59: {=IFERROR(SUMPRODUCT(('Pré-preparos e Variegatos'!$A$2:$A$1000=$A59)*'Pré-preparos e Variegatos'!$C$2:$C$1000*IFERROR(VLOOKUP('Pré-preparos e Variegatos'!$B$2:$B$1000, VSTACK($A$5:$K$23, $A$28:$K$31, $A$33:$K$58, $A$60:$K$96, $A$99:$K$137, $A$139:$K$140, $A$142:$K$151, $A$153:$K$168, $A$170:$K$188, $A$194:$K$500), 10, 0), 0))/SUMIF('Pré-preparos e Variegatos'!$A$2:$A$1000, $A59, 'Pré-preparos e Variegatos'!$C$2:$C$1000) * IFERROR(VLOOKUP($A59, 'Pré-preparos e Variegatos'!$M$2:$Q$100, 5, FALSE), 1), 0)} -> 0.071942446 | K59: {=IFERROR(SUMPRODUCT(('Pré-preparos e Variegatos'!$A$2:$A$1000=$A59)*'Pré-preparos e Variegatos'!$C$2:$C$1000*IFERROR(VLOOKUP('Pré-preparos e Variegatos'!$B$2:$B$1000, VSTACK($A$5:$K$23, $A$28:$K$31, $A$33:$K$58, $A$60:$K$96, $A$99:$K$137, $A$139:$K$140, $A$142:$K$151, $A$153:$K$168, $A$170:$K$188, $A$194:$K$500), 11, 0), 0))/SUMIF('Pré-preparos e Variegatos'!$A$2:$A$1000, $A59, 'Pré-preparos e Variegatos'!$C$2:$C$1000) * IFERROR(VLOOKUP($A59, 'Pré-preparos e Variegatos'!$M$2:$Q$100, 5, FALSE), 1), 0)} -> 0.032786271 | L59: {=IF(SUMPRODUCT(('Pré-preparos e Variegatos'!$A$2:$A$1000=$A59)*(IFERROR(VLOOKUP('Pré-preparos e Variegatos'!$B$2:$B$1000, VSTACK($A$5:$L$23, $A$28:$L$31, $A$33:$L$58, $A$60:$L$96, $A$99:$L$137, $A$139:$L$140, $A$142:$L$151, $A$153:$L$168, $A$170:$L$188, $A$194:$L$500), 12, 0), "Não")="Sim"))>0, "Sim", "Não")} -> Sim
A60: Damasco | B60: 0 | C60: 0.125 | D60: 0.001 | E60: 0 | F60: 0.025 | G60: 0.151 | H60: 0.849 | I60: 0.15 | J60: 0.18 | K60: 0.009 | L60: Não
A61: Doce De Leite - Lata | B61: 48 | C61: 0.49 | D61: 0.06 | E61: 0.135 | F61: 0 | G61: =0.69 -> 0.69 | H61: 0.31 | I61: 0.47 | J61: 0.649 | K61: 0.086 | L61: Sim
A62: Doce de leite Rocca | B62: 43 | C62: 0.28 | D62: 0.11 | E62: 0.185 | F62: 0 | G62: =SUM(C62:F62) -> 0.575 | H62: =1-G62 -> 0.425 | I62: 0.31 | J62: 0.37 | K62: 0.075 | L62: Sim
A63: DPO 165 Premium - Aroma Italia | B63: 97.5 | C63: 0.4 | D63: 0.2 | E63: 0.32 | F63: 0.05 | G63: =SUM(C63:F63) -> 0.97 | H63: =1-G63 -> 0.03 | I63: 0.4 | J63: 0.68 | K63: 0.115 | L63: Sim
A64: Eritritol | B64: 30 | C64: 1 | D64: 0 | E64: 0 | F64: 0 | G64: 1 | H64: 0 | I64: 0.7 | J64: 2.8 | K64: 0 | L64: Não
A65: Ervilha cozida | B65: 0 | C65: 0.034 | D65: 0.005 | E65: 0 | F65: 0.27 | G65: 0.31 | H65: 0.69 | I65: 0 | J65: 0 | K65: 0.0662 | L65: Não
A66: Ervilha(seca) | B66: 0 | C66: 0.08 | D66: 0.012 | E66: 0 | F66: 0.77 | G66: =SUM(C66:F66) -> 0.862 | H66: =1-G66 -> 0.138 | I66: 0 | J66: =0.08*1.9 -> 0.152 | K66: 0.2455 | L66: Não
A67: Extrato De Baunilha | B67: 0 | C67: 0.127 | D67: 0.0006 | E67: 0 | F67: 0.342 | G67: 0.4696 | H67: 0.53 | I67: 0.18 | J67: 0.15 | K67: 0.0006 | L67: Não
A68: Farinha De Semente De Alfarroba | B68: 0 | C68: 0 | D68: 0 | E68: 0 | F68: 1 | G68: 1 | H68: 0 | I68: 0 | J68: 3 | K68: 0 | L68: Não
A69: Farinha De Semente De Guar | B69: 0 | C69: 0 | D69: 0 | E69: 0 | F69: 1 | G69: 1 | H69: 0 | I69: 0 | J69: 3 | K69: 0 | L69: Não
A70: Farinha De Semente De Tara | B70: 0 | C70: 0 | D70: 0 | E70: 0 | F70: 1 | G70: 1 | H70: 0 | I70: 0 | J70: 3 | K70: 0 | L70: Não
A71: Farinha de trigo | B71: 6 | C71: 0 | D71: 0 | E71: 0 | F71: 1 | G71: 1 | H71: 0 | I71: 0 | J71: 0 | K71: 0.05 | L71: Sim
A72: Fava De Baunilha | B72: 10000 | C72: 0.127 | D72: 0.0006 | E72: 0 | F72: 0.59 | G72: 0.7176 | H72: 0.282 | I72: 0 | J72: 0 | K72: 0.0006 | L72: Não
A73: Figo | B73: 0 | C73: 0.11 | D73: 0 | E73: 0 | F73: 0.07 | G73: 0.18 | H73: 0.82 | I73: 0.18 | J73: 0.22 | K73: 0.01 | L73: Não
A74: Framboesa | B74: 0 | C74: 0.07 | D74: 0.01 | E74: 0 | F74: 0.08 | G74: 0.16 | H74: 0.84 | I74: 0.085 | J74: 0.105 | K74: 0.01 | L74: Não
A75: Fruta Groselha | B75: 0 | C75: 0.07 | D75: 0 | E75: 0 | F75: 0.16 | G75: 0.23 | H75: 0.77 | I75: 0.09 | J75: 0.11 | K75: 0.01 | L75: Não
A76: Fruta Nativa Araçá | B76: 0 | C76: 0.09 | D76: 0.01 | E76: 0 | F76: 0.143 | G76: =SUM(C76:F76) -> 0.243 | H76: =1-G76 -> 0.757 | I76: 0.126 | J76: 0.171 | K76: 0.01 | L76: Não
A77: Fruta Nativa Bergamota | B77: 0 | C77: 0.11 | D77: 0.01 | E77: 0 | F77: 0.03 | G77: 0.15 | H77: 0.85 | I77: 0.154 | J77: 0.209 | K77: 0.008 | L77: Não
A78: Fruta Nativa Butiá | B78: 0 | C78: 0.118 | D78: 0.02 | E78: 0 | F78: 0.094 | G78: =SUM(C78:F78) -> 0.232 | H78: =1-G78 -> 0.768 | I78: 0.1652 | J78: 0.2242 | K78: 0.0085 | L78: Não
A79: Fruta Nativa Guabiroba | B79: 0 | C79: 0.11 | D79: 0.01 | E79: 0 | F79: 0.054 | G79: 0.174 | H79: 0.826 | I79: 0.154 | J79: 0.209 | K79: 0.0061 | L79: Não
A80: Frutas Vermelhas | B80: 0 | C80: 0.07 | D80: 0 | E80: 0 | F80: 0.04 | G80: 0.11 | H80: 0.89 | I80: 0.08 | J80: 0.1 | K80: 0.01 | L80: Não
A81: Gema Do Ovo | B81: 25 | C81: 0 | D81: 0.32 | E81: 0 | F81: 0.18 | G81: 0.5 | H81: 0.5 | I81: 0 | J81: 0 | K81: 0.16 | L81: Sim
A82: Gema Do Ovo Pasteurizada | B82: 0 | C82: 0.01 | D82: 0.28 | E82: 0 | F82: 0.16 | G82: 0.45 | H82: 0.55 | I82: 0 | J82: 0.01 | K82: 0.16 | L82: Sim
A83: Goiaba | B83: 0 | C83: 0.04 | D83: 0.01 | E83: 0 | F83: 0.09 | G83: 0.14 | H83: 0.86 | I83: 0.09 | J83: 0.07 | K83: 0.01 | L83: Não
A84: Goiabada | B84: 15 | C84: 0.825 | D84: 0 | E84: 0 | F84: 0.12 | G84: =F84+C84 -> 0.945 | H84: 0.055 | I84: 0.925 | J84: 1.005 | K84: 0.008 | L84: Não
A85: Goma Xantana | B85: 0 | C85: 0 | D85: 0 | E85: 0 | F85: 1 | G85: 1 | H85: 0 | I85: 0 | J85: 3 | K85: 0 | L85: Não
A86: Hortelã | B86: 0 | C86: 0.002 | D86: 0 | E86: 0 | F86: 0.105 | G86: 0.107 | H86: 0.893 | I86: 0 | J86: 0 | K86: 0.033 | L86: Não
A87: IMO 900 + Taumatina (moonsugar) | B87: 56 | C87: 1 | D87: 0 | E87: 0 | F87: 0 | G87: 1 | H87: 0 | I87: 0.8 | J87: 0.8 | K87: 0 | L87: Não
A88: Inulina - Fibra Vegetal | B88: 95 | C88: 0 | D88: 0 | E88: 0 | F88: 0.95 | G88: 0.95 | H88: 0.05 | I88: 0 | J88: 0.2 | K88: 0 | L88: Não
A89: Iogurte Desnatado | B89: 0 | C89: 0 | D89: 0.009 | E89: 0.092 | F89: 0 | G89: 0.101 | H89: 0.899 | I89: 0.007 | J89: 0.045 | K89: 0.047 | L89: Sim
A90: Iogurte Grego | B90: 0 | C90: 0 | D90: 0.04 | E90: 0.21 | F90: 0 | G90: 0.25 | H90: 0.75 | I90: 0 | J90: 0.08 | K90: 0.052 | L90: Sim
A91: Iogurte Integral | B91: 0 | C91: 0 | D91: 0.039 | E91: 0.095 | F91: 0 | G91: 0.134 | H91: 0.866 | I91: 0.0072 | J91: 0.045 | K91: 0.047 | L91: Sim
A92: Iogurte semidesnatado | B92: 0 | C92: 0 | D92: 0.017 | E92: 0.092 | F92: 0 | G92: 0.109 | H92: 0.891 | I92: 0.007 | J92: 0.045 | K92: 0.047 | L92: Sim
A93: Kiwi | B93: 0 | C93: 0.09 | D93: 0.01 | E93: 0 | F93: 0.06 | G93: 0.16 | H93: 0.84 | I93: 0.09 | J93: 0.11 | K93: 0.01 | L93: Não
A94: Laranja Suco | B94: 0 | C94: 0.08 | D94: 0 | E94: 0 | F94: 0.03 | G94: 0.11 | H94: 0.89 | I94: 0.12 | J94: 0.14 | K94: 0.01 | L94: Não
A95: Leite Condensado | B95: 20.25 | C95: 0.44 | D95: 0.08 | E95: =0.11+0.072 -> 0.182 | F95: 0.018 | G95: =SUM(C95:F95) -> 0.72 | H95: =1-G95 -> 0.28 | I95: 0.43 | J95: 0.55 | K95: 0.08 | L95: Sim
A96: Leite Condensado Desnatado | B96: 0 | C96: 0 | D96: 0 | E96: 0.6 | F96: 0 | G96: 0.6 | H96: 0.4 | I96: 0.083 | J96: 0.52 | K96: 0.08 | L96: Sim
A97: Leite condensado Vegetal | B97: {=IFERROR(SUMPRODUCT(('Pré-preparos e Variegatos'!$A$2:$A$1000=$A97)*'Pré-preparos e Variegatos'!$C$2:$C$1000*IFERROR(VLOOKUP('Pré-preparos e Variegatos'!$B$2:$B$1000, VSTACK($A$5:$K$23, $A$28:$K$31, $A$33:$K$58, $A$60:$K$96, $A$99:$K$137, $A$139:$K$140, $A$142:$K$151, $A$153:$K$168, $A$170:$K$188, $A$194:$K$500), 2, 0), 0))/SUMIF('Pré-preparos e Variegatos'!$A$2:$A$1000, $A97, 'Pré-preparos e Variegatos'!$C$2:$C$1000) * IFERROR(VLOOKUP($A97, 'Pré-preparos e Variegatos'!$M$2:$Q$100, 5, FALSE), 1), 0)} -> 1.8133333 | C97: {=IFERROR(SUMPRODUCT(('Pré-preparos e Variegatos'!$A$2:$A$1000=$A97)*'Pré-preparos e Variegatos'!$C$2:$C$1000*IFERROR(VLOOKUP('Pré-preparos e Variegatos'!$B$2:$B$1000, VSTACK($A$5:$K$23, $A$28:$K$31, $A$33:$K$58, $A$60:$K$96, $A$99:$K$137, $A$139:$K$140, $A$142:$K$151, $A$153:$K$168, $A$170:$K$188, $A$194:$K$500), 3, 0), 0))/SUMIF('Pré-preparos e Variegatos'!$A$2:$A$1000, $A97, 'Pré-preparos e Variegatos'!$C$2:$C$1000) * IFERROR(VLOOKUP($A97, 'Pré-preparos e Variegatos'!$M$2:$Q$100, 5, FALSE), 1), 0)} -> 0.46693333 | D97: {=IFERROR(SUMPRODUCT(('Pré-preparos e Variegatos'!$A$2:$A$1000=$A97)*'Pré-preparos e Variegatos'!$C$2:$C$1000*IFERROR(VLOOKUP('Pré-preparos e Variegatos'!$B$2:$B$1000, VSTACK($A$5:$K$23, $A$28:$K$31, $A$33:$K$58, $A$60:$K$96, $A$99:$K$137, $A$139:$K$140, $A$142:$K$151, $A$153:$K$168, $A$170:$K$188, $A$194:$K$500), 4, 0), 0))/SUMIF('Pré-preparos e Variegatos'!$A$2:$A$1000, $A97, 'Pré-preparos e Variegatos'!$C$2:$C$1000) * IFERROR(VLOOKUP($A97, 'Pré-preparos e Variegatos'!$M$2:$Q$100, 5, FALSE), 1), 0)} -> 0.15306667 | E97: {=IFERROR(SUMPRODUCT(('Pré-preparos e Variegatos'!$A$2:$A$1000=$A97)*'Pré-preparos e Variegatos'!$C$2:$C$1000*IFERROR(VLOOKUP('Pré-preparos e Variegatos'!$B$2:$B$1000, VSTACK($A$5:$K$23, $A$28:$K$31, $A$33:$K$58, $A$60:$K$96, $A$99:$K$137, $A$139:$K$140, $A$142:$K$151, $A$153:$K$168, $A$170:$K$188, $A$194:$K$500), 5, 0), 0))/SUMIF('Pré-preparos e Variegatos'!$A$2:$A$1000, $A97, 'Pré-preparos e Variegatos'!$C$2:$C$1000) * IFERROR(VLOOKUP($A97, 'Pré-preparos e Variegatos'!$M$2:$Q$100, 5, FALSE), 1), 0)} -> 0 | F97: {=IFERROR(SUMPRODUCT(('Pré-preparos e Variegatos'!$A$2:$A$1000=$A97)*'Pré-preparos e Variegatos'!$C$2:$C$1000*IFERROR(VLOOKUP('Pré-preparos e Variegatos'!$B$2:$B$1000, VSTACK($A$5:$K$23, $A$28:$K$31, $A$33:$K$58, $A$60:$K$96, $A$99:$K$137, $A$139:$K$140, $A$142:$K$151, $A$153:$K$168, $A$170:$K$188, $A$194:$K$500), 6, 0), 0))/SUMIF('Pré-preparos e Variegatos'!$A$2:$A$1000, $A97, 'Pré-preparos e Variegatos'!$C$2:$C$1000) * IFERROR(VLOOKUP($A97, 'Pré-preparos e Variegatos'!$M$2:$Q$100, 5, FALSE), 1), 0)} -> 0.0952 | G97: =MIN(1, SUM(C97:F97)) -> 0.7152 | H97: =1-G97 -> 0.2848 | I97: {=IFERROR(SUMPRODUCT(('Pré-preparos e Variegatos'!$A$2:$A$1000=$A97)*'Pré-preparos e Variegatos'!$C$2:$C$1000*IFERROR(VLOOKUP('Pré-preparos e Variegatos'!$B$2:$B$1000, VSTACK($A$5:$K$23, $A$28:$K$31, $A$33:$K$58, $A$60:$K$96, $A$99:$K$137, $A$139:$K$140, $A$142:$K$151, $A$153:$K$168, $A$170:$K$188, $A$194:$K$500), 9, 0), 0))/SUMIF('Pré-preparos e Variegatos'!$A$2:$A$1000, $A97, 'Pré-preparos e Variegatos'!$C$2:$C$1000) * IFERROR(VLOOKUP($A97, 'Pré-preparos e Variegatos'!$M$2:$Q$100, 5, FALSE), 1), 0)} -> 0.45333333 | J97: {=IFERROR(SUMPRODUCT(('Pré-preparos e Variegatos'!$A$2:$A$1000=$A97)*'Pré-preparos e Variegatos'!$C$2:$C$1000*IFERROR(VLOOKUP('Pré-preparos e Variegatos'!$B$2:$B$1000, VSTACK($A$5:$K$23, $A$28:$K$31, $A$33:$K$58, $A$60:$K$96, $A$99:$K$137, $A$139:$K$140, $A$142:$K$151, $A$153:$K$168, $A$170:$K$188, $A$194:$K$500), 10, 0), 0))/SUMIF('Pré-preparos e Variegatos'!$A$2:$A$1000, $A97, 'Pré-preparos e Variegatos'!$C$2:$C$1000) * IFERROR(VLOOKUP($A97, 'Pré-preparos e Variegatos'!$M$2:$Q$100, 5, FALSE), 1), 0)} -> 0.45333333 | K97: {=IFERROR(SUMPRODUCT(('Pré-preparos e Variegatos'!$A$2:$A$1000=$A97)*'Pré-preparos e Variegatos'!$C$2:$C$1000*IFERROR(VLOOKUP('Pré-preparos e Variegatos'!$B$2:$B$1000, VSTACK($A$5:$K$23, $A$28:$K$31, $A$33:$K$58, $A$60:$K$96, $A$99:$K$137, $A$139:$K$140, $A$142:$K$151, $A$153:$K$168, $A$170:$K$188, $A$194:$K$500), 11, 0), 0))/SUMIF('Pré-preparos e Variegatos'!$A$2:$A$1000, $A97, 'Pré-preparos e Variegatos'!$C$2:$C$1000) * IFERROR(VLOOKUP($A97, 'Pré-preparos e Variegatos'!$M$2:$Q$100, 5, FALSE), 1), 0)} -> 0.0408 | L97: {=IF(SUMPRODUCT(('Pré-preparos e Variegatos'!$A$2:$A$1000=$A97)*(IFERROR(VLOOKUP('Pré-preparos e Variegatos'!$B$2:$B$1000, VSTACK($A$5:$L$23, $A$28:$L$31, $A$33:$L$58, $A$60:$L$96, $A$99:$L$137, $A$139:$L$140, $A$142:$L$151, $A$153:$L$168, $A$170:$L$188, $A$194:$L$500), 12, 0), "Não")="Sim"))>0, "Sim", "Não")} -> Sim
A98: Leite de castanha | B98: {=IFERROR(SUMPRODUCT(('Pré-preparos e Variegatos'!$A$2:$A$1000=$A98)*'Pré-preparos e Variegatos'!$C$2:$C$1000*IFERROR(VLOOKUP('Pré-preparos e Variegatos'!$B$2:$B$1000, VSTACK($A$5:$K$23, $A$28:$K$31, $A$33:$K$58, $A$60:$K$96, $A$99:$K$137, $A$139:$K$140, $A$142:$K$151, $A$153:$K$168, $A$170:$K$188, $A$194:$K$500), 2, 0), 0))/SUMIF('Pré-preparos e Variegatos'!$A$2:$A$1000, $A98, 'Pré-preparos e Variegatos'!$C$2:$C$1000) * IFERROR(VLOOKUP($A98, 'Pré-preparos e Variegatos'!$M$2:$Q$100, 5, FALSE), 1), 0)} -> 0 | C98: {=IFERROR(SUMPRODUCT(('Pré-preparos e Variegatos'!$A$2:$A$1000=$A98)*'Pré-preparos e Variegatos'!$C$2:$C$1000*IFERROR(VLOOKUP('Pré-preparos e Variegatos'!$B$2:$B$1000, VSTACK($A$5:$K$23, $A$28:$K$31, $A$33:$K$58, $A$60:$K$96, $A$99:$K$137, $A$139:$K$140, $A$142:$K$151, $A$153:$K$168, $A$170:$K$188, $A$194:$K$500), 3, 0), 0))/SUMIF('Pré-preparos e Variegatos'!$A$2:$A$1000, $A98, 'Pré-preparos e Variegatos'!$C$2:$C$1000) * IFERROR(VLOOKUP($A98, 'Pré-preparos e Variegatos'!$M$2:$Q$100, 5, FALSE), 1), 0)} -> 0.01009901 | D98: {=IFERROR(SUMPRODUCT(('Pré-preparos e Variegatos'!$A$2:$A$1000=$A98)*'Pré-preparos e Variegatos'!$C$2:$C$1000*IFERROR(VLOOKUP('Pré-preparos e Variegatos'!$B$2:$B$1000, VSTACK($A$5:$K$23, $A$28:$K$31, $A$33:$K$58, $A$60:$K$96, $A$99:$K$137, $A$139:$K$140, $A$142:$K$151, $A$153:$K$168, $A$170:$K$188, $A$194:$K$500), 4, 0), 0))/SUMIF('Pré-preparos e Variegatos'!$A$2:$A$1000, $A98, 'Pré-preparos e Variegatos'!$C$2:$C$1000) * IFERROR(VLOOKUP($A98, 'Pré-preparos e Variegatos'!$M$2:$Q$100, 5, FALSE), 1), 0)} -> 0.074059406 | E98: {=IFERROR(SUMPRODUCT(('Pré-preparos e Variegatos'!$A$2:$A$1000=$A98)*'Pré-preparos e Variegatos'!$C$2:$C$1000*IFERROR(VLOOKUP('Pré-preparos e Variegatos'!$B$2:$B$1000, VSTACK($A$5:$K$23, $A$28:$K$31, $A$33:$K$58, $A$60:$K$96, $A$99:$K$137, $A$139:$K$140, $A$142:$K$151, $A$153:$K$168, $A$170:$K$188, $A$194:$K$500), 5, 0), 0))/SUMIF('Pré-preparos e Variegatos'!$A$2:$A$1000, $A98, 'Pré-preparos e Variegatos'!$C$2:$C$1000) * IFERROR(VLOOKUP($A98, 'Pré-preparos e Variegatos'!$M$2:$Q$100, 5, FALSE), 1), 0)} -> 0 | F98: {=IFERROR(SUMPRODUCT(('Pré-preparos e Variegatos'!$A$2:$A$1000=$A98)*'Pré-preparos e Variegatos'!$C$2:$C$1000*IFERROR(VLOOKUP('Pré-preparos e Variegatos'!$B$2:$B$1000, VSTACK($A$5:$K$23, $A$28:$K$31, $A$33:$K$58, $A$60:$K$96, $A$99:$K$137, $A$139:$K$140, $A$142:$K$151, $A$153:$K$168, $A$170:$K$188, $A$194:$K$500), 6, 0), 0))/SUMIF('Pré-preparos e Variegatos'!$A$2:$A$1000, $A98, 'Pré-preparos e Variegatos'!$C$2:$C$1000) * IFERROR(VLOOKUP($A98, 'Pré-preparos e Variegatos'!$M$2:$Q$100, 5, FALSE), 1), 0)} -> 0.070693069 | G98: =MIN(1, SUM(C98:F98)) -> 0.15485149 | H98: =1-G98 -> 0.84514851 | I98: {=IFERROR(SUMPRODUCT(('Pré-preparos e Variegatos'!$A$2:$A$1000=$A98)*'Pré-preparos e Variegatos'!$C$2:$C$1000*IFERROR(VLOOKUP('Pré-preparos e Variegatos'!$B$2:$B$1000, VSTACK($A$5:$K$23, $A$28:$K$31, $A$33:$K$58, $A$60:$K$96, $A$99:$K$137, $A$139:$K$140, $A$142:$K$151, $A$153:$K$168, $A$170:$K$188, $A$194:$K$500), 9, 0), 0))/SUMIF('Pré-preparos e Variegatos'!$A$2:$A$1000, $A98, 'Pré-preparos e Variegatos'!$C$2:$C$1000) * IFERROR(VLOOKUP($A98, 'Pré-preparos e Variegatos'!$M$2:$Q$100, 5, FALSE), 1), 0)} -> 0 | J98: {=IFERROR(SUMPRODUCT(('Pré-preparos e Variegatos'!$A$2:$A$1000=$A98)*'Pré-preparos e Variegatos'!$C$2:$C$1000*IFERROR(VLOOKUP('Pré-preparos e Variegatos'!$B$2:$B$1000, VSTACK($A$5:$K$23, $A$28:$K$31, $A$33:$K$58, $A$60:$K$96, $A$99:$K$137, $A$139:$K$140, $A$142:$K$151, $A$153:$K$168, $A$170:$K$188, $A$194:$K$500), 10, 0), 0))/SUMIF('Pré-preparos e Variegatos'!$A$2:$A$1000, $A98, 'Pré-preparos e Variegatos'!$C$2:$C$1000) * IFERROR(VLOOKUP($A98, 'Pré-preparos e Variegatos'!$M$2:$Q$100, 5, FALSE), 1), 0)} -> 0 | K98: {=IFERROR(SUMPRODUCT(('Pré-preparos e Variegatos'!$A$2:$A$1000=$A98)*'Pré-preparos e Variegatos'!$C$2:$C$1000*IFERROR(VLOOKUP('Pré-preparos e Variegatos'!$B$2:$B$1000, VSTACK($A$5:$K$23, $A$28:$K$31, $A$33:$K$58, $A$60:$K$96, $A$99:$K$137, $A$139:$K$140, $A$142:$K$151, $A$153:$K$168, $A$170:$K$188, $A$194:$K$500), 11, 0), 0))/SUMIF('Pré-preparos e Variegatos'!$A$2:$A$1000, $A98, 'Pré-preparos e Variegatos'!$C$2:$C$1000) * IFERROR(VLOOKUP($A98, 'Pré-preparos e Variegatos'!$M$2:$Q$100, 5, FALSE), 1), 0)} -> 0.03029703 | L98: {=IF(SUMPRODUCT(('Pré-preparos e Variegatos'!$A$2:$A$1000=$A98)*(IFERROR(VLOOKUP('Pré-preparos e Variegatos'!$B$2:$B$1000, VSTACK($A$5:$L$23, $A$28:$L$31, $A$33:$L$58, $A$60:$L$96, $A$99:$L$137, $A$139:$L$140, $A$142:$L$151, $A$153:$L$168, $A$170:$L$188, $A$194:$L$500), 12, 0), "Não")="Sim"))>0, "Sim", "Não")} -> Sim
A99: Leite de Coco | B99: 0 | C99: 0.084 | D99: 0.05 | E99: 0 | F99: 0.035 | G99: =SUM(C99:F99) -> 0.169 | H99: =1-G99 -> 0.831 | I99: 0.13 | J99: 0.084 | K99: 0 | L99: Não
A100: Leite de coco em pó - IO | B100: 120 | C100: 0.44 | D100: 0.07 | E100: 0 | F100: 0.44 | G100: 0.95 | H100: 0.05 | I100: 0 | J100: 0.044 | K100: 0.04 | L100: Não
A101: Leite de Coco Sococo | B101: 15 | C101: 0.02 | D101: 0.2 | E101: 0 | F101: 0.005 | G101: =SUM(C101:F101) -> 0.225 | H101: =1-G101 -> 0.775 | I101: 0 | J101: 0.02 | K101: 0 | L101: Não
A102: Leite Desnatado | B102: 0 | C102: 0 | D102: 0 | E102: 0.09 | F102: 0 | G102: 0.09 | H102: 0.91 | I102: 0.007 | J102: 0.045 | K102: 0.035 | L102: Sim
A103: Leite Em Pó Desnatado | B103: 54 | C103: 0 | D103: 0 | E103: 0.97 | F103: 0 | G103: 0.97 | H103: 0.03 | I103: 0.08 | J103: 0.5 | K103: 0.36 | L103: Sim
A104: Leite Em Pó Integral | B104: 42 | C104: 0 | D104: 0.26 | E104: 0.72 | F104: 0 | G104: 0.98 | H104: 0.02 | I104: 0.061 | J104: 0.39 | K104: 0.28 | L104: Sim
A105: Leite Integral | B105: 4.6 | C105: 0 | D105: 0.035 | E105: 0.09 | F105: 0 | G105: 0.125 | H105: 0.875 | I105: 0.0078 | J105: 0.04 | K105: 0.035 | L105: Sim
A106: Leite Semidesnatado | B106: 0 | C106: 0 | D106: 0.015 | E106: 0.09 | F106: 0 | G106: 0.105 | H106: 0.895 | I106: 0.007 | J106: 0.045 | K106: 0.035 | L106: Sim
A107: Lichia | B107: 0 | C107: 0.17 | D107: 0 | E107: 0 | F107: 0.02 | G107: 0.19 | H107: 0.81 | I107: 0.14 | J107: 0.18 | K107: 0.01 | L107: Não
A108: Licor Amaretto | B108: 100 | C108: 0.2 | D108: 0 | E108: 0 | F108: 0 | G108: 0.2 | H108: 0.8 | I108: 0.2 | J108: 1.88 | K108: 0 | L108: Sim
A109: Lima Limão Taiti | B109: 0 | C109: 0.04 | D109: 0 | E109: 0 | F109: 0.045 | G109: 0.085 | H109: 0.915 | I109: 0.048 | J109: 0.058 | K109: 0 | L109: Não
A110: Limão Siciliano | B110: 19 | C110: 0.02 | D110: 0 | E110: 0 | F110: 0.06 | G110: 0.08 | H110: 0.92 | I110: 0.05 | J110: 0.06 | K110: 0 | L110: Não
A111: Limão Suco | B111: 13 | C111: 0.0252 | D111: 0.0024 | E111: 0 | F111: 0.05 | G111: 0.0776 | H111: 0.922 | I111: 0.03 | J111: 0.036 | K111: 0.003 | L111: Não
...

Sheet Catálogo Geral
A1: PAINEL GERENCIAL E CATÁLOGO DE RECEITAS DE GELATO
A2: Categoria (Aba Receitas) | B2: Total Receitas | C2: Status Ok | D2: Status Revisar | E2: % Conformidade | F2: Peso ≠ 1.000 g | G2: Custo Médio/Kg (R$) | H2: Menor Custo/Kg (R$) | I2: Maior Custo/Kg (R$) | J2: Preço Médio Pote 500g (R$)
A3: Gelatos de Leite | B3: =COUNTIF($B$14:$B$500, A3) -> 60 | C3: =COUNTIFS($B$14:$B$500, A3, $S$14:$S$500, "Ok") -> 31 | D3: =COUNTIFS($B$14:$B$500, A3, $S$14:$S$500, "Revisar") -> 29 | E3: =IFERROR(C3/B3, 0) -> 0.51666667 | F3: =COUNTIFS($B$14:$B$500, A3, $E$14:$E$500, "<>1.000 g (Padrão)") -> 52 | G3: =IFERROR(AVERAGEIF($B$14:$B$500, A3, $F$14:$F$500), 0) -> 20.881075 | H3: =IFERROR(MINIFS($F$14:$F$500, $B$14:$B$500, A3, $F$14:$F$500, ">0"), 0) -> 8.8261682 | I3: =IFERROR(MAXIFS($F$14:$F$500, $B$14:$B$500, A3), 0) -> 47.080042 | J3: =IFERROR(AVERAGEIF($B$14:$B$500, A3, $H$14:$H$500), 0) -> 39.636651
A4: Gelatos de Leite com Fruta | B4: =COUNTIF($B$14:$B$500, A4) -> 10 | C4: =COUNTIFS($B$14:$B$500, A4, $S$14:$S$500, "Ok") -> 2 | D4: =COUNTIFS($B$14:$B$500, A4, $S$14:$S$500, "Revisar") -> 8 | E4: =IFERROR(C4/B4, 0) -> 0.2 | F4: =COUNTIFS($B$14:$B$500, A4, $E$14:$E$500, "<>1.000 g (Padrão)") -> 9 | G4: =IFERROR(AVERAGEIF($B$14:$B$500, A4, $F$14:$F$500), 0) -> 14.629915 | H4: =IFERROR(MINIFS($F$14:$F$500, $B$14:$B$500, A4, $F$14:$F$500, ">0"), 0) -> 6.7196896 | I4: =IFERROR(MAXIFS($F$14:$F$500, $B$14:$B$500, A4), 0) -> 25.941849 | J4: =IFERROR(AVERAGEIF($B$14:$B$500, A4, $H$14:$H$500), 0) -> 34.46185
A5: Sorbets | B5: =COUNTIF($B$14:$B$500, A5) -> 26 | C5: =COUNTIFS($B$14:$B$500, A5, $S$14:$S$500, "Ok") -> 9 | D5: =COUNTIFS($B$14:$B$500, A5, $S$14:$S$500, "Revisar") -> 17 | E5: =IFERROR(C5/B5, 0) -> 0.34615385 | F5: =COUNTIFS($B$14:$B$500, A5, $E$14:$E$500, "<>1.000 g (Padrão)") -> 17 | G5: =IFERROR(AVERAGEIF($B$14:$B$500, A5, $F$14:$F$500), 0) -> 8.5329235 | H5: =IFERROR(MINIFS($F$14:$F$500, $B$14:$B$500, A5, $F$14:$F$500, ">0"), 0) -> 3.477534 | I5: =IFERROR(MAXIFS($F$14:$F$500, $B$14:$B$500, A5), 0) -> 28.195 | J5: =IFERROR(AVERAGEIF($B$14:$B$500, A5, $H$14:$H$500), 0) -> 29.414672
A6: Chocolate base água | B6: =COUNTIF($B$14:$B$500, A6) -> 3 | C6: =COUNTIFS($B$14:$B$500, A6, $S$14:$S$500, "Ok") -> 0 | D6: =COUNTIFS($B$14:$B$500, A6, $S$14:$S$500, "Revisar") -> 3 | E6: =IFERROR(C6/B6, 0) -> 0 | F6: =COUNTIFS($B$14:$B$500, A6, $E$14:$E$500, "<>1.000 g (Padrão)") -> 3 | G6: =IFERROR(AVERAGEIF($B$14:$B$500, A6, $F$14:$F$500), 0) -> 20.942898 | H6: =IFERROR(MINIFS($F$14:$F$500, $B$14:$B$500, A6, $F$14:$F$500, ">0"), 0) -> 2.9757576 | I6: =IFERROR(MAXIFS($F$14:$F$500, $B$14:$B$500, A6), 0) -> 38.935354 | J6: =IFERROR(AVERAGEIF($B$14:$B$500, A6, $H$14:$H$500), 0) -> 39.687829
A7: Vegano | B7: =COUNTIF($B$14:$B$500, A7) -> 9 | C7: =COUNTIFS($B$14:$B$500, A7, $S$14:$S$500, "Ok") -> 8 | D7: =COUNTIFS($B$14:$B$500, A7, $S$14:$S$500, "Revisar") -> 1 | E7: =IFERROR(C7/B7, 0) -> 0.88888889 | F7: =COUNTIFS($B$14:$B$500, A7, $E$14:$E$500, "<>1.000 g (Padrão)") -> 9 | G7: =IFERROR(AVERAGEIF($B$14:$B$500, A7, $F$14:$F$500), 0) -> 25.780519 | H7: =IFERROR(MINIFS($F$14:$F$500, $B$14:$B$500, A7, $F$14:$F$500, ">0"), 0) -> 7.8612774 | I7: =IFERROR(MAXIFS($F$14:$F$500, $B$14:$B$500, A7), 0) -> 43.030938 | J7: =IFERROR(AVERAGEIF($B$14:$B$500, A7, $H$14:$H$500), 0) -> 43.692483
A8: Alcoólicos | B8: =COUNTIF($B$14:$B$500, A8) -> 11 | C8: =COUNTIFS($B$14:$B$500, A8, $S$14:$S$500, "Ok") -> 4 | D8: =COUNTIFS($B$14:$B$500, A8, $S$14:$S$500, "Revisar") -> 7 | E8: =IFERROR(C8/B8, 0) -> 0.36363636 | F8: =COUNTIFS($B$14:$B$500, A8, $E$14:$E$500, "<>1.000 g (Padrão)") -> 7 | G8: =IFERROR(AVERAGEIF($B$14:$B$500, A8, $F$14:$F$500), 0) -> 21.827533 | H8: =IFERROR(MINIFS($F$14:$F$500, $B$14:$B$500, A8, $F$14:$F$500, ">0"), 0) -> 11.550304 | I8: =IFERROR(MAXIFS($F$14:$F$500, $B$14:$B$500, A8), 0) -> 59.029 | J8: =IFERROR(AVERAGEIF($B$14:$B$500, A8, $H$14:$H$500), 0) -> 40.420143
A9: Gelatos Proteicos | B9: =COUNTIF($B$14:$B$500, A9) -> 12 | C9: =COUNTIFS($B$14:$B$500, A9, $S$14:$S$500, "Ok") -> 8 | D9: =COUNTIFS($B$14:$B$500, A9, $S$14:$S$500, "Revisar") -> 4 | E9: =IFERROR(C9/B9, 0) -> 0.66666667 | F9: =COUNTIFS($B$14:$B$500, A9, $E$14:$E$500, "<>1.000 g (Padrão)") -> 11 | G9: =IFERROR(AVERAGEIF($B$14:$B$500, A9, $F$14:$F$500), 0) -> 27.929782 | H9: =IFERROR(MINIFS($F$14:$F$500, $B$14:$B$500, A9, $F$14:$F$500, ">0"), 0) -> 18.995584 | I9: =IFERROR(MAXIFS($F$14:$F$500, $B$14:$B$500, A9), 0) -> 45.105865 | J9: =IFERROR(AVERAGEIF($B$14:$B$500, A9, $H$14:$H$500), 0) -> 45.471674
A10: Zero | B10: =COUNTIF($B$14:$B$500, A10) -> 46 | C10: =COUNTIFS($B$14:$B$500, A10, $S$14:$S$500, "Ok") -> 34 | D10: =COUNTIFS($B$14:$B$500, A10, $S$14:$S$500, "Revisar") -> 12 | E10: =IFERROR(C10/B10, 0) -> 0.73913043 | F10: =COUNTIFS($B$14:$B$500, A10, $E$14:$E$500, "<>1.000 g (Padrão)") -> 36 | G10: =IFERROR(AVERAGEIF($B$14:$B$500, A10, $F$14:$F$500), 0) -> 19.40791 | H10: =IFERROR(MINIFS($F$14:$F$500, $B$14:$B$500, A10, $F$14:$F$500, ">0"), 0) -> 8.3033419 | I10: =IFERROR(MAXIFS($F$14:$F$500, $B$14:$B$500, A10), 0) -> 53.17012 | J10: =IFERROR(AVERAGEIF($B$14:$B$500, A10, $H$14:$H$500), 0) -> 38.417144
A11: Total / Média Geral | B11: =SUM(B3:B10) -> 177 | C11: =SUM(C3:C10) -> 96 | D11: =SUM(D3:D10) -> 81 | E11: =IFERROR(C11/B11, 0) -> 0.54237288 | F11: =SUM(F3:F10) -> 144 | G11: =IFERROR(AVERAGE(F14:F500), 0) -> 19.118063 | H11: =IFERROR(MIN(H3:H10), 0) -> 2.9757576 | I11: =IFERROR(MAX(I3:I10), 0) -> 59.029 | J11: =IFERROR(AVERAGE(H14:H500), 0) -> 38.177204
A13: Receita | B13: Categoria | C13: Nº Insumos | D13: Peso Receita (g) | E13: Padronização 1kg | F13: Custo / Kg (R$) | G13: Custo Bola 60g (R$) | H13: Preço Sugerido Pote 500g (R$) | I13: Açúcares (%) | J13: Gorduras (%) | K13: SLNG (%) | L13: Outros Sólidos (%) | M13: Sólidos Totais (%) | N13: Água (%) | O13: POD | P13: PAC | Q13: Proteína (%) | R13: Temp. Serviço (°C) | S13: Status Balanceamento
A14: =IFERROR(__xludf.DUMMYFUNCTION("UNIQUE(FILTER(Receitas!A2:A3500, Receitas!A2:A3500<>""""))"),"Fior di Latte (Direto ao Ponto)") -> Fior di Latte (Direto ao Ponto) | B14: {=IF(A14:A500="", "", VLOOKUP(A14:A500, Receitas!A2:D3500, 4, FALSE))} -> Gelatos de Leite | C14: {=IF(A14:A500="", "", COUNTIF(Receitas!A2:A3500, A14:A500))} -> 8 | D14: {=IF(A14:A500="", "", SUMIF(Receitas!A2:A3500, A14:A500, Receitas!C2:C3500))} -> 1001 | E14: {=IF(A14:A500="", "", IF(ROUND(D14:D500,0)=1000, "1.000 g (Padrão)", "Diferente (" & ROUND(D14:D500, 0) & " g)"))} -> Diferente (1001 g) | F14: {=IF(A14:A500="", "", SUMIF(Receitas!A2:A3500, A14:A500, Receitas!E2:E3500) * 1000 / D14:D500)} -> 11.703796 | G14: {=IF(A14:A500="", "", F14:F500 * 0.06)} -> 0.70222777 | H14: {=IF(A14:A500="", "", ((F14:F500 * ('Conversor Custo K|G'!$F$24/1000) + 'Conversor Custo K|G'!$H$24) + 'Conversor Custo K|G'!$C$11) / ((1 - 'Conversor Custo K|G'!$C$13/100) * (1 - 'Conversor Custo K|G'!$C$14/100)))} -> 32.039566 | I14: {=IF(A14:A500="", "", SUMIF(Receitas!A2:A3500, A14:A500, Receitas!F2:F3500) / D14:D500)} -> 0.17592408 | J14: {=IF(A14:A500="", "", SUMIF(Receitas!A2:A3500, A14:A500, Receitas!G2:G3500) / D14:D500)} -> 0.074125874 | K14: {=IF(A14:A500="", "", SUMIF(Receitas!A2:A3500, A14:A500, Receitas!H2:H3500) / D14:D500)} -> 0.10834166 | L14: {=IF(A14:A500="", "", SUMIF(Receitas!A2:A3500, A14:A500, Receitas!I2:I3500) / D14:D500)} -> 0.005994006 | M14: {=IF(A14:A500="", "", I14:I500 + J14:J500 + K14:K500 + L14:L500)} -> 0.36438561 | N14: {=IF(A14:A500="", "", 1 - M14:M500)} -> 0.63561439 | O14: {=IF(A14:A500="", "", 1000 * SUMIF(Receitas!A2:A3500, A14:A500, Receitas!J2:J3500) / D14:D500)} -> 163.28272 | P14: {=IF(A14:A500="", "", 1000 * SUMIF(Receitas!A2:A3500, A14:A500, Receitas!K2:K3500) / D14:D500)} -> 249.55045 | Q14: {=IF(A14:A500="", "", SUMIF(Receitas!A2:A3500, A14:A500, Receitas!L2:L3500) / D14:D500)} -> 0.041458541 | R14: {=IF(A14:A500="", "", IF((B14:B500="Chocolate base água")+(B14:B500="Vegano")>0, P14:P500/20, IF(B14:B500="Gelatos de Leite com Fruta", P14:P500/24, P14:P500/25)))} -> 9.982018 | S14: {=IF(A14="","", IF( (ROUND(I14,4) < INDEX('Tabela de ingredientes'!$O$1:$V$30, SWITCH(B14, "Gelatos de Leite", 7, "Sorbets", 10, "Gelatos de Leite com Fruta", 13, "Chocolate base água", 16, "Vegano", 19, "Alcoólicos", 22, "Zero", 25, "Gelatos Proteicos", 28, 7), 1)) + (ROUND(I14,4) > INDEX('Tabela de ingredientes'!$O$1:$V$30, SWITCH(B14, "Gelatos de Leite", 8, "Sorbets", 11, "Gelatos de Leite com Fruta", 14, "Chocolate base água", 17, "Vegano", 20, "Alcoólicos", 23, "Zero", 26, "Gelatos Proteicos", 29, 8), 1)) + (ROUND(J14,4) < INDEX('Tabela de ingredientes'!$O$1:$V$30, SWITCH(B14, "Gelatos de Leite", 7, "Sorbets", 10, "Gelatos de Leite com Fruta", 13, "Chocolate base água", 16, "Vegano", 19, "Alcoólicos", 22, "Zero", 25, "Gelatos Proteicos", 28, 7), 2)) + (ROUND(J14,4) > INDEX('Tabela de ingredientes'!$O$1:$V$30, SWITCH(B14, "Gelatos de Leite", 8, "Sorbets", 11, "Gelatos de Leite com Fruta", 14, "Chocolate base água", 17, "Vegano", 20, "Alcoólicos", 23, "Zero", 26, "Gelatos Proteicos", 29, 8), 2)) + (ROUND(K14,4) < INDEX('Tabela de ingredientes'!$O$1:$V$30, SWITCH(B14, "Gelatos de Leite", 7, "Sorbets", 10, "Gelatos de Leite com Fruta", 13, "Chocolate base água", 16, "Vegano", 19, "Alcoólicos", 22, "Zero", 25, "Gelatos Proteicos", 28, 7), 3)) + (ROUND(K14,4) > INDEX('Tabela de ingredientes'!$O$1:$V$30, SWITCH(B14, "Gelatos de Leite", 8, "Sorbets", 11, "Gelatos de Leite com Fruta", 14, "Chocolate base água", 17, "Vegano", 20, "Alcoólicos", 23, "Zero", 26, "Gelatos Proteicos", 29, 8), 3)) + (ROUND(L14,4) < INDEX('Tabela de ingredientes'!$O$1:$V$30, SWITCH(B14, "Gelatos de Leite", 7, "Sorbets", 10, "Gelatos de Leite com Fruta", 13, "Chocolate base água", 16, "Vegano", 19, "Alcoólicos", 22, "Zero", 25, "Gelatos Proteicos", 28, 7), 4)) + (ROUND(L14,4) > INDEX('Tabela de ingredientes'!$O$1:$V$30, SWITCH(B14, "Gelatos de Leite", 8, "Sorbets", 11, "Gelatos de Leite com Fruta", 14, "Chocolate base água", 17, "Vegano", 20, "Alcoólicos", 23, "Zero", 26, "Gelatos Proteicos", 29, 8), 4)) + (ROUND(M14,4) < INDEX('Tabela de ingredientes'!$O$1:$V$30, SWITCH(B14, "Gelatos de Leite", 7, "Sorbets", 10, "Gelatos de Leite com Fruta", 13, "Chocolate base água", 16, "Vegano", 19, "Alcoólicos", 22, "Zero", 25, "Gelatos Proteicos", 28, 7), 5)) + (ROUND(M14,4) > INDEX('Tabela de ingredientes'!$O$1:$V$30, SWITCH(B14, "Gelatos de Leite", 8, "Sorbets", 11, "Gelatos de Leite com Fruta", 14, "Chocolate base água", 17, "Vegano", 20, "Alcoólicos", 23, "Zero", 26, "Gelatos Proteicos", 29, 8), 5)) + (ROUND(N14,4) < INDEX('Tabela de ingredientes'!$O$1:$V$30, SWITCH(B14, "Gelatos de Leite", 7, "Sorbets", 10, "Gelatos de Leite com Fruta", 13, "Chocolate base água", 16, "Vegano", 19, "Alcoólicos", 22, "Zero", 25, "Gelatos Proteicos", 28, 7), 6)) + (ROUND(N14,4) > INDEX('Tabela de ingredientes'!$O$1:$V$30, SWITCH(B14, "Gelatos de Leite", 8, "Sorbets", 11, "Gelatos de Leite com Fruta", 14, "Chocolate base água", 17, "Vegano", 20, "Alcoólicos", 23, "Zero", 26, "Gelatos Proteicos", 29, 8), 6)) + (ROUND(O14,4) < INDEX('Tabela de ingredientes'!$O$1:$V$30, SWITCH(B14, "Gelatos de Leite", 7, "Sorbets", 10, "Gelatos de Leite com Fruta", 13, "Chocolate base água", 16, "Vegano", 19, "Alcoólicos", 22, "Zero", 25, "Gelatos Proteicos", 28, 7), 7)) + (ROUND(O14,4) > INDEX('Tabela de ingredientes'!$O$1:$V$30, SWITCH(B14, "Gelatos de Leite", 8, "Sorbets", 11, "Gelatos de Leite com Fruta", 14, "Chocolate base água", 17, "Vegano", 20, "Alcoólicos", 23, "Zero", 26, "Gelatos Proteicos", 29, 8), 7)) + (ROUND(P14,4) < INDEX('Tabela de ingredientes'!$O$1:$V$30, SWITCH(B14, "Gelatos de Leite", 7, "Sorbets", 10, "Gelatos de Leite com Fruta", 13, "Chocolate base água", 16, "Vegano", 19, "Alcoólicos", 22, "Zero", 25, "Gelatos Proteicos", 28, 7), 8)) + (ROUND(P14,4) > INDEX('Tabela de ingredientes'!$O$1:$V$30, SWITCH(B14, "Gelatos de Leite", 8, "Sorbets", 11, "Gelatos de Leite com Fruta", 14, "Chocolate base água", 17, "Vegano", 20, "Alcoólicos", 23, "Zero", 26, "Gelatos Proteicos", 29, 8), 8)) + IF(B14="Gelatos Proteicos", (ROUND(Q14,4)<'Tabela de ingredientes'!$W$28)+(ROUND(Q14,4)>'Tabela de ingredientes'!$W$29), 0) = 0, "Ok", "Revisar"))} -> Ok
A15: =IFERROR(__xludf.DUMMYFUNCTION("""COMPUTED_VALUE"""),"Café Bianco Flocado (Direto ao Ponto)") -> Café Bianco Flocado (Direto ao Ponto) | B15: Gelatos de Leite | C15: 8 | D15: 1001 | E15: Diferente (1001 g) | F15: 12.423077 | G15: 0.74538462 | H15: 32.634997 | I15: 0.17592408 | J15: 0.08986014 | K15: 0.10684316 | L15: 0.005994006 | M15: 0.37862138 | N15: 0.62137862 | O15: 163.16284 | P15: 249.05095 | Q15: 0.040909091 | R15: 9.962038 | S15: {=IF(A15="","", IF( (ROUND(I15,4) < INDEX('Tabela de ingredientes'!$O$1:$V$30, SWITCH(B15, "Gelatos de Leite", 7, "Sorbets", 10, "Gelatos de Leite com Fruta", 13, "Chocolate base água", 16, "Vegano", 19, "Alcoólicos", 22, "Zero", 25, "Gelatos Proteicos", 28, 7), 1)) + (ROUND(I15,4) > INDEX('Tabela de ingredientes'!$O$1:$V$30, SWITCH(B15, "Gelatos de Leite", 8, "Sorbets", 11, "Gelatos de Leite com Fruta", 14, "Chocolate base água", 17, "Vegano", 20, "Alcoólicos", 23, "Zero", 26, "Gelatos Proteicos", 29, 8), 1)) + (ROUND(J15,4) < INDEX('Tabela de ingredientes'!$O$1:$V$30, SWITCH(B15, "Gelatos de Leite", 7, "Sorbets", 10, "Gelatos de Leite com Fruta", 13, "Chocolate base água", 16, "Vegano", 19, "Alcoólicos", 22, "Zero", 25, "Gelatos Proteicos", 28, 7), 2)) + (ROUND(J15,4) > INDEX('Tabela de ingredientes'!$O$1:$V$30, SWITCH(B15, "Gelatos de Leite", 8, "Sorbets", 11, "Gelatos de Leite com Fruta", 14, "Chocolate base água", 17, "Vegano", 20, "Alcoólicos", 23, "Zero", 26, "Gelatos Proteicos", 29, 8), 2)) + (ROUND(K15,4) < INDEX('Tabela de ingredientes'!$O$1:$V$30, SWITCH(B15, "Gelatos de Leite", 7, "Sorbets", 10, "Gelatos de Leite com Fruta", 13, "Chocolate base água", 16, "Vegano", 19, "Alcoólicos", 22, "Zero", 25, "Gelatos Proteicos", 28, 7), 3)) + (ROUND(K15,4) > INDEX('Tabela de ingredientes'!$O$1:$V$30, SWITCH(B15, "Gelatos de Leite", 8, "Sorbets", 11, "Gelatos de Leite com Fruta", 14, "Chocolate base água", 17, "Vegano", 20, "Alcoólicos", 23, "Zero", 26, "Gelatos Proteicos", 29, 8), 3)) + (ROUND(L15,4) < INDEX('Tabela de ingredientes'!$O$1:$V$30, SWITCH(B15, "Gelatos de Leite", 7, "Sorbets", 10, "Gelatos de Leite com Fruta", 13, "Chocolate base água", 16, "Vegano", 19, "Alcoólicos", 22, "Zero", 25, "Gelatos Proteicos", 28, 7), 4)) + (ROUND(L15,4) > INDEX('Tabela de ingredientes'!$O$1:$V$30, SWITCH(B15, "Gelatos de Leite", 8, "Sorbets", 11, "Gelatos de Leite com Fruta", 14, "Chocolate base água", 17, "Vegano", 20, "Alcoólicos", 23, "Zero", 26, "Gelatos Proteicos", 29, 8), 4)) + (ROUND(M15,4) < INDEX('Tabela de ingredientes'!$O$1:$V$30, SWITCH(B15, "Gelatos de Leite", 7, "Sorbets", 10, "Gelatos de Leite com Fruta", 13, "Chocolate base água", 16, "Vegano", 19, "Alcoólicos", 22, "Zero", 25, "Gelatos Proteicos", 28, 7), 5)) + (ROUND(M15,4) > INDEX('Tabela de ingredientes'!$O$1:$V$30, SWITCH(B15, "Gelatos de Leite", 8, "Sorbets", 11, "Gelatos de Leite com Fruta", 14, "Chocolate base água", 17, "Vegano", 20, "Alcoólicos", 23, "Zero", 26, "Gelatos Proteicos", 29, 8), 5)) + (ROUND(N15,4) < INDEX('Tabela de ingredientes'!$O$1:$V$30, SWITCH(B15, "Gelatos de Leite", 7, "Sorbets", 10, "Gelatos de Leite com Fruta", 13, "Chocolate base água", 16, "Vegano", 19, "Alcoólicos", 22, "Zero", 25, "Gelatos Proteicos", 28, 7), 6)) + (ROUND(N15,4) > INDEX('Tabela de ingredientes'!$O$1:$V$30, SWITCH(B15, "Gelatos de Leite", 8, "Sorbets", 11, "Gelatos de Leite com Fruta", 14, "Chocolate base água", 17, "Vegano", 20, "Alcoólicos", 23, "Zero", 26, "Gelatos Proteicos", 29, 8), 6)) + (ROUND(O15,4) < INDEX('Tabela de ingredientes'!$O$1:$V$30, SWITCH(B15, "Gelatos de Leite", 7, "Sorbets", 10, "Gelatos de Leite com Fruta", 13, "Chocolate base água", 16, "Vegano", 19, "Alcoólicos", 22, "Zero", 25, "Gelatos Proteicos", 28, 7), 7)) + (ROUND(O15,4) > INDEX('Tabela de ingredientes'!$O$1:$V$30, SWITCH(B15, "Gelatos de Leite", 8, "Sorbets", 11, "Gelatos de Leite com Fruta", 14, "Chocolate base água", 17, "Vegano", 20, "Alcoólicos", 23, "Zero", 26, "Gelatos Proteicos", 29, 8), 7)) + (ROUND(P15,4) < INDEX('Tabela de ingredientes'!$O$1:$V$30, SWITCH(B15, "Gelatos de Leite", 7, "Sorbets", 10, "Gelatos de Leite com Fruta", 13, "Chocolate base água", 16, "Vegano", 19, "Alcoólicos", 22, "Zero", 25, "Gelatos Proteicos", 28, 7), 8)) + (ROUND(P15,4) > INDEX('Tabela de ingredientes'!$O$1:$V$30, SWITCH(B15, "Gelatos de Leite", 8, "Sorbets", 11, "Gelatos de Leite com Fruta", 14, "Chocolate base água", 17, "Vegano", 20, "Alcoólicos", 23, "Zero", 26, "Gelatos Proteicos", 29, 8), 8)) + IF(B15="Gelatos Proteicos", (ROUND(Q15,4)<'Tabela de ingredientes'!$W$28)+(ROUND(Q15,4)>'Tabela de ingredientes'!$W$29), 0) = 0, "Ok", "Revisar"))} -> Ok
A16: =IFERROR(__xludf.DUMMYFUNCTION("""COMPUTED_VALUE"""),"Chocolate com Gostosuras (Direto ao Ponto)") -> Chocolate com Gostosuras (Direto ao Ponto) | B16: Gelatos de Leite | C16: 9 | D16: 1000 | E16: 1.000 g (Padrão) | F16: 23.8625 | G16: 1.43175 | H16: 42.104719 | I16: 0.17 | J16: 0.07885 | K16: 0.0906 | L16: 0.0558 | M16: 0.39525 | N16: 0.60475 | O16: 191.143 | P16: 235.55 | Q16: 0.04416 | R16: 9.422 | S16: {=IF(A16="","", IF( (ROUND(I16,4) < INDEX('Tabela de ingredientes'!$O$1:$V$30, SWITCH(B16, "Gelatos de Leite", 7, "Sorbets", 10, "Gelatos de Leite com Fruta", 13, "Chocolate base água", 16, "Vegano", 19, "Alcoólicos", 22, "Zero", 25, "Gelatos Proteicos", 28, 7), 1)) + (ROUND(I16,4) > INDEX('Tabela de ingredientes'!$O$1:$V$30, SWITCH(B16, "Gelatos de Leite", 8, "Sorbets", 11, "Gelatos de Leite com Fruta", 14, "Chocolate base água", 17, "Vegano", 20, "Alcoólicos", 23, "Zero", 26, "Gelatos Proteicos", 29, 8), 1)) + (ROUND(J16,4) < INDEX('Tabela de ingredientes'!$O$1:$V$30, SWITCH(B16, "Gelatos de Leite", 7, "Sorbets", 10, "Gelatos de Leite com Fruta", 13, "Chocolate base água", 16, "Vegano", 19, "Alcoólicos", 22, "Zero", 25, "Gelatos Proteicos", 28, 7), 2)) + (ROUND(J16,4) > INDEX('Tabela de ingredientes'!$O$1:$V$30, SWITCH(B16, "Gelatos de Leite", 8, "Sorbets", 11, "Gelatos de Leite com Fruta", 14, "Chocolate base água", 17, "Vegano", 20, "Alcoólicos", 23, "Zero", 26, "Gelatos Proteicos", 29, 8), 2)) + (ROUND(K16,4) < INDEX('Tabela de ingredientes'!$O$1:$V$30, SWITCH(B16, "Gelatos de Leite", 7, "Sorbets", 10, "Gelatos de Leite com Fruta", 13, "Chocolate base água", 16, "Vegano", 19, "Alcoólicos", 22, "Zero", 25, "Gelatos Proteicos", 28, 7), 3)) + (ROUND(K16,4) > INDEX('Tabela de ingredientes'!$O$1:$V$30, SWITCH(B16, "Gelatos de Leite", 8, "Sorbets", 11, "Gelatos de Leite com Fruta", 14, "Chocolate base água", 17, "Vegano", 20, "Alcoólicos", 23, "Zero", 26, "Gelatos Proteicos", 29, 8), 3)) + (ROUND(L16,4) < INDEX('Tabela de ingredientes'!$O$1:$V$30, SWITCH(B16, "Gelatos de Leite", 7, "Sorbets", 10, "Gelatos de Leite com Fruta", 13, "Chocolate base água", 16, "Vegano", 19, "Alcoólicos", 22, "Zero", 25, "Gelatos Proteicos", 28, 7), 4)) + (ROUND(L16,4) > INDEX('Tabela de ingredientes'!$O$1:$V$30, SWITCH(B16, "Gelatos de Leite", 8, "Sorbets", 11, "Gelatos de Leite com Fruta", 14, "Chocolate base água", 17, "Vegano", 20, "Alcoólicos", 23, "Zero", 26, "Gelatos Proteicos", 29, 8), 4)) + (ROUND(M16,4) < INDEX('Tabela de ingredientes'!$O$1:$V$30, SWITCH(B16, "Gelatos de Leite", 7, "Sorbets", 10, "Gelatos de Leite com Fruta", 13, "Chocolate base água", 16, "Vegano", 19, "Alcoólicos", 22, "Zero", 25, "Gelatos Proteicos", 28, 7), 5)) + (ROUND(M16,4) > INDEX('Tabela de ingredientes'!$O$1:$V$30, SWITCH(B16, "Gelatos de Leite", 8, "Sorbets", 11, "Gelatos de Leite com Fruta", 14, "Chocolate base água", 17, "Vegano", 20, "Alcoólicos", 23, "Zero", 26, "Gelatos Proteicos", 29, 8), 5)) + (ROUND(N16,4) < INDEX('Tabela de ingredientes'!$O$1:$V$30, SWITCH(B16, "Gelatos de Leite", 7, "Sorbets", 10, "Gelatos de Leite com Fruta", 13, "Chocolate base água", 16, "Vegano", 19, "Alcoólicos", 22, "Zero", 25, "Gelatos Proteicos", 28, 7), 6)) + (ROUND(N16,4) > INDEX('Tabela de ingredientes'!$O$1:$V$30, SWITCH(B16, "Gelatos de Leite", 8, "Sorbets", 11, "Gelatos de Leite com Fruta", 14, "Chocolate base água", 17, "Vegano", 20, "Alcoólicos", 23, "Zero", 26, "Gelatos Proteicos", 29, 8), 6)) + (ROUND(O16,4) < INDEX('Tabela de ingredientes'!$O$1:$V$30, SWITCH(B16, "Gelatos de Leite", 7, "Sorbets", 10, "Gelatos de Leite com Fruta", 13, "Chocolate base água", 16, "Vegano", 19, "Alcoólicos", 22, "Zero", 25, "Gelatos Proteicos", 28, 7), 7)) + (ROUND(O16,4) > INDEX('Tabela de ingredientes'!$O$1:$V$30, SWITCH(B16, "Gelatos de Leite", 8, "Sorbets", 11, "Gelatos de Leite com Fruta", 14, "Chocolate base água", 17, "Vegano", 20, "Alcoólicos", 23, "Zero", 26, "Gelatos Proteicos", 29, 8), 7)) + (ROUND(P16,4) < INDEX('Tabela de ingredientes'!$O$1:$V$30, SWITCH(B16, "Gelatos de Leite", 7, "Sorbets", 10, "Gelatos de Leite com Fruta", 13, "Chocolate base água", 16, "Vegano", 19, "Alcoólicos", 22, "Zero", 25, "Gelatos Proteicos", 28, 7), 8)) + (ROUND(P16,4) > INDEX('Tabela de ingredientes'!$O$1:$V$30, SWITCH(B16, "Gelatos de Leite", 8, "Sorbets", 11, "Gelatos de Leite com Fruta", 14, "Chocolate base água", 17, "Vegano", 20, "Alcoólicos", 23, "Zero", 26, "Gelatos Proteicos", 29, 8), 8)) + IF(B16="Gelatos Proteicos", (ROUND(Q16,4)<'Tabela de ingredientes'!$W$28)+(ROUND(Q16,4)>'Tabela de ingredientes'!$W$29), 0) = 0, "Ok", "Revisar"))} -> Ok
A17: =IFERROR(__xludf.DUMMYFUNCTION("""COMPUTED_VALUE"""),"Crema (Direto ao Ponto)") -> Crema (Direto ao Ponto) | B17: Gelatos de Leite | C17: 9 | D17: 1005 | E17: Diferente (1005 g) | F17: 16.630348 | G17: 0.9978209 | H17: 36.117838 | I17: 0.15084577 | J17: 0.088159204 | K17: 0.10432836 | L17: 0.019303483 | M17: 0.36263682 | N17: 0.63736318 | O17: 152.61493 | P17: 229.70149 | Q17: 0.052616915 | R17: 9.1880597 | S17: {=IF(A17="","", IF( (ROUND(I17,4) < INDEX('Tabela de ingredientes'!$O$1:$V$30, SWITCH(B17, "Gelatos de Leite", 7, "Sorbets", 10, "Gelatos de Leite com Fruta", 13, "Chocolate base água", 16, "Vegano", 19, "Alcoólicos", 22, "Zero", 25, "Gelatos Proteicos", 28, 7), 1)) + (ROUND(I17,4) > INDEX('Tabela de ingredientes'!$O$1:$V$30, SWITCH(B17, "Gelatos de Leite", 8, "Sorbets", 11, "Gelatos de Leite com Fruta", 14, "Chocolate base água", 17, "Vegano", 20, "Alcoólicos", 23, "Zero", 26, "Gelatos Proteicos", 29, 8), 1)) + (ROUND(J17,4) < INDEX('Tabela de ingredientes'!$O$1:$V$30, SWITCH(B17, "Gelatos de Leite", 7, "Sorbets", 10, "Gelatos de Leite com Fruta", 13, "Chocolate base água", 16, "Vegano", 19, "Alcoólicos", 22, "Zero", 25, "Gelatos Proteicos", 28, 7), 2)) + (ROUND(J17,4) > INDEX('Tabela de ingredientes'!$O$1:$V$30, SWITCH(B17, "Gelatos de Leite", 8, "Sorbets", 11, "Gelatos de Leite com Fruta", 14, "Chocolate base água", 17, "Vegano", 20, "Alcoólicos", 23, "Zero", 26, "Gelatos Proteicos", 29, 8), 2)) + (ROUND(K17,4) < INDEX('Tabela de ingredientes'!$O$1:$V$30, SWITCH(B17, "Gelatos de Leite", 7, "Sorbets", 10, "Gelatos de Leite com Fruta", 13, "Chocolate base água", 16, "Vegano", 19, "Alcoólicos", 22, "Zero", 25, "Gelatos Proteicos", 28, 7), 3)) + (ROUND(K17,4) > INDEX('Tabela de ingredientes'!$O$1:$V$30, SWITCH(B17, "Gelatos de Leite", 8, "Sorbets", 11, "Gelatos de Leite com Fruta", 14, "Chocolate base água", 17, "Vegano", 20, "Alcoólicos", 23, "Zero", 26, "Gelatos Proteicos", 29, 8), 3)) + (ROUND(L17,4) < INDEX('Tabela de ingredientes'!$O$1:$V$30, SWITCH(B17, "Gelatos de Leite", 7, "Sorbets", 10, "Gelatos de Leite com Fruta", 13, "Chocolate base água", 16, "Vegano", 19, "Alcoólicos", 22, "Zero", 25, "Gelatos Proteicos", 28, 7), 4)) + (ROUND(L17,4) > INDEX('Tabela de ingredientes'!$O$1:$V$30, SWITCH(B17, "Gelatos de Leite", 8, "Sorbets", 11, "Gelatos de Leite com Fruta", 14, "Chocolate base água", 17, "Vegano", 20, "Alcoólicos", 23, "Zero", 26, "Gelatos Proteicos", 29, 8), 4)) + (ROUND(M17,4) < INDEX('Tabela de ingredientes'!$O$1:$V$30, SWITCH(B17, "Gelatos de Leite", 7, "Sorbets", 10, "Gelatos de Leite com Fruta", 13, "Chocolate base água", 16, "Vegano", 19, "Alcoólicos", 22, "Zero", 25, "Gelatos Proteicos", 28, 7), 5)) + (ROUND(M17,4) > INDEX('Tabela de ingredientes'!$O$1:$V$30, SWITCH(B17, "Gelatos de Leite", 8, "Sorbets", 11, "Gelatos de Leite com Fruta", 14, "Chocolate base água", 17, "Vegano", 20, "Alcoólicos", 23, "Zero", 26, "Gelatos Proteicos", 29, 8), 5)) + (ROUND(N17,4) < INDEX('Tabela de ingredientes'!$O$1:$V$30, SWITCH(B17, "Gelatos de Leite", 7, "Sorbets", 10, "Gelatos de Leite com Fruta", 13, "Chocolate base água", 16, "Vegano", 19, "Alcoólicos", 22, "Zero", 25, "Gelatos Proteicos", 28, 7), 6)) + (ROUND(N17,4) > INDEX('Tabela de ingredientes'!$O$1:$V$30, SWITCH(B17, "Gelatos de Leite", 8, "Sorbets", 11, "Gelatos de Leite com Fruta", 14, "Chocolate base água", 17, "Vegano", 20, "Alcoólicos", 23, "Zero", 26, "Gelatos Proteicos", 29, 8), 6)) + (ROUND(O17,4) < INDEX('Tabela de ingredientes'!$O$1:$V$30, SWITCH(B17, "Gelatos de Leite", 7, "Sorbets", 10, "Gelatos de Leite com Fruta", 13, "Chocolate base água", 16, "Vegano", 19, "Alcoólicos", 22, "Zero", 25, "Gelatos Proteicos", 28, 7), 7)) + (ROUND(O17,4) > INDEX('Tabela de ingredientes'!$O$1:$V$30, SWITCH(B17, "Gelatos de Leite", 8, "Sorbets", 11, "Gelatos de Leite com Fruta", 14, "Chocolate base água", 17, "Vegano", 20, "Alcoólicos", 23, "Zero", 26, "Gelatos Proteicos", 29, 8), 7)) + (ROUND(P17,4) < INDEX('Tabela de ingredientes'!$O$1:$V$30, SWITCH(B17, "Gelatos de Leite", 7, "Sorbets", 10, "Gelatos de Leite com Fruta", 13, "Chocolate base água", 16, "Vegano", 19, "Alcoólicos", 22, "Zero", 25, "Gelatos Proteicos", 28, 7), 8)) + (ROUND(P17,4) > INDEX('Tabela de ingredientes'!$O$1:$V$30, SWITCH(B17, "Gelatos de Leite", 8, "Sorbets", 11, "Gelatos de Leite com Fruta", 14, "Chocolate base água", 17, "Vegano", 20, "Alcoólicos", 23, "Zero", 26, "Gelatos Proteicos", 29, 8), 8)) + IF(B17="Gelatos Proteicos", (ROUND(Q17,4)<'Tabela de ingredientes'!$W$28)+(ROUND(Q17,4)>'Tabela de ingredientes'!$W$29), 0) = 0, "Ok", "Revisar"))} -> Ok
A18: =IFERROR(__xludf.DUMMYFUNCTION("""COMPUTED_VALUE"""),"Crema di Santa Fina (Direto ao Ponto)") -> Crema di Santa Fina (Direto ao Ponto) | B18: Gelatos de Leite | C18: 10 | D18: 1003 | E18: Diferente (1003 g) | F18: 17.193918 | G18: 1.0316351 | H18: 36.584369 | I18: 0.16490528 | J18: 0.090777667 | K18: 0.10244267 | L18: 0.019880359 | M18: 0.37800598 | N18: 0.62199402 | O18: 163.95613 | P18: 256.39083 | Q18: 0.051914257 | R18: 10.255633 | S18: {=IF(A18="","", IF( (ROUND(I18,4) < INDEX('Tabela de ingredientes'!$O$1:$V$30, SWITCH(B18, "Gelatos de Leite", 7, "Sorbets", 10, "Gelatos de Leite com Fruta", 13, "Chocolate base água", 16, "Vegano", 19, "Alcoólicos", 22, "Zero", 25, "Gelatos Proteicos", 28, 7), 1)) + (ROUND(I18,4) > INDEX('Tabela de ingredientes'!$O$1:$V$30, SWITCH(B18, "Gelatos de Leite", 8, "Sorbets", 11, "Gelatos de Leite com Fruta", 14, "Chocolate base água", 17, "Vegano", 20, "Alcoólicos", 23, "Zero", 26, "Gelatos Proteicos", 29, 8), 1)) + (ROUND(J18,4) < INDEX('Tabela de ingredientes'!$O$1:$V$30, SWITCH(B18, "Gelatos de Leite", 7, "Sorbets", 10, "Gelatos de Leite com Fruta", 13, "Chocolate base água", 16, "Vegano", 19, "Alcoólicos", 22, "Zero", 25, "Gelatos Proteicos", 28, 7), 2)) + (ROUND(J18,4) > INDEX('Tabela de ingredientes'!$O$1:$V$30, SWITCH(B18, "Gelatos de Leite", 8, "Sorbets", 11, "Gelatos de Leite com Fruta", 14, "Chocolate base água", 17, "Vegano", 20, "Alcoólicos", 23, "Zero", 26, "Gelatos Proteicos", 29, 8), 2)) + (ROUND(K18,4) < INDEX('Tabela de ingredientes'!$O$1:$V$30, SWITCH(B18, "Gelatos de Leite", 7, "Sorbets", 10, "Gelatos de Leite com Fruta", 13, "Chocolate base água", 16, "Vegano", 19, "Alcoólicos", 22, "Zero", 25, "Gelatos Proteicos", 28, 7), 3)) + (ROUND(K18,4) > INDEX('Tabela de ingredientes'!$O$1:$V$30, SWITCH(B18, "Gelatos de Leite", 8, "Sorbets", 11, "Gelatos de Leite com Fruta", 14, "Chocolate base água", 17, "Vegano", 20, "Alcoólicos", 23, "Zero", 26, "Gelatos Proteicos", 29, 8), 3)) + (ROUND(L18,4) < INDEX('Tabela de ingredientes'!$O$1:$V$30, SWITCH(B18, "Gelatos de Leite", 7, "Sorbets", 10, "Gelatos de Leite com Fruta", 13, "Chocolate base água", 16, "Vegano", 19, "Alcoólicos", 22, "Zero", 25, "Gelatos Proteicos", 28, 7), 4)) + (ROUND(L18,4) > INDEX('Tabela de ingredientes'!$O$1:$V$30, SWITCH(B18, "Gelatos de Leite", 8, "Sorbets", 11, "Gelatos de Leite com Fruta", 14, "Chocolate base água", 17, "Vegano", 20, "Alcoólicos", 23, "Zero", 26, "Gelatos Proteicos", 29, 8), 4)) + (ROUND(M18,4) < INDEX('Tabela de ingredientes'!$O$1:$V$30, SWITCH(B18, "Gelatos de Leite", 7, "Sorbets", 10, "Gelatos de Leite com Fruta", 13, "Chocolate base água", 16, "Vegano", 19, "Alcoólicos", 22, "Zero", 25, "Gelatos Proteicos", 28, 7), 5)) + (ROUND(M18,4) > INDEX('Tabela de ingredientes'!$O$1:$V$30, SWITCH(B18, "Gelatos de Leite", 8, "Sorbets", 11, "Gelatos de Leite com Fruta", 14, "Chocolate base água", 17, "Vegano", 20, "Alcoólicos", 23, "Zero", 26, "Gelatos Proteicos", 29, 8), 5)) + (ROUND(N18,4) < INDEX('Tabela de ingredientes'!$O$1:$V$30, SWITCH(B18, "Gelatos de Leite", 7, "Sorbets", 10, "Gelatos de Leite com Fruta", 13, "Chocolate base água", 16, "Vegano", 19, "Alcoólicos", 22, "Zero", 25, "Gelatos Proteicos", 28, 7), 6)) + (ROUND(N18,4) > INDEX('Tabela de ingredientes'!$O$1:$V$30, SWITCH(B18, "Gelatos de Leite", 8, "Sorbets", 11, "Gelatos de Leite com Fruta", 14, "Chocolate base água", 17, "Vegano", 20, "Alcoólicos", 23, "Zero", 26, "Gelatos Proteicos", 29, 8), 6)) + (ROUND(O18,4) < INDEX('Tabela de ingredientes'!$O$1:$V$30, SWITCH(B18, "Gelatos de Leite", 7, "Sorbets", 10, "Gelatos de Leite com Fruta", 13, "Chocolate base água", 16, "Vegano", 19, "Alcoólicos", 22, "Zero", 25, "Gelatos Proteicos", 28, 7), 7)) + (ROUND(O18,4) > INDEX('Tabela de ingredientes'!$O$1:$V$30, SWITCH(B18, "Gelatos de Leite", 8, "Sorbets", 11, "Gelatos de Leite com Fruta", 14, "Chocolate base água", 17, "Vegano", 20, "Alcoólicos", 23, "Zero", 26, "Gelatos Proteicos", 29, 8), 7)) + (ROUND(P18,4) < INDEX('Tabela de ingredientes'!$O$1:$V$30, SWITCH(B18, "Gelatos de Leite", 7, "Sorbets", 10, "Gelatos de Leite com Fruta", 13, "Chocolate base água", 16, "Vegano", 19, "Alcoólicos", 22, "Zero", 25, "Gelatos Proteicos", 28, 7), 8)) + (ROUND(P18,4) > INDEX('Tabela de ingredientes'!$O$1:$V$30, SWITCH(B18, "Gelatos de Leite", 8, "Sorbets", 11, "Gelatos de Leite com Fruta", 14, "Chocolate base água", 17, "Vegano", 20, "Alcoólicos", 23, "Zero", 26, "Gelatos Proteicos", 29, 8), 8)) + IF(B18="Gelatos Proteicos", (ROUND(Q18,4)<'Tabela de ingredientes'!$W$28)+(ROUND(Q18,4)>'Tabela de ingredientes'!$W$29), 0) = 0, "Ok", "Revisar"))} -> Ok
A19: =IFERROR(__xludf.DUMMYFUNCTION("""COMPUTED_VALUE"""),"Baunilha com Mascavo (Direto ao Ponto)") -> Baunilha com Mascavo (Direto ao Ponto) | B19: Gelatos de Leite | C19: 10 | D19: 1002 | E19: Diferente (1002 g) | F19: 22.596307 | G19: 1.3557784 | H19: 41.056546 | I19: 0.18353293 | J19: 0.074401198 | K19: 0.10494012 | L19: 0.028692615 | M19: 0.39156687 | N19: 0.60843313 | O19: 168.47405 | P19: 270.65868 | Q19: 0.040139721 | R19: 10.826347 | S19: {=IF(A19="","", IF( (ROUND(I19,4) < INDEX('Tabela de ingredientes'!$O$1:$V$30, SWITCH(B19, "Gelatos de Leite", 7, "Sorbets", 10, "Gelatos de Leite com Fruta", 13, "Chocolate base água", 16, "Vegano", 19, "Alcoólicos", 22, "Zero", 25, "Gelatos Proteicos", 28, 7), 1)) + (ROUND(I19,4) > INDEX('Tabela de ingredientes'!$O$1:$V$30, SWITCH(B19, "Gelatos de Leite", 8, "Sorbets", 11, "Gelatos de Leite com Fruta", 14, "Chocolate base água", 17, "Vegano", 20, "Alcoólicos", 23, "Zero", 26, "Gelatos Proteicos", 29, 8), 1)) + (ROUND(J19,4) < INDEX('Tabela de ingredientes'!$O$1:$V$30, SWITCH(B19, "Gelatos de Leite", 7, "Sorbets", 10, "Gelatos de Leite com Fruta", 13, "Chocolate base água", 16, "Vegano", 19, "Alcoólicos", 22, "Zero", 25, "Gelatos Proteicos", 28, 7), 2)) + (ROUND(J19,4) > INDEX('Tabela de ingredientes'!$O$1:$V$30, SWITCH(B19, "Gelatos de Leite", 8, "Sorbets", 11, "Gelatos de Leite com Fruta", 14, "Chocolate base água", 17, "Vegano", 20, "Alcoólicos", 23, "Zero", 26, "Gelatos Proteicos", 29, 8), 2)) + (ROUND(K19,4) < INDEX('Tabela de ingredientes'!$O$1:$V$30, SWITCH(B19, "Gelatos de Leite", 7, "Sorbets", 10, "Gelatos de Leite com Fruta", 13, "Chocolate base água", 16, "Vegano", 19, "Alcoólicos", 22, "Zero", 25, "Gelatos Proteicos", 28, 7), 3)) + (ROUND(K19,4) > INDEX('Tabela de ingredientes'!$O$1:$V$30, SWITCH(B19, "Gelatos de Leite", 8, "Sorbets", 11, "Gelatos de Leite com Fruta", 14, "Chocolate base água", 17, "Vegano", 20, "Alcoólicos", 23, "Zero", 26, "Gelatos Proteicos", 29, 8), 3)) + (ROUND(L19,4) < INDEX('Tabela de ingredientes'!$O$1:$V$30, SWITCH(B19, "Gelatos de Leite", 7, "Sorbets", 10, "Gelatos de Leite com Fruta", 13, "Chocolate base água", 16, "Vegano", 19, "Alcoólicos", 22, "Zero", 25, "Gelatos Proteicos", 28, 7), 4)) + (ROUND(L19,4) > INDEX('Tabela de ingredientes'!$O$1:$V$30, SWITCH(B19, "Gelatos de Leite", 8, "Sorbets", 11, "Gelatos de Leite com Fruta", 14, "Chocolate base água", 17, "Vegano", 20, "Alcoólicos", 23, "Zero", 26, "Gelatos Proteicos", 29, 8), 4)) + (ROUND(M19,4) < INDEX('Tabela de ingredientes'!$O$1:$V$30, SWITCH(B19, "Gelatos de Leite", 7, "Sorbets", 10, "Gelatos de Leite com Fruta", 13, "Chocolate base água", 16, "Vegano", 19, "Alcoólicos", 22, "Zero", 25, "Gelatos Proteicos", 28, 7), 5)) + (ROUND(M19,4) > INDEX('Tabela de ingredientes'!$O$1:$V$30, SWITCH(B19, "Gelatos de Leite", 8, "Sorbets", 11, "Gelatos de Leite com Fruta", 14, "Chocolate base água", 17, "Vegano", 20, "Alcoólicos", 23, "Zero", 26, "Gelatos Proteicos", 29, 8), 5)) + (ROUND(N19,4) < INDEX('Tabela de ingredientes'!$O$1:$V$30, SWITCH(B19, "Gelatos de Leite", 7, "Sorbets", 10, "Gelatos de Leite com Fruta", 13, "Chocolate base água", 16, "Vegano", 19, "Alcoólicos", 22, "Zero", 25, "Gelatos Proteicos", 28, 7), 6)) + (ROUND(N19,4) > INDEX('Tabela de ingredientes'!$O$1:$V$30, SWITCH(B19, "Gelatos de Leite", 8, "Sorbets", 11, "Gelatos de Leite com Fruta", 14, "Chocolate base água", 17, "Vegano", 20, "Alcoólicos", 23, "Zero", 26, "Gelatos Proteicos", 29, 8), 6)) + (ROUND(O19,4) < INDEX('Tabela de ingredientes'!$O$1:$V$30, SWITCH(B19, "Gelatos de Leite", 7, "Sorbets", 10, "Gelatos de Leite com Fruta", 13, "Chocolate base água", 16, "Vegano", 19, "Alcoólicos", 22, "Zero", 25, "Gelatos Proteicos", 28, 7), 7)) + (ROUND(O19,4) > INDEX('Tabela de ingredientes'!$O$1:$V$30, SWITCH(B19, "Gelatos de Leite", 8, "Sorbets", 11, "Gelatos de Leite com Fruta", 14, "Chocolate base água", 17, "Vegano", 20, "Alcoólicos", 23, "Zero", 26, "Gelatos Proteicos", 29, 8), 7)) + (ROUND(P19,4) < INDEX('Tabela de ingredientes'!$O$1:$V$30, SWITCH(B19, "Gelatos de Leite", 7, "Sorbets", 10, "Gelatos de Leite com Fruta", 13, "Chocolate base água", 16, "Vegano", 19, "Alcoólicos", 22, "Zero", 25, "Gelatos Proteicos", 28, 7), 8)) + (ROUND(P19,4) > INDEX('Tabela de ingredientes'!$O$1:$V$30, SWITCH(B19, "Gelatos de Leite", 8, "Sorbets", 11, "Gelatos de Leite com Fruta", 14, "Chocolate base água", 17, "Vegano", 20, "Alcoólicos", 23, "Zero", 26, "Gelatos Proteicos", 29, 8), 8)) + IF(B19="Gelatos Proteicos", (ROUND(Q19,4)<'Tabela de ingredientes'!$W$28)+(ROUND(Q19,4)>'Tabela de ingredientes'!$W$29), 0) = 0, "Ok", "Revisar"))} -> Ok
A20: =IFERROR(__xludf.DUMMYFUNCTION("""COMPUTED_VALUE"""),"Doce de Leite (Direto ao Ponto)") -> Doce de Leite (Direto ao Ponto) | B20: Gelatos de Leite | C20: 6 | D20: 1001 | E20: Diferente (1001 g) | F20: 23.246254 | G20: 1.3947752 | H20: 41.594581 | I20: 0.18511489 | J20: 0.088636364 | K20: 0.0995005 | L20: 0.005994006 | M20: 0.37924575 | N20: 0.62075425 | O20: 179.98601 | P20: 280.61938 | Q20: 0.050504496 | R20: 11.224775 | S20: {=IF(A20="","", IF( (ROUND(I20,4) < INDEX('Tabela de ingredientes'!$O$1:$V$30, SWITCH(B20, "Gelatos de Leite", 7, "Sorbets", 10, "Gelatos de Leite com Fruta", 13, "Chocolate base água", 16, "Vegano", 19, "Alcoólicos", 22, "Zero", 25, "Gelatos Proteicos", 28, 7), 1)) + (ROUND(I20,4) > INDEX('Tabela de ingredientes'!$O$1:$V$30, SWITCH(B20, "Gelatos de Leite", 8, "Sorbets", 11, "Gelatos de Leite com Fruta", 14, "Chocolate base água", 17, "Vegano", 20, "Alcoólicos", 23, "Zero", 26, "Gelatos Proteicos", 29, 8), 1)) + (ROUND(J20,4) < INDEX('Tabela de ingredientes'!$O$1:$V$30, SWITCH(B20, "Gelatos de Leite", 7, "Sorbets", 10, "Gelatos de Leite com Fruta", 13, "Chocolate base água", 16, "Vegano", 19, "Alcoólicos", 22, "Zero", 25, "Gelatos Proteicos", 28, 7), 2)) + (ROUND(J20,4) > INDEX('Tabela de ingredientes'!$O$1:$V$30, SWITCH(B20, "Gelatos de Leite", 8, "Sorbets", 11, "Gelatos de Leite com Fruta", 14, "Chocolate base água", 17, "Vegano", 20, "Alcoólicos", 23, "Zero", 26, "Gelatos Proteicos", 29, 8), 2)) + (ROUND(K20,4) < INDEX('Tabela de ingredientes'!$O$1:$V$30, SWITCH(B20, "Gelatos de Leite", 7, "Sorbets", 10, "Gelatos de Leite com Fruta", 13, "Chocolate base água", 16, "Vegano", 19, "Alcoólicos", 22, "Zero", 25, "Gelatos Proteicos", 28, 7), 3)) + (ROUND(K20,4) > INDEX('Tabela de ingredientes'!$O$1:$V$30, SWITCH(B20, "Gelatos de Leite", 8, "Sorbets", 11, "Gelatos de Leite com Fruta", 14, "Chocolate base água", 17, "Vegano", 20, "Alcoólicos", 23, "Zero", 26, "Gelatos Proteicos", 29, 8), 3)) + (ROUND(L20,4) < INDEX('Tabela de ingredientes'!$O$1:$V$30, SWITCH(B20, "Gelatos de Leite", 7, "Sorbets", 10, "Gelatos de Leite com Fruta", 13, "Chocolate base água", 16, "Vegano", 19, "Alcoólicos", 22, "Zero", 25, "Gelatos Proteicos", 28, 7), 4)) + (ROUND(L20,4) > INDEX('Tabela de ingredientes'!$O$1:$V$30, SWITCH(B20, "Gelatos de Leite", 8, "Sorbets", 11, "Gelatos de Leite com Fruta", 14, "Chocolate base água", 17, "Vegano", 20, "Alcoólicos", 23, "Zero", 26, "Gelatos Proteicos", 29, 8), 4)) + (ROUND(M20,4) < INDEX('Tabela de ingredientes'!$O$1:$V$30, SWITCH(B20, "Gelatos de Leite", 7, "Sorbets", 10, "Gelatos de Leite com Fruta", 13, "Chocolate base água", 16, "Vegano", 19, "Alcoólicos", 22, "Zero", 25, "Gelatos Proteicos", 28, 7), 5)) + (ROUND(M20,4) > INDEX('Tabela de ingredientes'!$O$1:$V$30, SWITCH(B20, "Gelatos de Leite", 8, "Sorbets", 11, "Gelatos de Leite com Fruta", 14, "Chocolate base água", 17, "Vegano", 20, "Alcoólicos", 23, "Zero", 26, "Gelatos Proteicos", 29, 8), 5)) + (ROUND(N20,4) < INDEX('Tabela de ingredientes'!$O$1:$V$30, SWITCH(B20, "Gelatos de Leite", 7, "Sorbets", 10, "Gelatos de Leite com Fruta", 13, "Chocolate base água", 16, "Vegano", 19, "Alcoólicos", 22, "Zero", 25, "Gelatos Proteicos", 28, 7), 6)) + (ROUND(N20,4) > INDEX('Tabela de ingredientes'!$O$1:$V$30, SWITCH(B20, "Gelatos de Leite", 8, "Sorbets", 11, "Gelatos de Leite com Fruta", 14, "Chocolate base água", 17, "Vegano", 20, "Alcoólicos", 23, "Zero", 26, "Gelatos Proteicos", 29, 8), 6)) + (ROUND(O20,4) < INDEX('Tabela de ingredientes'!$O$1:$V$30, SWITCH(B20, "Gelatos de Leite", 7, "Sorbets", 10, "Gelatos de Leite com Fruta", 13, "Chocolate base água", 16, "Vegano", 19, "Alcoólicos", 22, "Zero", 25, "Gelatos Proteicos", 28, 7), 7)) + (ROUND(O20,4) > INDEX('Tabela de ingredientes'!$O$1:$V$30, SWITCH(B20, "Gelatos de Leite", 8, "Sorbets", 11, "Gelatos de Leite com Fruta", 14, "Chocolate base água", 17, "Vegano", 20, "Alcoólicos", 23, "Zero", 26, "Gelatos Proteicos", 29, 8), 7)) + (ROUND(P20,4) < INDEX('Tabela de ingredientes'!$O$1:$V$30, SWITCH(B20, "Gelatos de Leite", 7, "Sorbets", 10, "Gelatos de Leite com Fruta", 13, "Chocolate base água", 16, "Vegano", 19, "Alcoólicos", 22, "Zero", 25, "Gelatos Proteicos", 28, 7), 8)) + (ROUND(P20,4) > INDEX('Tabela de ingredientes'!$O$1:$V$30, SWITCH(B20, "Gelatos de Leite", 8, "Sorbets", 11, "Gelatos de Leite com Fruta", 14, "Chocolate base água", 17, "Vegano", 20, "Alcoólicos", 23, "Zero", 26, "Gelatos Proteicos", 29, 8), 8)) + IF(B20="Gelatos Proteicos", (ROUND(Q20,4)<'Tabela de ingredientes'!$W$28)+(ROUND(Q20,4)>'Tabela de ingredientes'!$W$29), 0) = 0, "Ok", "Revisar"))} -> Ok
A21: =IFERROR(__xludf.DUMMYFUNCTION("""COMPUTED_VALUE"""),"Nesquik (Direto ao Ponto)") -> Nesquik (Direto ao Ponto) | B21: Gelatos de Leite | C21: 8 | D21: 1001 | E21: Diferente (1001 g) | F21: 14.077423 | G21: 0.84464535 | H21: 34.004489 | I21: 0.13491508 | J21: 0.066133866 | K21: 0.10814186 | L21: 0.024175824 | M21: 0.33336663 | N21: 0.66663337 | O21: 127.17083 | P21: 199.3007 | Q21: 0.044195804 | R21: 7.972028 | S21: {=IF(A21="","", IF( (ROUND(I21,4) < INDEX('Tabela de ingredientes'!$O$1:$V$30, SWITCH(B21, "Gelatos de Leite", 7, "Sorbets", 10, "Gelatos de Leite com Fruta", 13, "Chocolate base água", 16, "Vegano", 19, "Alcoólicos", 22, "Zero", 25, "Gelatos Proteicos", 28, 7), 1)) + (ROUND(I21,4) > INDEX('Tabela de ingredientes'!$O$1:$V$30, SWITCH(B21, "Gelatos de Leite", 8, "Sorbets", 11, "Gelatos de Leite com Fruta", 14, "Chocolate base água", 17, "Vegano", 20, "Alcoólicos", 23, "Zero", 26, "Gelatos Proteicos", 29, 8), 1)) + (ROUND(J21,4) < INDEX('Tabela de ingredientes'!$O$1:$V$30, SWITCH(B21, "Gelatos de Leite", 7, "Sorbets", 10, "Gelatos de Leite com Fruta", 13, "Chocolate base água", 16, "Vegano", 19, "Alcoólicos", 22, "Zero", 25, "Gelatos Proteicos", 28, 7), 2)) + (ROUND(J21,4) > INDEX('Tabela de ingredientes'!$O$1:$V$30, SWITCH(B21, "Gelatos de Leite", 8, "Sorbets", 11, "Gelatos de Leite com Fruta", 14, "Chocolate base água", 17, "Vegano", 20, "Alcoólicos", 23, "Zero", 26, "Gelatos Proteicos", 29, 8), 2)) + (ROUND(K21,4) < INDEX('Tabela de ingredientes'!$O$1:$V$30, SWITCH(B21, "Gelatos de Leite", 7, "Sorbets", 10, "Gelatos de Leite com Fruta", 13, "Chocolate base água", 16, "Vegano", 19, "Alcoólicos", 22, "Zero", 25, "Gelatos Proteicos", 28, 7), 3)) + (ROUND(K21,4) > INDEX('Tabela de ingredientes'!$O$1:$V$30, SWITCH(B21, "Gelatos de Leite", 8, "Sorbets", 11, "Gelatos de Leite com Fruta", 14, "Chocolate base água", 17, "Vegano", 20, "Alcoólicos", 23, "Zero", 26, "Gelatos Proteicos", 29, 8), 3)) + (ROUND(L21,4) < INDEX('Tabela de ingredientes'!$O$1:$V$30, SWITCH(B21, "Gelatos de Leite", 7, "Sorbets", 10, "Gelatos de Leite com Fruta", 13, "Chocolate base água", 16, "Vegano", 19, "Alcoólicos", 22, "Zero", 25, "Gelatos Proteicos", 28, 7), 4)) + (ROUND(L21,4) > INDEX('Tabela de ingredientes'!$O$1:$V$30, SWITCH(B21, "Gelatos de Leite", 8, "Sorbets", 11, "Gelatos de Leite com Fruta", 14, "Chocolate base água", 17, "Vegano", 20, "Alcoólicos", 23, "Zero", 26, "Gelatos Proteicos", 29, 8), 4)) + (ROUND(M21,4) < INDEX('Tabela de ingredientes'!$O$1:$V$30, SWITCH(B21, "Gelatos de Leite", 7, "Sorbets", 10, "Gelatos de Leite com Fruta", 13, "Chocolate base água", 16, "Vegano", 19, "Alcoólicos", 22, "Zero", 25, "Gelatos Proteicos", 28, 7), 5)) + (ROUND(M21,4) > INDEX('Tabela de ingredientes'!$O$1:$V$30, SWITCH(B21, "Gelatos de Leite", 8, "Sorbets", 11, "Gelatos de Leite com Fruta", 14, "Chocolate base água", 17, "Vegano", 20, "Alcoólicos", 23, "Zero", 26, "Gelatos Proteicos", 29, 8), 5)) + (ROUND(N21,4) < INDEX('Tabela de ingredientes'!$O$1:$V$30, SWITCH(B21, "Gelatos de Leite", 7, "Sorbets", 10, "Gelatos de Leite com Fruta", 13, "Chocolate base água", 16, "Vegano", 19, "Alcoólicos", 22, "Zero", 25, "Gelatos Proteicos", 28, 7), 6)) + (ROUND(N21,4) > INDEX('Tabela de ingredientes'!$O$1:$V$30, SWITCH(B21, "Gelatos de Leite", 8, "Sorbets", 11, "Gelatos de Leite com Fruta", 14, "Chocolate base água", 17, "Vegano", 20, "Alcoólicos", 23, "Zero", 26, "Gelatos Proteicos", 29, 8), 6)) + (ROUND(O21,4) < INDEX('Tabela de ingredientes'!$O$1:$V$30, SWITCH(B21, "Gelatos de Leite", 7, "Sorbets", 10, "Gelatos de Leite com Fruta", 13, "Chocolate base água", 16, "Vegano", 19, "Alcoólicos", 22, "Zero", 25, "Gelatos Proteicos", 28, 7), 7)) + (ROUND(O21,4) > INDEX('Tabela de ingredientes'!$O$1:$V$30, SWITCH(B21, "Gelatos de Leite", 8, "Sorbets", 11, "Gelatos de Leite com Fruta", 14, "Chocolate base água", 17, "Vegano", 20, "Alcoólicos", 23, "Zero", 26, "Gelatos Proteicos", 29, 8), 7)) + (ROUND(P21,4) < INDEX('Tabela de ingredientes'!$O$1:$V$30, SWITCH(B21, "Gelatos de Leite", 7, "Sorbets", 10, "Gelatos de Leite com Fruta", 13, "Chocolate base água", 16, "Vegano", 19, "Alcoólicos", 22, "Zero", 25, "Gelatos Proteicos", 28, 7), 8)) + (ROUND(P21,4) > INDEX('Tabela de ingredientes'!$O$1:$V$30, SWITCH(B21, "Gelatos de Leite", 8, "Sorbets", 11, "Gelatos de Leite com Fruta", 14, "Chocolate base água", 17, "Vegano", 20, "Alcoólicos", 23, "Zero", 26, "Gelatos Proteicos", 29, 8), 8)) + IF(B21="Gelatos Proteicos", (ROUND(Q21,4)<'Tabela de ingredientes'!$W$28)+(ROUND(Q21,4)>'Tabela de ingredientes'!$W$29), 0) = 0, "Ok", "Revisar"))} -> Revisar
A22: =IFERROR(__xludf.DUMMYFUNCTION("""COMPUTED_VALUE"""),"Cream Cheese (Direto ao Ponto)") -> Cream Cheese (Direto ao Ponto) | B22: Gelatos de Leite | C22: 8 | D22: 1001 | E22: Diferente (1001 g) | F22: 19.466034 | G22: 1.167962 | H22: 38.46526 | I22: 0.16663337 | J22: 0.095604396 | K22: 0.10564436 | L22: 0.0071928072 | M22: 0.37507493 | N22: 0.62492507 | O22: 165.59041 | P22: 247.69231 | Q22: 0.052247752 | R22: 9.9076923 | S22: {=IF(A22="","", IF( (ROUND(I22,4) < INDEX('Tabela de ingredientes'!$O$1:$V$30, SWITCH(B22, "Gelatos de Leite", 7, "Sorbets", 10, "Gelatos de Leite com Fruta", 13, "Chocolate base água", 16, "Vegano", 19, "Alcoólicos", 22, "Zero", 25, "Gelatos Proteicos", 28, 7), 1)) + (ROUND(I22,4) > INDEX('Tabela de ingredientes'!$O$1:$V$30, SWITCH(B22, "Gelatos de Leite", 8, "Sorbets", 11, "Gelatos de Leite com Fruta", 14, "Chocolate base água", 17, "Vegano", 20, "Alcoólicos", 23, "Zero", 26, "Gelatos Proteicos", 29, 8), 1)) + (ROUND(J22,4) < INDEX('Tabela de ingredientes'!$O$1:$V$30, SWITCH(B22, "Gelatos de Leite", 7, "Sorbets", 10, "Gelatos de Leite com Fruta", 13, "Chocolate base água", 16, "Vegano", 19, "Alcoólicos", 22, "Zero", 25, "Gelatos Proteicos", 28, 7), 2)) + (ROUND(J22,4) > INDEX('Tabela de ingredientes'!$O$1:$V$30, SWITCH(B22, "Gelatos de Leite", 8, "Sorbets", 11, "Gelatos de Leite com Fruta", 14, "Chocolate base água", 17, "Vegano", 20, "Alcoólicos", 23, "Zero", 26, "Gelatos Proteicos", 29, 8), 2)) + (ROUND(K22,4) < INDEX('Tabela de ingredientes'!$O$1:$V$30, SWITCH(B22, "Gelatos de Leite", 7, "Sorbets", 10, "Gelatos de Leite com Fruta", 13, "Chocolate base água", 16, "Vegano", 19, "Alcoólicos", 22, "Zero", 25, "Gelatos Proteicos", 28, 7), 3)) + (ROUND(K22,4) > INDEX('Tabela de ingredientes'!$O$1:$V$30, SWITCH(B22, "Gelatos de Leite", 8, "Sorbets", 11, "Gelatos de Leite com Fruta", 14, "Chocolate base água", 17, "Vegano", 20, "Alcoólicos", 23, "Zero", 26, "Gelatos Proteicos", 29, 8), 3)) + (ROUND(L22,4) < INDEX('Tabela de ingredientes'!$O$1:$V$30, SWITCH(B22, "Gelatos de Leite", 7, "Sorbets", 10, "Gelatos de Leite com Fruta", 13, "Chocolate base água", 16, "Vegano", 19, "Alcoólicos", 22, "Zero", 25, "Gelatos Proteicos", 28, 7), 4)) + (ROUND(L22,4) > INDEX('Tabela de ingredientes'!$O$1:$V$30, SWITCH(B22, "Gelatos de Leite", 8, "Sorbets", 11, "Gelatos de Leite com Fruta", 14, "Chocolate base água", 17, "Vegano", 20, "Alcoólicos", 23, "Zero", 26, "Gelatos Proteicos", 29, 8), 4)) + (ROUND(M22,4) < INDEX('Tabela de ingredientes'!$O$1:$V$30, SWITCH(B22, "Gelatos de Leite", 7, "Sorbets", 10, "Gelatos de Leite com Fruta", 13, "Chocolate base água", 16, "Vegano", 19, "Alcoólicos", 22, "Zero", 25, "Gelatos Proteicos", 28, 7), 5)) + (ROUND(M22,4) > INDEX('Tabela de ingredientes'!$O$1:$V$30, SWITCH(B22, "Gelatos de Leite", 8, "Sorbets", 11, "Gelatos de Leite com Fruta", 14, "Chocolate base água", 17, "Vegano", 20, "Alcoólicos", 23, "Zero", 26, "Gelatos Proteicos", 29, 8), 5)) + (ROUND(N22,4) < INDEX('Tabela de ingredientes'!$O$1:$V$30, SWITCH(B22, "Gelatos de Leite", 7, "Sorbets", 10, "Gelatos de Leite com Fruta", 13, "Chocolate base água", 16, "Vegano", 19, "Alcoólicos", 22, "Zero", 25, "Gelatos Proteicos", 28, 7), 6)) + (ROUND(N22,4) > INDEX('Tabela de ingredientes'!$O$1:$V$30, SWITCH(B22, "Gelatos de Leite", 8, "Sorbets", 11, "Gelatos de Leite com Fruta", 14, "Chocolate base água", 17, "Vegano", 20, "Alcoólicos", 23, "Zero", 26, "Gelatos Proteicos", 29, 8), 6)) + (ROUND(O22,4) < INDEX('Tabela de ingredientes'!$O$1:$V$30, SWITCH(B22, "Gelatos de Leite", 7, "Sorbets", 10, "Gelatos de Leite com Fruta", 13, "Chocolate base água", 16, "Vegano", 19, "Alcoólicos", 22, "Zero", 25, "Gelatos Proteicos", 28, 7), 7)) + (ROUND(O22,4) > INDEX('Tabela de ingredientes'!$O$1:$V$30, SWITCH(B22, "Gelatos de Leite", 8, "Sorbets", 11, "Gelatos de Leite com Fruta", 14, "Chocolate base água", 17, "Vegano", 20, "Alcoólicos", 23, "Zero", 26, "Gelatos Proteicos", 29, 8), 7)) + (ROUND(P22,4) < INDEX('Tabela de ingredientes'!$O$1:$V$30, SWITCH(B22, "Gelatos de Leite", 7, "Sorbets", 10, "Gelatos de Leite com Fruta", 13, "Chocolate base água", 16, "Vegano", 19, "Alcoólicos", 22, "Zero", 25, "Gelatos Proteicos", 28, 7), 8)) + (ROUND(P22,4) > INDEX('Tabela de ingredientes'!$O$1:$V$30, SWITCH(B22, "Gelatos de Leite", 8, "Sorbets", 11, "Gelatos de Leite com Fruta", 14, "Chocolate base água", 17, "Vegano", 20, "Alcoólicos", 23, "Zero", 26, "Gelatos Proteicos", 29, 8), 8)) + IF(B22="Gelatos Proteicos", (ROUND(Q22,4)<'Tabela de ingredientes'!$W$28)+(ROUND(Q22,4)>'Tabela de ingredientes'!$W$29), 0) = 0, "Ok", "Revisar"))} -> Ok
A23: =IFERROR(__xludf.DUMMYFUNCTION("""COMPUTED_VALUE"""),"Parmesão (Direto ao Ponto)") -> Parmesão (Direto ao Ponto) | B23: Gelatos de Leite | C23: 8 | D23: 997 | E23: Diferente (997 g) | F23: 26.384152 | G23: 1.5830491 | H23: 44.192179 | I23: 0.17111334 | J23: 0.081544634 | K23: 0.14658977 | L23: 0.0070210632 | M23: 0.40626881 | N23: 0.59373119 | O23: 168.8004 | P23: 268.00401 | Q23: 0.08776329 | R23: 10.72016 | S23: {=IF(A23="","", IF( (ROUND(I23,4) < INDEX('Tabela de ingredientes'!$O$1:$V$30, SWITCH(B23, "Gelatos de Leite", 7, "Sorbets", 10, "Gelatos de Leite com Fruta", 13, "Chocolate base água", 16, "Vegano", 19, "Alcoólicos", 22, "Zero", 25, "Gelatos Proteicos", 28, 7), 1)) + (ROUND(I23,4) > INDEX('Tabela de ingredientes'!$O$1:$V$30, SWITCH(B23, "Gelatos de Leite", 8, "Sorbets", 11, "Gelatos de Leite com Fruta", 14, "Chocolate base água", 17, "Vegano", 20, "Alcoólicos", 23, "Zero", 26, "Gelatos Proteicos", 29, 8), 1)) + (ROUND(J23,4) < INDEX('Tabela de ingredientes'!$O$1:$V$30, SWITCH(B23, "Gelatos de Leite", 7, "Sorbets", 10, "Gelatos de Leite com Fruta", 13, "Chocolate base água", 16, "Vegano", 19, "Alcoólicos", 22, "Zero", 25, "Gelatos Proteicos", 28, 7), 2)) + (ROUND(J23,4) > INDEX('Tabela de ingredientes'!$O$1:$V$30, SWITCH(B23, "Gelatos de Leite", 8, "Sorbets", 11, "Gelatos de Leite com Fruta", 14, "Chocolate base água", 17, "Vegano", 20, "Alcoólicos", 23, "Zero", 26, "Gelatos Proteicos", 29, 8), 2)) + (ROUND(K23,4) < INDEX('Tabela de ingredientes'!$O$1:$V$30, SWITCH(B23, "Gelatos de Leite", 7, "Sorbets", 10, "Gelatos de Leite com Fruta", 13, "Chocolate base água", 16, "Vegano", 19, "Alcoólicos", 22, "Zero", 25, "Gelatos Proteicos", 28, 7), 3)) + (ROUND(K23,4) > INDEX('Tabela de ingredientes'!$O$1:$V$30, SWITCH(B23, "Gelatos de Leite", 8, "Sorbets", 11, "Gelatos de Leite com Fruta", 14, "Chocolate base água", 17, "Vegano", 20, "Alcoólicos", 23, "Zero", 26, "Gelatos Proteicos", 29, 8), 3)) + (ROUND(L23,4) < INDEX('Tabela de ingredientes'!$O$1:$V$30, SWITCH(B23, "Gelatos de Leite", 7, "Sorbets", 10, "Gelatos de Leite com Fruta", 13, "Chocolate base água", 16, "Vegano", 19, "Alcoólicos", 22, "Zero", 25, "Gelatos Proteicos", 28, 7), 4)) + (ROUND(L23,4) > INDEX('Tabela de ingredientes'!$O$1:$V$30, SWITCH(B23, "Gelatos de Leite", 8, "Sorbets", 11, "Gelatos de Leite com Fruta", 14, "Chocolate base água", 17, "Vegano", 20, "Alcoólicos", 23, "Zero", 26, "Gelatos Proteicos", 29, 8), 4)) + (ROUND(M23,4) < INDEX('Tabela de ingredientes'!$O$1:$V$30, SWITCH(B23, "Gelatos de Leite", 7, "Sorbets", 10, "Gelatos de Leite com Fruta", 13, "Chocolate base água", 16, "Vegano", 19, "Alcoólicos", 22, "Zero", 25, "Gelatos Proteicos", 28, 7), 5)) + (ROUND(M23,4) > INDEX('Tabela de ingredientes'!$O$1:$V$30, SWITCH(B23, "Gelatos de Leite", 8, "Sorbets", 11, "Gelatos de Leite com Fruta", 14, "Chocolate base água", 17, "Vegano", 20, "Alcoólicos", 23, "Zero", 26, "Gelatos Proteicos", 29, 8), 5)) + (ROUND(N23,4) < INDEX('Tabela de ingredientes'!$O$1:$V$30, SWITCH(B23, "Gelatos de Leite", 7, "Sorbets", 10, "Gelatos de Leite com Fruta", 13, "Chocolate base água", 16, "Vegano", 19, "Alcoólicos", 22, "Zero", 25, "Gelatos Proteicos", 28, 7), 6)) + (ROUND(N23,4) > INDEX('Tabela de ingredientes'!$O$1:$V$30, SWITCH(B23, "Gelatos de Leite", 8, "Sorbets", 11, "Gelatos de Leite com Fruta", 14, "Chocolate base água", 17, "Vegano", 20, "Alcoólicos", 23, "Zero", 26, "Gelatos Proteicos", 29, 8), 6)) + (ROUND(O23,4) < INDEX('Tabela de ingredientes'!$O$1:$V$30, SWITCH(B23, "Gelatos de Leite", 7, "Sorbets", 10, "Gelatos de Leite com Fruta", 13, "Chocolate base água", 16, "Vegano", 19, "Alcoólicos", 22, "Zero", 25, "Gelatos Proteicos", 28, 7), 7)) + (ROUND(O23,4) > INDEX('Tabela de ingredientes'!$O$1:$V$30, SWITCH(B23, "Gelatos de Leite", 8, "Sorbets", 11, "Gelatos de Leite com Fruta", 14, "Chocolate base água", 17, "Vegano", 20, "Alcoólicos", 23, "Zero", 26, "Gelatos Proteicos", 29, 8), 7)) + (ROUND(P23,4) < INDEX('Tabela de ingredientes'!$O$1:$V$30, SWITCH(B23, "Gelatos de Leite", 7, "Sorbets", 10, "Gelatos de Leite com Fruta", 13, "Chocolate base água", 16, "Vegano", 19, "Alcoólicos", 22, "Zero", 25, "Gelatos Proteicos", 28, 7), 8)) + (ROUND(P23,4) > INDEX('Tabela de ingredientes'!$O$1:$V$30, SWITCH(B23, "Gelatos de Leite", 8, "Sorbets", 11, "Gelatos de Leite com Fruta", 14, "Chocolate base água", 17, "Vegano", 20, "Alcoólicos", 23, "Zero", 26, "Gelatos Proteicos", 29, 8), 8)) + IF(B23="Gelatos Proteicos", (ROUND(Q23,4)<'Tabela de ingredientes'!$W$28)+(ROUND(Q23,4)>'Tabela de ingredientes'!$W$29), 0) = 0, "Ok", "Revisar"))} -> Revisar
A24: =IFERROR(__xludf.DUMMYFUNCTION("""COMPUTED_VALUE"""),"Gorgonzola (Direto ao Ponto)") -> Gorgonzola (Direto ao Ponto) | B24: Gelatos de Leite | C24: 7 | D24: 996 | E24: Diferente (996 g) | F24: 25.90512 | G24: 1.5543072 | H24: 43.79563 | I24: 0.17128514 | J24: 0.084638554 | K24: 0.12866466 | L24: 0.010040161 | M24: 0.39462851 | N24: 0.60537149 | O24: 168.6988 | P24: 273.79518 | Q24: 0.075200803 | R24: 10.951807 | S24: {=IF(A24="","", IF( (ROUND(I24,4) < INDEX('Tabela de ingredientes'!$O$1:$V$30, SWITCH(B24, "Gelatos de Leite", 7, "Sorbets", 10, "Gelatos de Leite com Fruta", 13, "Chocolate base água", 16, "Vegano", 19, "Alcoólicos", 22, "Zero", 25, "Gelatos Proteicos", 28, 7), 1)) + (ROUND(I24,4) > INDEX('Tabela de ingredientes'!$O$1:$V$30, SWITCH(B24, "Gelatos de Leite", 8, "Sorbets", 11, "Gelatos de Leite com Fruta", 14, "Chocolate base água", 17, "Vegano", 20, "Alcoólicos", 23, "Zero", 26, "Gelatos Proteicos", 29, 8), 1)) + (ROUND(J24,4) < INDEX('Tabela de ingredientes'!$O$1:$V$30, SWITCH(B24, "Gelatos de Leite", 7, "Sorbets", 10, "Gelatos de Leite com Fruta", 13, "Chocolate base água", 16, "Vegano", 19, "Alcoólicos", 22, "Zero", 25, "Gelatos Proteicos", 28, 7), 2)) + (ROUND(J24,4) > INDEX('Tabela de ingredientes'!$O$1:$V$30, SWITCH(B24, "Gelatos de Leite", 8, "Sorbets", 11, "Gelatos de Leite com Fruta", 14, "Chocolate base água", 17, "Vegano", 20, "Alcoólicos", 23, "Zero", 26, "Gelatos Proteicos", 29, 8), 2)) + (ROUND(K24,4) < INDEX('Tabela de ingredientes'!$O$1:$V$30, SWITCH(B24, "Gelatos de Leite", 7, "Sorbets", 10, "Gelatos de Leite com Fruta", 13, "Chocolate base água", 16, "Vegano", 19, "Alcoólicos", 22, "Zero", 25, "Gelatos Proteicos", 28, 7), 3)) + (ROUND(K24,4) > INDEX('Tabela de ingredientes'!$O$1:$V$30, SWITCH(B24, "Gelatos de Leite", 8, "Sorbets", 11, "Gelatos de Leite com Fruta", 14, "Chocolate base água", 17, "Vegano", 20, "Alcoólicos", 23, "Zero", 26, "Gelatos Proteicos", 29, 8), 3)) + (ROUND(L24,4) < INDEX('Tabela de ingredientes'!$O$1:$V$30, SWITCH(B24, "Gelatos de Leite", 7, "Sorbets", 10, "Gelatos de Leite com Fruta", 13, "Chocolate base água", 16, "Vegano", 19, "Alcoólicos", 22, "Zero", 25, "Gelatos Proteicos", 28, 7), 4)) + (ROUND(L24,4) > INDEX('Tabela de ingredientes'!$O$1:$V$30, SWITCH(B24, "Gelatos de Leite", 8, "Sorbets", 11, "Gelatos de Leite com Fruta", 14, "Chocolate base água", 17, "Vegano", 20, "Alcoólicos", 23, "Zero", 26, "Gelatos Proteicos", 29, 8), 4)) + (ROUND(M24,4) < INDEX('Tabela de ingredientes'!$O$1:$V$30, SWITCH(B24, "Gelatos de Leite", 7, "Sorbets", 10, "Gelatos de Leite com Fruta", 13, "Chocolate base água", 16, "Vegano", 19, "Alcoólicos", 22, "Zero", 25, "Gelatos Proteicos", 28, 7), 5)) + (ROUND(M24,4) > INDEX('Tabela de ingredientes'!$O$1:$V$30, SWITCH(B24, "Gelatos de Leite", 8, "Sorbets", 11, "Gelatos de Leite com Fruta", 14, "Chocolate base água", 17, "Vegano", 20, "Alcoólicos", 23, "Zero", 26, "Gelatos Proteicos", 29, 8), 5)) + (ROUND(N24,4) < INDEX('Tabela de ingredientes'!$O$1:$V$30, SWITCH(B24, "Gelatos de Leite", 7, "Sorbets", 10, "Gelatos de Leite com Fruta", 13, "Chocolate base água", 16, "Vegano", 19, "Alcoólicos", 22, "Zero", 25, "Gelatos Proteicos", 28, 7), 6)) + (ROUND(N24,4) > INDEX('Tabela de ingredientes'!$O$1:$V$30, SWITCH(B24, "Gelatos de Leite", 8, "Sorbets", 11, "Gelatos de Leite com Fruta", 14, "Chocolate base água", 17, "Vegano", 20, "Alcoólicos", 23, "Zero", 26, "Gelatos Proteicos", 29, 8), 6)) + (ROUND(O24,4) < INDEX('Tabela de ingredientes'!$O$1:$V$30, SWITCH(B24, "Gelatos de Leite", 7, "Sorbets", 10, "Gelatos de Leite com Fruta", 13, "Chocolate base água", 16, "Vegano", 19, "Alcoólicos", 22, "Zero", 25, "Gelatos Proteicos", 28, 7), 7)) + (ROUND(O24,4) > INDEX('Tabela de ingredientes'!$O$1:$V$30, SWITCH(B24, "Gelatos de Leite", 8, "Sorbets", 11, "Gelatos de Leite com Fruta", 14, "Chocolate base água", 17, "Vegano", 20, "Alcoólicos", 23, "Zero", 26, "Gelatos Proteicos", 29, 8), 7)) + (ROUND(P24,4) < INDEX('Tabela de ingredientes'!$O$1:$V$30, SWITCH(B24, "Gelatos de Leite", 7, "Sorbets", 10, "Gelatos de Leite com Fruta", 13, "Chocolate base água", 16, "Vegano", 19, "Alcoólicos", 22, "Zero", 25, "Gelatos Proteicos", 28, 7), 8)) + (ROUND(P24,4) > INDEX('Tabela de ingredientes'!$O$1:$V$30, SWITCH(B24, "Gelatos de Leite", 8, "Sorbets", 11, "Gelatos de Leite com Fruta", 14, "Chocolate base água", 17, "Vegano", 20, "Alcoólicos", 23, "Zero", 26, "Gelatos Proteicos", 29, 8), 8)) + IF(B24="Gelatos Proteicos", (ROUND(Q24,4)<'Tabela de ingredientes'!$W$28)+(ROUND(Q24,4)>'Tabela de ingredientes'!$W$29), 0) = 0, "Ok", "Revisar"))} -> Revisar
A25: =IFERROR(__xludf.DUMMYFUNCTION("""COMPUTED_VALUE"""),"Chocolate Branco Assado com Missô (Direto ao Ponto)") -> Chocolate Branco Assado com Missô (Direto ao Ponto) | B25: Gelatos de Leite | C25: 8 | D25: 1000 | E25: 1.000 g (Padrão) | F25: 35.075 | G25: 2.1045 | H25: 51.386589 | I25: 0.18655 | J25: 0.057425 | K25: 0.11385 | L25: 0.0324 | M25: 0.390225 | N25: 0.609775 | O25: 182.365 | P25: 269.5 | Q25: 0.044425 | R25: 10.78 | S25: {=IF(A25="","", IF( (ROUND(I25,4) < INDEX('Tabela de ingredientes'!$O$1:$V$30, SWITCH(B25, "Gelatos de Leite", 7, "Sorbets", 10, "Gelatos de Leite com Fruta", 13, "Chocolate base água", 16, "Vegano", 19, "Alcoólicos", 22, "Zero", 25, "Gelatos Proteicos", 28, 7), 1)) + (ROUND(I25,4) > INDEX('Tabela de ingredientes'!$O$1:$V$30, SWITCH(B25, "Gelatos de Leite", 8, "Sorbets", 11, "Gelatos de Leite com Fruta", 14, "Chocolate base água", 17, "Vegano", 20, "Alcoólicos", 23, "Zero", 26, "Gelatos Proteicos", 29, 8), 1)) + (ROUND(J25,4) < INDEX('Tabela de ingredientes'!$O$1:$V$30, SWITCH(B25, "Gelatos de Leite", 7, "Sorbets", 10, "Gelatos de Leite com Fruta", 13, "Chocolate base água", 16, "Vegano", 19, "Alcoólicos", 22, "Zero", 25, "Gelatos Proteicos", 28, 7), 2)) + (ROUND(J25,4) > INDEX('Tabela de ingredientes'!$O$1:$V$30, SWITCH(B25, "Gelatos de Leite", 8, "Sorbets", 11, "Gelatos de Leite com Fruta", 14, "Chocolate base água", 17, "Vegano", 20, "Alcoólicos", 23, "Zero", 26, "Gelatos Proteicos", 29, 8), 2)) + (ROUND(K25,4) < INDEX('Tabela de ingredientes'!$O$1:$V$30, SWITCH(B25, "Gelatos de Leite", 7, "Sorbets", 10, "Gelatos de Leite com Fruta", 13, "Chocolate base água", 16, "Vegano", 19, "Alcoólicos", 22, "Zero", 25, "Gelatos Proteicos", 28, 7), 3)) + (ROUND(K25,4) > INDEX('Tabela de ingredientes'!$O$1:$V$30, SWITCH(B25, "Gelatos de Leite", 8, "Sorbets", 11, "Gelatos de Leite com Fruta", 14, "Chocolate base água", 17, "Vegano", 20, "Alcoólicos", 23, "Zero", 26, "Gelatos Proteicos", 29, 8), 3)) + (ROUND(L25,4) < INDEX('Tabela de ingredientes'!$O$1:$V$30, SWITCH(B25, "Gelatos de Leite", 7, "Sorbets", 10, "Gelatos de Leite com Fruta", 13, "Chocolate base água", 16, "Vegano", 19, "Alcoólicos", 22, "Zero", 25, "Gelatos Proteicos", 28, 7), 4)) + (ROUND(L25,4) > INDEX('Tabela de ingredientes'!$O$1:$V$30, SWITCH(B25, "Gelatos de Leite", 8, "Sorbets", 11, "Gelatos de Leite com Fruta", 14, "Chocolate base água", 17, "Vegano", 20, "Alcoólicos", 23, "Zero", 26, "Gelatos Proteicos", 29, 8), 4)) + (ROUND(M25,4) < INDEX('Tabela de ingredientes'!$O$1:$V$30, SWITCH(B25, "Gelatos de Leite", 7, "Sorbets", 10, "Gelatos de Leite com Fruta", 13, "Chocolate base água", 16, "Vegano", 19, "Alcoólicos", 22, "Zero", 25, "Gelatos Proteicos", 28, 7), 5)) + (ROUND(M25,4) > INDEX('Tabela de ingredientes'!$O$1:$V$30, SWITCH(B25, "Gelatos de Leite", 8, "Sorbets", 11, "Gelatos de Leite com Fruta", 14, "Chocolate base água", 17, "Vegano", 20, "Alcoólicos", 23, "Zero", 26, "Gelatos Proteicos", 29, 8), 5)) + (ROUND(N25,4) < INDEX('Tabela de ingredientes'!$O$1:$V$30, SWITCH(B25, "Gelatos de Leite", 7, "Sorbets", 10, "Gelatos de Leite com Fruta", 13, "Chocolate base água", 16, "Vegano", 19, "Alcoólicos", 22, "Zero", 25, "Gelatos Proteicos", 28, 7), 6)) + (ROUND(N25,4) > INDEX('Tabela de ingredientes'!$O$1:$V$30, SWITCH(B25, "Gelatos de Leite", 8, "Sorbets", 11, "Gelatos de Leite com Fruta", 14, "Chocolate base água", 17, "Vegano", 20, "Alcoólicos", 23, "Zero", 26, "Gelatos Proteicos", 29, 8), 6)) + (ROUND(O25,4) < INDEX('Tabela de ingredientes'!$O$1:$V$30, SWITCH(B25, "Gelatos de Leite", 7, "Sorbets", 10, "Gelatos de Leite com Fruta", 13, "Chocolate base água", 16, "Vegano", 19, "Alcoólicos", 22, "Zero", 25, "Gelatos Proteicos", 28, 7), 7)) + (ROUND(O25,4) > INDEX('Tabela de ingredientes'!$O$1:$V$30, SWITCH(B25, "Gelatos de Leite", 8, "Sorbets", 11, "Gelatos de Leite com Fruta", 14, "Chocolate base água", 17, "Vegano", 20, "Alcoólicos", 23, "Zero", 26, "Gelatos Proteicos", 29, 8), 7)) + (ROUND(P25,4) < INDEX('Tabela de ingredientes'!$O$1:$V$30, SWITCH(B25, "Gelatos de Leite", 7, "Sorbets", 10, "Gelatos de Leite com Fruta", 13, "Chocolate base água", 16, "Vegano", 19, "Alcoólicos", 22, "Zero", 25, "Gelatos Proteicos", 28, 7), 8)) + (ROUND(P25,4) > INDEX('Tabela de ingredientes'!$O$1:$V$30, SWITCH(B25, "Gelatos de Leite", 8, "Sorbets", 11, "Gelatos de Leite com Fruta", 14, "Chocolate base água", 17, "Vegano", 20, "Alcoólicos", 23, "Zero", 26, "Gelatos Proteicos", 29, 8), 8)) + IF(B25="Gelatos Proteicos", (ROUND(Q25,4)<'Tabela de ingredientes'!$W$28)+(ROUND(Q25,4)>'Tabela de ingredientes'!$W$29), 0) = 0, "Ok", "Revisar"))} -> Ok
A26: =IFERROR(__xludf.DUMMYFUNCTION("""COMPUTED_VALUE"""),"Iogurte (Direto ao Ponto)") -> Iogurte (Direto ao Ponto) | B26: Gelatos de Leite | C26: 9 | D26: 1006 | E26: Diferente (1006 g) | F26: 10.048211 | G26: 0.60289264 | H26: 30.669049 | I26: 0.17415507 | J26: 0.053399602 | K26: 0.10173956 | L26: 0.029572565 | M26: 0.3588668 | N26: 0.6411332 | O26: 171.61829 | P26: 283.79722 | Q26: 0.043817097 | R26: 11.351889 | S26: {=IF(A26="","", IF( (ROUND(I26,4) < INDEX('Tabela de ingredientes'!$O$1:$V$30, SWITCH(B26, "Gelatos de Leite", 7, "Sorbets", 10, "Gelatos de Leite com Fruta", 13, "Chocolate base água", 16, "Vegano", 19, "Alcoólicos", 22, "Zero", 25, "Gelatos Proteicos", 28, 7), 1)) + (ROUND(I26,4) > INDEX('Tabela de ingredientes'!$O$1:$V$30, SWITCH(B26, "Gelatos de Leite", 8, "Sorbets", 11, "Gelatos de Leite com Fruta", 14, "Chocolate base água", 17, "Vegano", 20, "Alcoólicos", 23, "Zero", 26, "Gelatos Proteicos", 29, 8), 1)) + (ROUND(J26,4) < INDEX('Tabela de ingredientes'!$O$1:$V$30, SWITCH(B26, "Gelatos de Leite", 7, "Sorbets", 10, "Gelatos de Leite com Fruta", 13, "Chocolate base água", 16, "Vegano", 19, "Alcoólicos", 22, "Zero", 25, "Gelatos Proteicos", 28, 7), 2)) + (ROUND(J26,4) > INDEX('Tabela de ingredientes'!$O$1:$V$30, SWITCH(B26, "Gelatos de Leite", 8, "Sorbets", 11, "Gelatos de Leite com Fruta", 14, "Chocolate base água", 17, "Vegano", 20, "Alcoólicos", 23, "Zero", 26, "Gelatos Proteicos", 29, 8), 2)) + (ROUND(K26,4) < INDEX('Tabela de ingredientes'!$O$1:$V$30, SWITCH(B26, "Gelatos de Leite", 7, "Sorbets", 10, "Gelatos de Leite com Fruta", 13, "Chocolate base água", 16, "Vegano", 19, "Alcoólicos", 22, "Zero", 25, "Gelatos Proteicos", 28, 7), 3)) + (ROUND(K26,4) > INDEX('Tabela de ingredientes'!$O$1:$V$30, SWITCH(B26, "Gelatos de Leite", 8, "Sorbets", 11, "Gelatos de Leite com Fruta", 14, "Chocolate base água", 17, "Vegano", 20, "Alcoólicos", 23, "Zero", 26, "Gelatos Proteicos", 29, 8), 3)) + (ROUND(L26,4) < INDEX('Tabela de ingredientes'!$O$1:$V$30, SWITCH(B26, "Gelatos de Leite", 7, "Sorbets", 10, "Gelatos de Leite com Fruta", 13, "Chocolate base água", 16, "Vegano", 19, "Alcoólicos", 22, "Zero", 25, "Gelatos Proteicos", 28, 7), 4)) + (ROUND(L26,4) > INDEX('Tabela de ingredientes'!$O$1:$V$30, SWITCH(B26, "Gelatos de Leite", 8, "Sorbets", 11, "Gelatos de Leite com Fruta", 14, "Chocolate base água", 17, "Vegano", 20, "Alcoólicos", 23, "Zero", 26, "Gelatos Proteicos", 29, 8), 4)) + (ROUND(M26,4) < INDEX('Tabela de ingredientes'!$O$1:$V$30, SWITCH(B26, "Gelatos de Leite", 7, "Sorbets", 10, "Gelatos de Leite com Fruta", 13, "Chocolate base água", 16, "Vegano", 19, "Alcoólicos", 22, "Zero", 25, "Gelatos Proteicos", 28, 7), 5)) + (ROUND(M26,4) > INDEX('Tabela de ingredientes'!$O$1:$V$30, SWITCH(B26, "Gelatos de Leite", 8, "Sorbets", 11, "Gelatos de Leite com Fruta", 14, "Chocolate base água", 17, "Vegano", 20, "Alcoólicos", 23, "Zero", 26, "Gelatos Proteicos", 29, 8), 5)) + (ROUND(N26,4) < INDEX('Tabela de ingredientes'!$O$1:$V$30, SWITCH(B26, "Gelatos de Leite", 7, "Sorbets", 10, "Gelatos de Leite com Fruta", 13, "Chocolate base água", 16, "Vegano", 19, "Alcoólicos", 22, "Zero", 25, "Gelatos Proteicos", 28, 7), 6)) + (ROUND(N26,4) > INDEX('Tabela de ingredientes'!$O$1:$V$30, SWITCH(B26, "Gelatos de Leite", 8, "Sorbets", 11, "Gelatos de Leite com Fruta", 14, "Chocolate base água", 17, "Vegano", 20, "Alcoólicos", 23, "Zero", 26, "Gelatos Proteicos", 29, 8), 6)) + (ROUND(O26,4) < INDEX('Tabela de ingredientes'!$O$1:$V$30, SWITCH(B26, "Gelatos de Leite", 7, "Sorbets", 10, "Gelatos de Leite com Fruta", 13, "Chocolate base água", 16, "Vegano", 19, "Alcoólicos", 22, "Zero", 25, "Gelatos Proteicos", 28, 7), 7)) + (ROUND(O26,4) > INDEX('Tabela de ingredientes'!$O$1:$V$30, SWITCH(B26, "Gelatos de Leite", 8, "Sorbets", 11, "Gelatos de Leite com Fruta", 14, "Chocolate base água", 17, "Vegano", 20, "Alcoólicos", 23, "Zero", 26, "Gelatos Proteicos", 29, 8), 7)) + (ROUND(P26,4) < INDEX('Tabela de ingredientes'!$O$1:$V$30, SWITCH(B26, "Gelatos de Leite", 7, "Sorbets", 10, "Gelatos de Leite com Fruta", 13, "Chocolate base água", 16, "Vegano", 19, "Alcoólicos", 22, "Zero", 25, "Gelatos Proteicos", 28, 7), 8)) + (ROUND(P26,4) > INDEX('Tabela de ingredientes'!$O$1:$V$30, SWITCH(B26, "Gelatos de Leite", 8, "Sorbets", 11, "Gelatos de Leite com Fruta", 14, "Chocolate base água", 17, "Vegano", 20, "Alcoólicos", 23, "Zero", 26, "Gelatos Proteicos", 29, 8), 8)) + IF(B26="Gelatos Proteicos", (ROUND(Q26,4)<'Tabela de ingredientes'!$W$28)+(ROUND(Q26,4)>'Tabela de ingredientes'!$W$29), 0) = 0, "Ok", "Revisar"))} -> Ok
A27: =IFERROR(__xludf.DUMMYFUNCTION("""COMPUTED_VALUE"""),"Milho (Direto ao Ponto)") -> Milho (Direto ao Ponto) | B27: Gelatos de Leite | C27: 9 | D27: 1046 | E27: Diferente (1046 g) | F27: 13.210803 | G27: 0.79264818 | H27: 33.287089 | I27: 0.18164436 | J27: 0.045602294 | K27: 0.089340344 | L27: 0.057217973 | M27: 0.37380497 | N27: 0.62619503 | O27: 182.34417 | P27: 263.95793 | Q27: 0.040363289 | R27: 10.558317 | S27: {=IF(A27="","", IF( (ROUND(I27,4) < INDEX('Tabela de ingredientes'!$O$1:$V$30, SWITCH(B27, "Gelatos de Leite", 7, "Sorbets", 10, "Gelatos de Leite com Fruta", 13, "Chocolate base água", 16, "Vegano", 19, "Alcoólicos", 22, "Zero", 25, "Gelatos Proteicos", 28, 7), 1)) + (ROUND(I27,4) > INDEX('Tabela de ingredientes'!$O$1:$V$30, SWITCH(B27, "Gelatos de Leite", 8, "Sorbets", 11, "Gelatos de Leite com Fruta", 14, "Chocolate base água", 17, "Vegano", 20, "Alcoólicos", 23, "Zero", 26, "Gelatos Proteicos", 29, 8), 1)) + (ROUND(J27,4) < INDEX('Tabela de ingredientes'!$O$1:$V$30, SWITCH(B27, "Gelatos de Leite", 7, "Sorbets", 10, "Gelatos de Leite com Fruta", 13, "Chocolate base água", 16, "Vegano", 19, "Alcoólicos", 22, "Zero", 25, "Gelatos Proteicos", 28, 7), 2)) + (ROUND(J27,4) > INDEX('Tabela de ingredientes'!$O$1:$V$30, SWITCH(B27, "Gelatos de Leite", 8, "Sorbets", 11, "Gelatos de Leite com Fruta", 14, "Chocolate base água", 17, "Vegano", 20, "Alcoólicos", 23, "Zero", 26, "Gelatos Proteicos", 29, 8), 2)) + (ROUND(K27,4) < INDEX('Tabela de ingredientes'!$O$1:$V$30, SWITCH(B27, "Gelatos de Leite", 7, "Sorbets", 10, "Gelatos de Leite com Fruta", 13, "Chocolate base água", 16, "Vegano", 19, "Alcoólicos", 22, "Zero", 25, "Gelatos Proteicos", 28, 7), 3)) + (ROUND(K27,4) > INDEX('Tabela de ingredientes'!$O$1:$V$30, SWITCH(B27, "Gelatos de Leite", 8, "Sorbets", 11, "Gelatos de Leite com Fruta", 14, "Chocolate base água", 17, "Vegano", 20, "Alcoólicos", 23, "Zero", 26, "Gelatos Proteicos", 29, 8), 3)) + (ROUND(L27,4) < INDEX('Tabela de ingredientes'!$O$1:$V$30, SWITCH(B27, "Gelatos de Leite", 7, "Sorbets", 10, "Gelatos de Leite com Fruta", 13, "Chocolate base água", 16, "Vegano", 19, "Alcoólicos", 22, "Zero", 25, "Gelatos Proteicos", 28, 7), 4)) + (ROUND(L27,4) > INDEX('Tabela de ingredientes'!$O$1:$V$30, SWITCH(B27, "Gelatos de Leite", 8, "Sorbets", 11, "Gelatos de Leite com Fruta", 14, "Chocolate base água", 17, "Vegano", 20, "Alcoólicos", 23, "Zero", 26, "Gelatos Proteicos", 29, 8), 4)) + (ROUND(M27,4) < INDEX('Tabela de ingredientes'!$O$1:$V$30, SWITCH(B27, "Gelatos de Leite", 7, "Sorbets", 10, "Gelatos de Leite com Fruta", 13, "Chocolate base água", 16, "Vegano", 19, "Alcoólicos", 22, "Zero", 25, "Gelatos Proteicos", 28, 7), 5)) + (ROUND(M27,4) > INDEX('Tabela de ingredientes'!$O$1:$V$30, SWITCH(B27, "Gelatos de Leite", 8, "Sorbets", 11, "Gelatos de Leite com Fruta", 14, "Chocolate base água", 17, "Vegano", 20, "Alcoólicos", 23, "Zero", 26, "Gelatos Proteicos", 29, 8), 5)) + (ROUND(N27,4) < INDEX('Tabela de ingredientes'!$O$1:$V$30, SWITCH(B27, "Gelatos de Leite", 7, "Sorbets", 10, "Gelatos de Leite com Fruta", 13, "Chocolate base água", 16, "Vegano", 19, "Alcoólicos", 22, "Zero", 25, "Gelatos Proteicos", 28, 7), 6)) + (ROUND(N27,4) > INDEX('Tabela de ingredientes'!$O$1:$V$30, SWITCH(B27, "Gelatos de Leite", 8, "Sorbets", 11, "Gelatos de Leite com Fruta", 14, "Chocolate base água", 17, "Vegano", 20, "Alcoólicos", 23, "Zero", 26, "Gelatos Proteicos", 29, 8), 6)) + (ROUND(O27,4) < INDEX('Tabela de ingredientes'!$O$1:$V$30, SWITCH(B27, "Gelatos de Leite", 7, "Sorbets", 10, "Gelatos de Leite com Fruta", 13, "Chocolate base água", 16, "Vegano", 19, "Alcoólicos", 22, "Zero", 25, "Gelatos Proteicos", 28, 7), 7)) + (ROUND(O27,4) > INDEX('Tabela de ingredientes'!$O$1:$V$30, SWITCH(B27, "Gelatos de Leite", 8, "Sorbets", 11, "Gelatos de Leite com Fruta", 14, "Chocolate base água", 17, "Vegano", 20, "Alcoólicos", 23, "Zero", 26, "Gelatos Proteicos", 29, 8), 7)) + (ROUND(P27,4) < INDEX('Tabela de ingredientes'!$O$1:$V$30, SWITCH(B27, "Gelatos de Leite", 7, "Sorbets", 10, "Gelatos de Leite com Fruta", 13, "Chocolate base água", 16, "Vegano", 19, "Alcoólicos", 22, "Zero", 25, "Gelatos Proteicos", 28, 7), 8)) + (ROUND(P27,4) > INDEX('Tabela de ingredientes'!$O$1:$V$30, SWITCH(B27, "Gelatos de Leite", 8, "Sorbets", 11, "Gelatos de Leite com Fruta", 14, "Chocolate base água", 17, "Vegano", 20, "Alcoólicos", 23, "Zero", 26, "Gelatos Proteicos", 29, 8), 8)) + IF(B27="Gelatos Proteicos", (ROUND(Q27,4)<'Tabela de ingredientes'!$W$28)+(ROUND(Q27,4)>'Tabela de ingredientes'!$W$29), 0) = 0, "Ok", "Revisar"))} -> Revisar
A28: =IFERROR(__xludf.DUMMYFUNCTION("""COMPUTED_VALUE"""),"Coco Fresco (Direto ao Ponto)") -> Coco Fresco (Direto ao Ponto) | B28: Gelatos de Leite | C28: 9 | D28: 1006 | E28: Diferente (1006 g) | F28: 10.29672 | G28: 0.61780318 | H28: 30.874768 | I28: 0.18477137 | J28: 0.065854871 | K28: 0.086878728 | L28: 0.038220676 | M28: 0.37572565 | N28: 0.62427435 | O28: 209.55268 | P28: 265.08946 | Q28: 0.032654076 | R28: 10.603579 | S28: {=IF(A28="","", IF( (ROUND(I28,4) < INDEX('Tabela de ingredientes'!$O$1:$V$30, SWITCH(B28, "Gelatos de Leite", 7, "Sorbets", 10, "Gelatos de Leite com Fruta", 13, "Chocolate base água", 16, "Vegano", 19, "Alcoólicos", 22, "Zero", 25, "Gelatos Proteicos", 28, 7), 1)) + (ROUND(I28,4) > INDEX('Tabela de ingredientes'!$O$1:$V$30, SWITCH(B28, "Gelatos de Leite", 8, "Sorbets", 11, "Gelatos de Leite com Fruta", 14, "Chocolate base água", 17, "Vegano", 20, "Alcoólicos", 23, "Zero", 26, "Gelatos Proteicos", 29, 8), 1)) + (ROUND(J28,4) < INDEX('Tabela de ingredientes'!$O$1:$V$30, SWITCH(B28, "Gelatos de Leite", 7, "Sorbets", 10, "Gelatos de Leite com Fruta", 13, "Chocolate base água", 16, "Vegano", 19, "Alcoólicos", 22, "Zero", 25, "Gelatos Proteicos", 28, 7), 2)) + (ROUND(J28,4) > INDEX('Tabela de ingredientes'!$O$1:$V$30, SWITCH(B28, "Gelatos de Leite", 8, "Sorbets", 11, "Gelatos de Leite com Fruta", 14, "Chocolate base água", 17, "Vegano", 20, "Alcoólicos", 23, "Zero", 26, "Gelatos Proteicos", 29, 8), 2)) + (ROUND(K28,4) < INDEX('Tabela de ingredientes'!$O$1:$V$30, SWITCH(B28, "Gelatos de Leite", 7, "Sorbets", 10, "Gelatos de Leite com Fruta", 13, "Chocolate base água", 16, "Vegano", 19, "Alcoólicos", 22, "Zero", 25, "Gelatos Proteicos", 28, 7), 3)) + (ROUND(K28,4) > INDEX('Tabela de ingredientes'!$O$1:$V$30, SWITCH(B28, "Gelatos de Leite", 8, "Sorbets", 11, "Gelatos de Leite com Fruta", 14, "Chocolate base água", 17, "Vegano", 20, "Alcoólicos", 23, "Zero", 26, "Gelatos Proteicos", 29, 8), 3)) + (ROUND(L28,4) < INDEX('Tabela de ingredientes'!$O$1:$V$30, SWITCH(B28, "Gelatos de Leite", 7, "Sorbets", 10, "Gelatos de Leite com Fruta", 13, "Chocolate base água", 16, "Vegano", 19, "Alcoólicos", 22, "Zero", 25, "Gelatos Proteicos", 28, 7), 4)) + (ROUND(L28,4) > INDEX('Tabela de ingredientes'!$O$1:$V$30, SWITCH(B28, "Gelatos de Leite", 8, "Sorbets", 11, "Gelatos de Leite com Fruta", 14, "Chocolate base água", 17, "Vegano", 20, "Alcoólicos", 23, "Zero", 26, "Gelatos Proteicos", 29, 8), 4)) + (ROUND(M28,4) < INDEX('Tabela de ingredientes'!$O$1:$V$30, SWITCH(B28, "Gelatos de Leite", 7, "Sorbets", 10, "Gelatos de Leite com Fruta", 13, "Chocolate base água", 16, "Vegano", 19, "Alcoólicos", 22, "Zero", 25, "Gelatos Proteicos", 28, 7), 5)) + (ROUND(M28,4) > INDEX('Tabela de ingredientes'!$O$1:$V$30, SWITCH(B28, "Gelatos de Leite", 8, "Sorbets", 11, "Gelatos de Leite com Fruta", 14, "Chocolate base água", 17, "Vegano", 20, "Alcoólicos", 23, "Zero", 26, "Gelatos Proteicos", 29, 8), 5)) + (ROUND(N28,4) < INDEX('Tabela de ingredientes'!$O$1:$V$30, SWITCH(B28, "Gelatos de Leite", 7, "Sorbets", 10, "Gelatos de Leite com Fruta", 13, "Chocolate base água", 16, "Vegano", 19, "Alcoólicos", 22, "Zero", 25, "Gelatos Proteicos", 28, 7), 6)) + (ROUND(N28,4) > INDEX('Tabela de ingredientes'!$O$1:$V$30, SWITCH(B28, "Gelatos de Leite", 8, "Sorbets", 11, "Gelatos de Leite com Fruta", 14, "Chocolate base água", 17, "Vegano", 20, "Alcoólicos", 23, "Zero", 26, "Gelatos Proteicos", 29, 8), 6)) + (ROUND(O28,4) < INDEX('Tabela de ingredientes'!$O$1:$V$30, SWITCH(B28, "Gelatos de Leite", 7, "Sorbets", 10, "Gelatos de Leite com Fruta", 13, "Chocolate base água", 16, "Vegano", 19, "Alcoólicos", 22, "Zero", 25, "Gelatos Proteicos", 28, 7), 7)) + (ROUND(O28,4) > INDEX('Tabela de ingredientes'!$O$1:$V$30, SWITCH(B28, "Gelatos de Leite", 8, "Sorbets", 11, "Gelatos de Leite com Fruta", 14, "Chocolate base água", 17, "Vegano", 20, "Alcoólicos", 23, "Zero", 26, "Gelatos Proteicos", 29, 8), 7)) + (ROUND(P28,4) < INDEX('Tabela de ingredientes'!$O$1:$V$30, SWITCH(B28, "Gelatos de Leite", 7, "Sorbets", 10, "Gelatos de Leite com Fruta", 13, "Chocolate base água", 16, "Vegano", 19, "Alcoólicos", 22, "Zero", 25, "Gelatos Proteicos", 28, 7), 8)) + (ROUND(P28,4) > INDEX('Tabela de ingredientes'!$O$1:$V$30, SWITCH(B28, "Gelatos de Leite", 8, "Sorbets", 11, "Gelatos de Leite com Fruta", 14, "Chocolate base água", 17, "Vegano", 20, "Alcoólicos", 23, "Zero", 26, "Gelatos Proteicos", 29, 8), 8)) + IF(B28="Gelatos Proteicos", (ROUND(Q28,4)<'Tabela de ingredientes'!$W$28)+(ROUND(Q28,4)>'Tabela de ingredientes'!$W$29), 0) = 0, "Ok", "Revisar"))} -> Revisar
A29: =IFERROR(__xludf.DUMMYFUNCTION("""COMPUTED_VALUE"""),"Sucrilhos (Direto ao Ponto)") -> Sucrilhos (Direto ao Ponto) | B29: Gelatos de Leite | C29: 9 | D29: 1101 | E29: Diferente (1101 g) | F29: 13.827884 | G29: 0.82967302 | H29: 33.797917 | I29: 0.20622162 | J29: 0.058333333 | K29: 0.098092643 | L29: 0.058128974 | M29: 0.42077657 | N29: 0.57922343 | O29: 190.55495 | P29: 279.74569 | Q29: 0.042057221 | R29: 11.189827 | S29: {=IF(A29="","", IF( (ROUND(I29,4) < INDEX('Tabela de ingredientes'!$O$1:$V$30, SWITCH(B29, "Gelatos de Leite", 7, "Sorbets", 10, "Gelatos de Leite com Fruta", 13, "Chocolate base água", 16, "Vegano", 19, "Alcoólicos", 22, "Zero", 25, "Gelatos Proteicos", 28, 7), 1)) + (ROUND(I29,4) > INDEX('Tabela de ingredientes'!$O$1:$V$30, SWITCH(B29, "Gelatos de Leite", 8, "Sorbets", 11, "Gelatos de Leite com Fruta", 14, "Chocolate base água", 17, "Vegano", 20, "Alcoólicos", 23, "Zero", 26, "Gelatos Proteicos", 29, 8), 1)) + (ROUND(J29,4) < INDEX('Tabela de ingredientes'!$O$1:$V$30, SWITCH(B29, "Gelatos de Leite", 7, "Sorbets", 10, "Gelatos de Leite com Fruta", 13, "Chocolate base água", 16, "Vegano", 19, "Alcoólicos", 22, "Zero", 25, "Gelatos Proteicos", 28, 7), 2)) + (ROUND(J29,4) > INDEX('Tabela de ingredientes'!$O$1:$V$30, SWITCH(B29, "Gelatos de Leite", 8, "Sorbets", 11, "Gelatos de Leite com Fruta", 14, "Chocolate base água", 17, "Vegano", 20, "Alcoólicos", 23, "Zero", 26, "Gelatos Proteicos", 29, 8), 2)) + (ROUND(K29,4) < INDEX('Tabela de ingredientes'!$O$1:$V$30, SWITCH(B29, "Gelatos de Leite", 7, "Sorbets", 10, "Gelatos de Leite com Fruta", 13, "Chocolate base água", 16, "Vegano", 19, "Alcoólicos", 22, "Zero", 25, "Gelatos Proteicos", 28, 7), 3)) + (ROUND(K29,4) > INDEX('Tabela de ingredientes'!$O$1:$V$30, SWITCH(B29, "Gelatos de Leite", 8, "Sorbets", 11, "Gelatos de Leite com Fruta", 14, "Chocolate base água", 17, "Vegano", 20, "Alcoólicos", 23, "Zero", 26, "Gelatos Proteicos", 29, 8), 3)) + (ROUND(L29,4) < INDEX('Tabela de ingredientes'!$O$1:$V$30, SWITCH(B29, "Gelatos de Leite", 7, "Sorbets", 10, "Gelatos de Leite com Fruta", 13, "Chocolate base água", 16, "Vegano", 19, "Alcoólicos", 22, "Zero", 25, "Gelatos Proteicos", 28, 7), 4)) + (ROUND(L29,4) > INDEX('Tabela de ingredientes'!$O$1:$V$30, SWITCH(B29, "Gelatos de Leite", 8, "Sorbets", 11, "Gelatos de Leite com Fruta", 14, "Chocolate base água", 17, "Vegano", 20, "Alcoólicos", 23, "Zero", 26, "Gelatos Proteicos", 29, 8), 4)) + (ROUND(M29,4) < INDEX('Tabela de ingredientes'!$O$1:$V$30, SWITCH(B29, "Gelatos de Leite", 7, "Sorbets", 10, "Gelatos de Leite com Fruta", 13, "Chocolate base água", 16, "Vegano", 19, "Alcoólicos", 22, "Zero", 25, "Gelatos Proteicos", 28, 7), 5)) + (ROUND(M29,4) > INDEX('Tabela de ingredientes'!$O$1:$V$30, SWITCH(B29, "Gelatos de Leite", 8, "Sorbets", 11, "Gelatos de Leite com Fruta", 14, "Chocolate base água", 17, "Vegano", 20, "Alcoólicos", 23, "Zero", 26, "Gelatos Proteicos", 29, 8), 5)) + (ROUND(N29,4) < INDEX('Tabela de ingredientes'!$O$1:$V$30, SWITCH(B29, "Gelatos de Leite", 7, "Sorbets", 10, "Gelatos de Leite com Fruta", 13, "Chocolate base água", 16, "Vegano", 19, "Alcoólicos", 22, "Zero", 25, "Gelatos Proteicos", 28, 7), 6)) + (ROUND(N29,4) > INDEX('Tabela de ingredientes'!$O$1:$V$30, SWITCH(B29, "Gelatos de Leite", 8, "Sorbets", 11, "Gelatos de Leite com Fruta", 14, "Chocolate base água", 17, "Vegano", 20, "Alcoólicos", 23, "Zero", 26, "Gelatos Proteicos", 29, 8), 6)) + (ROUND(O29,4) < INDEX('Tabela de ingredientes'!$O$1:$V$30, SWITCH(B29, "Gelatos de Leite", 7, "Sorbets", 10, "Gelatos de Leite com Fruta", 13, "Chocolate base água", 16, "Vegano", 19, "Alcoólicos", 22, "Zero", 25, "Gelatos Proteicos", 28, 7), 7)) + (ROUND(O29,4) > INDEX('Tabela de ingredientes'!$O$1:$V$30, SWITCH(B29, "Gelatos de Leite", 8, "Sorbets", 11, "Gelatos de Leite com Fruta", 14, "Chocolate base água", 17, "Vegano", 20, "Alcoólicos", 23, "Zero", 26, "Gelatos Proteicos", 29, 8), 7)) + (ROUND(P29,4) < INDEX('Tabela de ingredientes'!$O$1:$V$30, SWITCH(B29, "Gelatos de Leite", 7, "Sorbets", 10, "Gelatos de Leite com Fruta", 13, "Chocolate base água", 16, "Vegano", 19, "Alcoólicos", 22, "Zero", 25, "Gelatos Proteicos", 28, 7), 8)) + (ROUND(P29,4) > INDEX('Tabela de ingredientes'!$O$1:$V$30, SWITCH(B29, "Gelatos de Leite", 8, "Sorbets", 11, "Gelatos de Leite com Fruta", 14, "Chocolate base água", 17, "Vegano", 20, "Alcoólicos", 23, "Zero", 26, "Gelatos Proteicos", 29, 8), 8)) + IF(B29="Gelatos Proteicos", (ROUND(Q29,4)<'Tabela de ingredientes'!$W$28)+(ROUND(Q29,4)>'Tabela de ingredientes'!$W$29), 0) = 0, "Ok", "Revisar"))} -> Revisar
A30: =IFERROR(__xludf.DUMMYFUNCTION("""COMPUTED_VALUE"""),"Intenso de Cacau (Direto ao Ponto)") -> Intenso de Cacau (Direto ao Ponto) | B30: Gelatos de Leite | C30: 8 | D30: 975 | E30: Diferente (975 g) | F30: 12.71641 | G30: 0.76298462 | H30: 32.877823 | I30: 0.18953846 | J30: 0.056358974 | K30: 0.094820513 | L30: 0.065435897 | M30: 0.40615385 | N30: 0.59384615 | O30: 185.62564 | P30: 296.15385 | Q30: 0.049230769 | R30: 11.846154 | S30: {=IF(A30="","", IF( (ROUND(I30,4) < INDEX('Tabela de ingredientes'!$O$1:$V$30, SWITCH(B30, "Gelatos de Leite", 7, "Sorbets", 10, "Gelatos de Leite com Fruta", 13, "Chocolate base água", 16, "Vegano", 19, "Alcoólicos", 22, "Zero", 25, "Gelatos Proteicos", 28, 7), 1)) + (ROUND(I30,4) > INDEX('Tabela de ingredientes'!$O$1:$V$30, SWITCH(B30, "Gelatos de Leite", 8, "Sorbets", 11, "Gelatos de Leite com Fruta", 14, "Chocolate base água", 17, "Vegano", 20, "Alcoólicos", 23, "Zero", 26, "Gelatos Proteicos", 29, 8), 1)) + (ROUND(J30,4) < INDEX('Tabela de ingredientes'!$O$1:$V$30, SWITCH(B30, "Gelatos de Leite", 7, "Sorbets", 10, "Gelatos de Leite com Fruta", 13, "Chocolate base água", 16, "Vegano", 19, "Alcoólicos", 22, "Zero", 25, "Gelatos Proteicos", 28, 7), 2)) + (ROUND(J30,4) > INDEX('Tabela de ingredientes'!$O$1:$V$30, SWITCH(B30, "Gelatos de Leite", 8, "Sorbets", 11, "Gelatos de Leite com Fruta", 14, "Chocolate base água", 17, "Vegano", 20, "Alcoólicos", 23, "Zero", 26, "Gelatos Proteicos", 29, 8), 2)) + (ROUND(K30,4) < INDEX('Tabela de ingredientes'!$O$1:$V$30, SWITCH(B30, "Gelatos de Leite", 7, "Sorbets", 10, "Gelatos de Leite com Fruta", 13, "Chocolate base água", 16, "Vegano", 19, "Alcoólicos", 22, "Zero", 25, "Gelatos Proteicos", 28, 7), 3)) + (ROUND(K30,4) > INDEX('Tabela de ingredientes'!$O$1:$V$30, SWITCH(B30, "Gelatos de Leite", 8, "Sorbets", 11, "Gelatos de Leite com Fruta", 14, "Chocolate base água", 17, "Vegano", 20, "Alcoólicos", 23, "Zero", 26, "Gelatos Proteicos", 29, 8), 3)) + (ROUND(L30,4) < INDEX('Tabela de ingredientes'!$O$1:$V$30, SWITCH(B30, "Gelatos de Leite", 7, "Sorbets", 10, "Gelatos de Leite com Fruta", 13, "Chocolate base água", 16, "Vegano", 19, "Alcoólicos", 22, "Zero", 25, "Gelatos Proteicos", 28, 7), 4)) + (ROUND(L30,4) > INDEX('Tabela de ingredientes'!$O$1:$V$30, SWITCH(B30, "Gelatos de Leite", 8, "Sorbets", 11, "Gelatos de Leite com Fruta", 14, "Chocolate base água", 17, "Vegano", 20, "Alcoólicos", 23, "Zero", 26, "Gelatos Proteicos", 29, 8), 4)) + (ROUND(M30,4) < INDEX('Tabela de ingredientes'!$O$1:$V$30, SWITCH(B30, "Gelatos de Leite", 7, "Sorbets", 10, "Gelatos de Leite com Fruta", 13, "Chocolate base água", 16, "Vegano", 19, "Alcoólicos", 22, "Zero", 25, "Gelatos Proteicos", 28, 7), 5)) + (ROUND(M30,4) > INDEX('Tabela de ingredientes'!$O$1:$V$30, SWITCH(B30, "Gelatos de Leite", 8, "Sorbets", 11, "Gelatos de Leite com Fruta", 14, "Chocolate base água", 17, "Vegano", 20, "Alcoólicos", 23, "Zero", 26, "Gelatos Proteicos", 29, 8), 5)) + (ROUND(N30,4) < INDEX('Tabela de ingredientes'!$O$1:$V$30, SWITCH(B30, "Gelatos de Leite", 7, "Sorbets", 10, "Gelatos de Leite com Fruta", 13, "Chocolate base água", 16, "Vegano", 19, "Alcoólicos", 22, "Zero", 25, "Gelatos Proteicos", 28, 7), 6)) + (ROUND(N30,4) > INDEX('Tabela de ingredientes'!$O$1:$V$30, SWITCH(B30, "Gelatos de Leite", 8, "Sorbets", 11, "Gelatos de Leite com Fruta", 14, "Chocolate base água", 17, "Vegano", 20, "Alcoólicos", 23, "Zero", 26, "Gelatos Proteicos", 29, 8), 6)) + (ROUND(O30,4) < INDEX('Tabela de ingredientes'!$O$1:$V$30, SWITCH(B30, "Gelatos de Leite", 7, "Sorbets", 10, "Gelatos de Leite com Fruta", 13, "Chocolate base água", 16, "Vegano", 19, "Alcoólicos", 22, "Zero", 25, "Gelatos Proteicos", 28, 7), 7)) + (ROUND(O30,4) > INDEX('Tabela de ingredientes'!$O$1:$V$30, SWITCH(B30, "Gelatos de Leite", 8, "Sorbets", 11, "Gelatos de Leite com Fruta", 14, "Chocolate base água", 17, "Vegano", 20, "Alcoólicos", 23, "Zero", 26, "Gelatos Proteicos", 29, 8), 7)) + (ROUND(P30,4) < INDEX('Tabela de ingredientes'!$O$1:$V$30, SWITCH(B30, "Gelatos de Leite", 7, "Sorbets", 10, "Gelatos de Leite com Fruta", 13, "Chocolate base água", 16, "Vegano", 19, "Alcoólicos", 22, "Zero", 25, "Gelatos Proteicos", 28, 7), 8)) + (ROUND(P30,4) > INDEX('Tabela de ingredientes'!$O$1:$V$30, SWITCH(B30, "Gelatos de Leite", 8, "Sorbets", 11, "Gelatos de Leite com Fruta", 14, "Chocolate base água", 17, "Vegano", 20, "Alcoólicos", 23, "Zero", 26, "Gelatos Proteicos", 29, 8), 8)) + IF(B30="Gelatos Proteicos", (ROUND(Q30,4)<'Tabela de ingredientes'!$W$28)+(ROUND(Q30,4)>'Tabela de ingredientes'!$W$29), 0) = 0, "Ok", "Revisar"))} -> Ok
A31: =IFERROR(__xludf.DUMMYFUNCTION("""COMPUTED_VALUE"""),"Chocolate 70% (Direto ao Ponto)") -> Chocolate 70% (Direto ao Ponto) | B31: Gelatos de Leite | C31: 8 | D31: 1004 | E31: Diferente (1004 g) | F31: 42.622012 | G31: 2.5573207 | H31: 57.634116 | I31: 0.16573705 | J31: 0.12241036 | K31: 0.081523904 | L31: 0.067729084 | M31: 0.4374004 | N31: 0.5625996 | O31: 220.4253 | P31: 186.60359 | Q31: 0.041284861 | R31: 7.4641434 | S31: {=IF(A31="","", IF( (ROUND(I31,4) < INDEX('Tabela de ingredientes'!$O$1:$V$30, SWITCH(B31, "Gelatos de Leite", 7, "Sorbets", 10, "Gelatos de Leite com Fruta", 13, "Chocolate base água", 16, "Vegano", 19, "Alcoólicos", 22, "Zero", 25, "Gelatos Proteicos", 28, 7), 1)) + (ROUND(I31,4) > INDEX('Tabela de ingredientes'!$O$1:$V$30, SWITCH(B31, "Gelatos de Leite", 8, "Sorbets", 11, "Gelatos de Leite com Fruta", 14, "Chocolate base água", 17, "Vegano", 20, "Alcoólicos", 23, "Zero", 26, "Gelatos Proteicos", 29, 8), 1)) + (ROUND(J31,4) < INDEX('Tabela de ingredientes'!$O$1:$V$30, SWITCH(B31, "Gelatos de Leite", 7, "Sorbets", 10, "Gelatos de Leite com Fruta", 13, "Chocolate base água", 16, "Vegano", 19, "Alcoólicos", 22, "Zero", 25, "Gelatos Proteicos", 28, 7), 2)) + (ROUND(J31,4) > INDEX('Tabela de ingredientes'!$O$1:$V$30, SWITCH(B31, "Gelatos de Leite", 8, "Sorbets", 11, "Gelatos de Leite com Fruta", 14, "Chocolate base água", 17, "Vegano", 20, "Alcoólicos", 23, "Zero", 26, "Gelatos Proteicos", 29, 8), 2)) + (ROUND(K31,4) < INDEX('Tabela de ingredientes'!$O$1:$V$30, SWITCH(B31, "Gelatos de Leite", 7, "Sorbets", 10, "Gelatos de Leite com Fruta", 13, "Chocolate base água", 16, "Vegano", 19, "Alcoólicos", 22, "Zero", 25, "Gelatos Proteicos", 28, 7), 3)) + (ROUND(K31,4) > INDEX('Tabela de ingredientes'!$O$1:$V$30, SWITCH(B31, "Gelatos de Leite", 8, "Sorbets", 11, "Gelatos de Leite com Fruta", 14, "Chocolate base água", 17, "Vegano", 20, "Alcoólicos", 23, "Zero", 26, "Gelatos Proteicos", 29, 8), 3)) + (ROUND(L31,4) < INDEX('Tabela de ingredientes'!$O$1:$V$30, SWITCH(B31, "Gelatos de Leite", 7, "Sorbets", 10, "Gelatos de Leite com Fruta", 13, "Chocolate base água", 16, "Vegano", 19, "Alcoólicos", 22, "Zero", 25, "Gelatos Proteicos", 28, 7), 4)) + (ROUND(L31,4) > INDEX('Tabela de ingredientes'!$O$1:$V$30, SWITCH(B31, "Gelatos de Leite", 8, "Sorbets", 11, "Gelatos de Leite com Fruta", 14, "Chocolate base água", 17, "Vegano", 20, "Alcoólicos", 23, "Zero", 26, "Gelatos Proteicos", 29, 8), 4)) + (ROUND(M31,4) < INDEX('Tabela de ingredientes'!$O$1:$V$30, SWITCH(B31, "Gelatos de Leite", 7, "Sorbets", 10, "Gelatos de Leite com Fruta", 13, "Chocolate base água", 16, "Vegano", 19, "Alcoólicos", 22, "Zero", 25, "Gelatos Proteicos", 28, 7), 5)) + (ROUND(M31,4) > INDEX('Tabela de ingredientes'!$O$1:$V$30, SWITCH(B31, "Gelatos de Leite", 8, "Sorbets", 11, "Gelatos de Leite com Fruta", 14, "Chocolate base água", 17, "Vegano", 20, "Alcoólicos", 23, "Zero", 26, "Gelatos Proteicos", 29, 8), 5)) + (ROUND(N31,4) < INDEX('Tabela de ingredientes'!$O$1:$V$30, SWITCH(B31, "Gelatos de Leite", 7, "Sorbets", 10, "Gelatos de Leite com Fruta", 13, "Chocolate base água", 16, "Vegano", 19, "Alcoólicos", 22, "Zero", 25, "Gelatos Proteicos", 28, 7), 6)) + (ROUND(N31,4) > INDEX('Tabela de ingredientes'!$O$1:$V$30, SWITCH(B31, "Gelatos de Leite", 8, "Sorbets", 11, "Gelatos de Leite com Fruta", 14, "Chocolate base água", 17, "Vegano", 20, "Alcoólicos", 23, "Zero", 26, "Gelatos Proteicos", 29, 8), 6)) + (ROUND(O31,4) < INDEX('Tabela de ingredientes'!$O$1:$V$30, SWITCH(B31, "Gelatos de Leite", 7, "Sorbets", 10, "Gelatos de Leite com Fruta", 13, "Chocolate base água", 16, "Vegano", 19, "Alcoólicos", 22, "Zero", 25, "Gelatos Proteicos", 28, 7), 7)) + (ROUND(O31,4) > INDEX('Tabela de ingredientes'!$O$1:$V$30, SWITCH(B31, "Gelatos de Leite", 8, "Sorbets", 11, "Gelatos de Leite com Fruta", 14, "Chocolate base água", 17, "Vegano", 20, "Alcoólicos", 23, "Zero", 26, "Gelatos Proteicos", 29, 8), 7)) + (ROUND(P31,4) < INDEX('Tabela de ingredientes'!$O$1:$V$30, SWITCH(B31, "Gelatos de Leite", 7, "Sorbets", 10, "Gelatos de Leite com Fruta", 13, "Chocolate base água", 16, "Vegano", 19, "Alcoólicos", 22, "Zero", 25, "Gelatos Proteicos", 28, 7), 8)) + (ROUND(P31,4) > INDEX('Tabela de ingredientes'!$O$1:$V$30, SWITCH(B31, "Gelatos de Leite", 8, "Sorbets", 11, "Gelatos de Leite com Fruta", 14, "Chocolate base água", 17, "Vegano", 20, "Alcoólicos", 23, "Zero", 26, "Gelatos Proteicos", 29, 8), 8)) + IF(B31="Gelatos Proteicos", (ROUND(Q31,4)<'Tabela de ingredientes'!$W$28)+(ROUND(Q31,4)>'Tabela de ingredientes'!$W$29), 0) = 0, "Ok", "Revisar"))} -> Revisar
A32: =IFERROR(__xludf.DUMMYFUNCTION("""COMPUTED_VALUE"""),"Pistache - Base Oleaginosas (Direto ao Ponto)") -> Pistache - Base Oleaginosas (Direto ao Ponto) | B32: Gelatos de Leite | C32: 8 | D32: 1001 | E32: Diferente (1001 g) | F32: 35.523976 | G32: 2.1314386 | H32: 51.758258 | I32: 0.16568432 | J32: 0.10314685 | K32: 0.099000999 | L32: 0.041508492 | M32: 0.40934066 | N32: 0.59065934 | O32: 162.88112 | P32: 246.85315 | Q32: 0.04956044 | R32: 9.8741259 | S32: {=IF(A32="","", IF( (ROUND(I32,4) < INDEX('Tabela de ingredientes'!$O$1:$V$30, SWITCH(B32, "Gelatos de Leite", 7, "Sorbets", 10, "Gelatos de Leite com Fruta", 13, "Chocolate base água", 16, "Vegano", 19, "Alcoólicos", 22, "Zero", 25, "Gelatos Proteicos", 28, 7), 1)) + (ROUND(I32,4) > INDEX('Tabela de ingredientes'!$O$1:$V$30, SWITCH(B32, "Gelatos de Leite", 8, "Sorbets", 11, "Gelatos de Leite com Fruta", 14, "Chocolate base água", 17, "Vegano", 20, "Alcoólicos", 23, "Zero", 26, "Gelatos Proteicos", 29, 8), 1)) + (ROUND(J32,4) < INDEX('Tabela de ingredientes'!$O$1:$V$30, SWITCH(B32, "Gelatos de Leite", 7, "Sorbets", 10, "Gelatos de Leite com Fruta", 13, "Chocolate base água", 16, "Vegano", 19, "Alcoólicos", 22, "Zero", 25, "Gelatos Proteicos", 28, 7), 2)) + (ROUND(J32,4) > INDEX('Tabela de ingredientes'!$O$1:$V$30, SWITCH(B32, "Gelatos de Leite", 8, "Sorbets", 11, "Gelatos de Leite com Fruta", 14, "Chocolate base água", 17, "Vegano", 20, "Alcoólicos", 23, "Zero", 26, "Gelatos Proteicos", 29, 8), 2)) + (ROUND(K32,4) < INDEX('Tabela de ingredientes'!$O$1:$V$30, SWITCH(B32, "Gelatos de Leite", 7, "Sorbets", 10, "Gelatos de Leite com Fruta", 13, "Chocolate base água", 16, "Vegano", 19, "Alcoólicos", 22, "Zero", 25, "Gelatos Proteicos", 28, 7), 3)) + (ROUND(K32,4) > INDEX('Tabela de ingredientes'!$O$1:$V$30, SWITCH(B32, "Gelatos de Leite", 8, "Sorbets", 11, "Gelatos de Leite com Fruta", 14, "Chocolate base água", 17, "Vegano", 20, "Alcoólicos", 23, "Zero", 26, "Gelatos Proteicos", 29, 8), 3)) + (ROUND(L32,4) < INDEX('Tabela de ingredientes'!$O$1:$V$30, SWITCH(B32, "Gelatos de Leite", 7, "Sorbets", 10, "Gelatos de Leite com Fruta", 13, "Chocolate base água", 16, "Vegano", 19, "Alcoólicos", 22, "Zero", 25, "Gelatos Proteicos", 28, 7), 4)) + (ROUND(L32,4) > INDEX('Tabela de ingredientes'!$O$1:$V$30, SWITCH(B32, "Gelatos de Leite", 8, "Sorbets", 11, "Gelatos de Leite com Fruta", 14, "Chocolate base água", 17, "Vegano", 20, "Alcoólicos", 23, "Zero", 26, "Gelatos Proteicos", 29, 8), 4)) + (ROUND(M32,4) < INDEX('Tabela de ingredientes'!$O$1:$V$30, SWITCH(B32, "Gelatos de Leite", 7, "Sorbets", 10, "Gelatos de Leite com Fruta", 13, "Chocolate base água", 16, "Vegano", 19, "Alcoólicos", 22, "Zero", 25, "Gelatos Proteicos", 28, 7), 5)) + (ROUND(M32,4) > INDEX('Tabela de ingredientes'!$O$1:$V$30, SWITCH(B32, "Gelatos de Leite", 8, "Sorbets", 11, "Gelatos de Leite com Fruta", 14, "Chocolate base água", 17, "Vegano", 20, "Alcoólicos", 23, "Zero", 26, "Gelatos Proteicos", 29, 8), 5)) + (ROUND(N32,4) < INDEX('Tabela de ingredientes'!$O$1:$V$30, SWITCH(B32, "Gelatos de Leite", 7, "Sorbets", 10, "Gelatos de Leite com Fruta", 13, "Chocolate base água", 16, "Vegano", 19, "Alcoólicos", 22, "Zero", 25, "Gelatos Proteicos", 28, 7), 6)) + (ROUND(N32,4) > INDEX('Tabela de ingredientes'!$O$1:$V$30, SWITCH(B32, "Gelatos de Leite", 8, "Sorbets", 11, "Gelatos de Leite com Fruta", 14, "Chocolate base água", 17, "Vegano", 20, "Alcoólicos", 23, "Zero", 26, "Gelatos Proteicos", 29, 8), 6)) + (ROUND(O32,4) < INDEX('Tabela de ingredientes'!$O$1:$V$30, SWITCH(B32, "Gelatos de Leite", 7, "Sorbets", 10, "Gelatos de Leite com Fruta", 13, "Chocolate base água", 16, "Vegano", 19, "Alcoólicos", 22, "Zero", 25, "Gelatos Proteicos", 28, 7), 7)) + (ROUND(O32,4) > INDEX('Tabela de ingredientes'!$O$1:$V$30, SWITCH(B32, "Gelatos de Leite", 8, "Sorbets", 11, "Gelatos de Leite com Fruta", 14, "Chocolate base água", 17, "Vegano", 20, "Alcoólicos", 23, "Zero", 26, "Gelatos Proteicos", 29, 8), 7)) + (ROUND(P32,4) < INDEX('Tabela de ingredientes'!$O$1:$V$30, SWITCH(B32, "Gelatos de Leite", 7, "Sorbets", 10, "Gelatos de Leite com Fruta", 13, "Chocolate base água", 16, "Vegano", 19, "Alcoólicos", 22, "Zero", 25, "Gelatos Proteicos", 28, 7), 8)) + (ROUND(P32,4) > INDEX('Tabela de ingredientes'!$O$1:$V$30, SWITCH(B32, "Gelatos de Leite", 8, "Sorbets", 11, "Gelatos de Leite com Fruta", 14, "Chocolate base água", 17, "Vegano", 20, "Alcoólicos", 23, "Zero", 26, "Gelatos Proteicos", 29, 8), 8)) + IF(B32="Gelatos Proteicos", (ROUND(Q32,4)<'Tabela de ingredientes'!$W$28)+(ROUND(Q32,4)>'Tabela de ingredientes'!$W$29), 0) = 0, "Ok", "Revisar"))} -> Ok
A33: =IFERROR(__xludf.DUMMYFUNCTION("""COMPUTED_VALUE"""),"Gelato Base Branca (Addolcire)") -> Gelato Base Branca (Addolcire) | B33: Gelatos de Leite | C33: 7 | D33: 1004 | E33: Diferente (1004 g) | F33: 11.901594 | G33: 0.71409562 | H33: 32.203306 | I33: 0.18080677 | J33: 0.094541833 | K33: 0.10876494 | L33: 0.0039840637 | M33: 0.38809761 | N33: 0.61190239 | O33: 176.26693 | P33: 245.07968 | Q33: 0.04161753 | R33: 9.8031873 | S33: {=IF(A33="","", IF( (ROUND(I33,4) < INDEX('Tabela de ingredientes'!$O$1:$V$30, SWITCH(B33, "Gelatos de Leite", 7, "Sorbets", 10, "Gelatos de Leite com Fruta", 13, "Chocolate base água", 16, "Vegano", 19, "Alcoólicos", 22, "Zero", 25, "Gelatos Proteicos", 28, 7), 1)) + (ROUND(I33,4) > INDEX('Tabela de ingredientes'!$O$1:$V$30, SWITCH(B33, "Gelatos de Leite", 8, "Sorbets", 11, "Gelatos de Leite com Fruta", 14, "Chocolate base água", 17, "Vegano", 20, "Alcoólicos", 23, "Zero", 26, "Gelatos Proteicos", 29, 8), 1)) + (ROUND(J33,4) < INDEX('Tabela de ingredientes'!$O$1:$V$30, SWITCH(B33, "Gelatos de Leite", 7, "Sorbets", 10, "Gelatos de Leite com Fruta", 13, "Chocolate base água", 16, "Vegano", 19, "Alcoólicos", 22, "Zero", 25, "Gelatos Proteicos", 28, 7), 2)) + (ROUND(J33,4) > INDEX('Tabela de ingredientes'!$O$1:$V$30, SWITCH(B33, "Gelatos de Leite", 8, "Sorbets", 11, "Gelatos de Leite com Fruta", 14, "Chocolate base água", 17, "Vegano", 20, "Alcoólicos", 23, "Zero", 26, "Gelatos Proteicos", 29, 8), 2)) + (ROUND(K33,4) < INDEX('Tabela de ingredientes'!$O$1:$V$30, SWITCH(B33, "Gelatos de Leite", 7, "Sorbets", 10, "Gelatos de Leite com Fruta", 13, "Chocolate base água", 16, "Vegano", 19, "Alcoólicos", 22, "Zero", 25, "Gelatos Proteicos", 28, 7), 3)) + (ROUND(K33,4) > INDEX('Tabela de ingredientes'!$O$1:$V$30, SWITCH(B33, "Gelatos de Leite", 8, "Sorbets", 11, "Gelatos de Leite com Fruta", 14, "Chocolate base água", 17, "Vegano", 20, "Alcoólicos", 23, "Zero", 26, "Gelatos Proteicos", 29, 8), 3)) + (ROUND(L33,4) < INDEX('Tabela de ingredientes'!$O$1:$V$30, SWITCH(B33, "Gelatos de Leite", 7, "Sorbets", 10, "Gelatos de Leite com Fruta", 13, "Chocolate base água", 16, "Vegano", 19, "Alcoólicos", 22, "Zero", 25, "Gelatos Proteicos", 28, 7), 4)) + (ROUND(L33,4) > INDEX('Tabela de ingredientes'!$O$1:$V$30, SWITCH(B33, "Gelatos de Leite", 8, "Sorbets", 11, "Gelatos de Leite com Fruta", 14, "Chocolate base água", 17, "Vegano", 20, "Alcoólicos", 23, "Zero", 26, "Gelatos Proteicos", 29, 8), 4)) + (ROUND(M33,4) < INDEX('Tabela de ingredientes'!$O$1:$V$30, SWITCH(B33, "Gelatos de Leite", 7, "Sorbets", 10, "Gelatos de Leite com Fruta", 13, "Chocolate base água", 16, "Vegano", 19, "Alcoólicos", 22, "Zero", 25, "Gelatos Proteicos", 28, 7), 5)) + (ROUND(M33,4) > INDEX('Tabela de ingredientes'!$O$1:$V$30, SWITCH(B33, "Gelatos de Leite", 8, "Sorbets", 11, "Gelatos de Leite com Fruta", 14, "Chocolate base água", 17, "Vegano", 20, "Alcoólicos", 23, "Zero", 26, "Gelatos Proteicos", 29, 8), 5)) + (ROUND(N33,4) < INDEX('Tabela de ingredientes'!$O$1:$V$30, SWITCH(B33, "Gelatos de Leite", 7, "Sorbets", 10, "Gelatos de Leite com Fruta", 13, "Chocolate base água", 16, "Vegano", 19, "Alcoólicos", 22, "Zero", 25, "Gelatos Proteicos", 28, 7), 6)) + (ROUND(N33,4) > INDEX('Tabela de ingredientes'!$O$1:$V$30, SWITCH(B33, "Gelatos de Leite", 8, "Sorbets", 11, "Gelatos de Leite com Fruta", 14, "Chocolate base água", 17, "Vegano", 20, "Alcoólicos", 23, "Zero", 26, "Gelatos Proteicos", 29, 8), 6)) + (ROUND(O33,4) < INDEX('Tabela de ingredientes'!$O$1:$V$30, SWITCH(B33, "Gelatos de Leite", 7, "Sorbets", 10, "Gelatos de Leite com Fruta", 13, "Chocolate base água", 16, "Vegano", 19, "Alcoólicos", 22, "Zero", 25, "Gelatos Proteicos", 28, 7), 7)) + (ROUND(O33,4) > INDEX('Tabela de ingredientes'!$O$1:$V$30, SWITCH(B33, "Gelatos de Leite", 8, "Sorbets", 11, "Gelatos de Leite com Fruta", 14, "Chocolate base água", 17, "Vegano", 20, "Alcoólicos", 23, "Zero", 26, "Gelatos Proteicos", 29, 8), 7)) + (ROUND(P33,4) < INDEX('Tabela de ingredientes'!$O$1:$V$30, SWITCH(B33, "Gelatos de Leite", 7, "Sorbets", 10, "Gelatos de Leite com Fruta", 13, "Chocolate base água", 16, "Vegano", 19, "Alcoólicos", 22, "Zero", 25, "Gelatos Proteicos", 28, 7), 8)) + (ROUND(P33,4) > INDEX('Tabela de ingredientes'!$O$1:$V$30, SWITCH(B33, "Gelatos de Leite", 8, "Sorbets", 11, "Gelatos de Leite com Fruta", 14, "Chocolate base água", 17, "Vegano", 20, "Alcoólicos", 23, "Zero", 26, "Gelatos Proteicos", 29, 8), 8)) + IF(B33="Gelatos Proteicos", (ROUND(Q33,4)<'Tabela de ingredientes'!$W$28)+(ROUND(Q33,4)>'Tabela de ingredientes'!$W$29), 0) = 0, "Ok", "Revisar"))} -> Ok
A34: =IFERROR(__xludf.DUMMYFUNCTION("""COMPUTED_VALUE"""),"Gelato de Caffè Bianco (Addolcire)") -> Gelato de Caffè Bianco (Addolcire) | B34: Gelatos de Leite | C34: 7 | D34: 991 | E34: Diferente (991 g) | F34: 11.731988 | G34: 0.70391927 | H34: 32.062904 | I34: 0.17361251 | J34: 0.097265388 | K34: 0.10082745 | L34: 0.0040363269 | M34: 0.37574168 | N34: 0.62425832 | O34: 167.15358 | P34: 239.21292 | Q34: 0.038698285 | R34: 9.5685166 | S34: {=IF(A34="","", IF( (ROUND(I34,4) < INDEX('Tabela de ingredientes'!$O$1:$V$30, SWITCH(B34, "Gelatos de Leite", 7, "Sorbets", 10, "Gelatos de Leite com Fruta", 13, "Chocolate base água", 16, "Vegano", 19, "Alcoólicos", 22, "Zero", 25, "Gelatos Proteicos", 28, 7), 1)) + (ROUND(I34,4) > INDEX('Tabela de ingredientes'!$O$1:$V$30, SWITCH(B34, "Gelatos de Leite", 8, "Sorbets", 11, "Gelatos de Leite com Fruta", 14, "Chocolate base água", 17, "Vegano", 20, "Alcoólicos", 23, "Zero", 26, "Gelatos Proteicos", 29, 8), 1)) + (ROUND(J34,4) < INDEX('Tabela de ingredientes'!$O$1:$V$30, SWITCH(B34, "Gelatos de Leite", 7, "Sorbets", 10, "Gelatos de Leite com Fruta", 13, "Chocolate base água", 16, "Vegano", 19, "Alcoólicos", 22, "Zero", 25, "Gelatos Proteicos", 28, 7), 2)) + (ROUND(J34,4) > INDEX('Tabela de ingredientes'!$O$1:$V$30, SWITCH(B34, "Gelatos de Leite", 8, "Sorbets", 11, "Gelatos de Leite com Fruta", 14, "Chocolate base água", 17, "Vegano", 20, "Alcoólicos", 23, "Zero", 26, "Gelatos Proteicos", 29, 8), 2)) + (ROUND(K34,4) < INDEX('Tabela de ingredientes'!$O$1:$V$30, SWITCH(B34, "Gelatos de Leite", 7, "Sorbets", 10, "Gelatos de Leite com Fruta", 13, "Chocolate base água", 16, "Vegano", 19, "Alcoólicos", 22, "Zero", 25, "Gelatos Proteicos", 28, 7), 3)) + (ROUND(K34,4) > INDEX('Tabela de ingredientes'!$O$1:$V$30, SWITCH(B34, "Gelatos de Leite", 8, "Sorbets", 11, "Gelatos de Leite com Fruta", 14, "Chocolate base água", 17, "Vegano", 20, "Alcoólicos", 23, "Zero", 26, "Gelatos Proteicos", 29, 8), 3)) + (ROUND(L34,4) < INDEX('Tabela de ingredientes'!$O$1:$V$30, SWITCH(B34, "Gelatos de Leite", 7, "Sorbets", 10, "Gelatos de Leite com Fruta", 13, "Chocolate base água", 16, "Vegano", 19, "Alcoólicos", 22, "Zero", 25, "Gelatos Proteicos", 28, 7), 4)) + (ROUND(L34,4) > INDEX('Tabela de ingredientes'!$O$1:$V$30, SWITCH(B34, "Gelatos de Leite", 8, "Sorbets", 11, "Gelatos de Leite com Fruta", 14, "Chocolate base água", 17, "Vegano", 20, "Alcoólicos", 23, "Zero", 26, "Gelatos Proteicos", 29, 8), 4)) + (ROUND(M34,4) < INDEX('Tabela de ingredientes'!$O$1:$V$30, SWITCH(B34, "Gelatos de Leite", 7, "Sorbets", 10, "Gelatos de Leite com Fruta", 13, "Chocolate base água", 16, "Vegano", 19, "Alcoólicos", 22, "Zero", 25, "Gelatos Proteicos", 28, 7), 5)) + (ROUND(M34,4) > INDEX('Tabela de ingredientes'!$O$1:$V$30, SWITCH(B34, "Gelatos de Leite", 8, "Sorbets", 11, "Gelatos de Leite com Fruta", 14, "Chocolate base água", 17, "Vegano", 20, "Alcoólicos", 23, "Zero", 26, "Gelatos Proteicos", 29, 8), 5)) + (ROUND(N34,4) < INDEX('Tabela de ingredientes'!$O$1:$V$30, SWITCH(B34, "Gelatos de Leite", 7, "Sorbets", 10, "Gelatos de Leite com Fruta", 13, "Chocolate base água", 16, "Vegano", 19, "Alcoólicos", 22, "Zero", 25, "Gelatos Proteicos", 28, 7), 6)) + (ROUND(N34,4) > INDEX('Tabela de ingredientes'!$O$1:$V$30, SWITCH(B34, "Gelatos de Leite", 8, "Sorbets", 11, "Gelatos de Leite com Fruta", 14, "Chocolate base água", 17, "Vegano", 20, "Alcoólicos", 23, "Zero", 26, "Gelatos Proteicos", 29, 8), 6)) + (ROUND(O34,4) < INDEX('Tabela de ingredientes'!$O$1:$V$30, SWITCH(B34, "Gelatos de Leite", 7, "Sorbets", 10, "Gelatos de Leite com Fruta", 13, "Chocolate base água", 16, "Vegano", 19, "Alcoólicos", 22, "Zero", 25, "Gelatos Proteicos", 28, 7), 7)) + (ROUND(O34,4) > INDEX('Tabela de ingredientes'!$O$1:$V$30, SWITCH(B34, "Gelatos de Leite", 8, "Sorbets", 11, "Gelatos de Leite com Fruta", 14, "Chocolate base água", 17, "Vegano", 20, "Alcoólicos", 23, "Zero", 26, "Gelatos Proteicos", 29, 8), 7)) + (ROUND(P34,4) < INDEX('Tabela de ingredientes'!$O$1:$V$30, SWITCH(B34, "Gelatos de Leite", 7, "Sorbets", 10, "Gelatos de Leite com Fruta", 13, "Chocolate base água", 16, "Vegano", 19, "Alcoólicos", 22, "Zero", 25, "Gelatos Proteicos", 28, 7), 8)) + (ROUND(P34,4) > INDEX('Tabela de ingredientes'!$O$1:$V$30, SWITCH(B34, "Gelatos de Leite", 8, "Sorbets", 11, "Gelatos de Leite com Fruta", 14, "Chocolate base água", 17, "Vegano", 20, "Alcoólicos", 23, "Zero", 26, "Gelatos Proteicos", 29, 8), 8)) + IF(B34="Gelatos Proteicos", (ROUND(Q34,4)<'Tabela de ingredientes'!$W$28)+(ROUND(Q34,4)>'Tabela de ingredientes'!$W$29), 0) = 0, "Ok", "Revisar"))} -> Ok
A35: =IFERROR(__xludf.DUMMYFUNCTION("""COMPUTED_VALUE"""),"Gelato de Iogurte com Amarena (Addolcire)") -> Gelato de Iogurte com Amarena (Addolcire) | B35: Gelatos de Leite | C35: 9 | D35: 1040 | E35: Diferente (1040 g) | F35: 9.6701923 | G35: 0.58021154 | H35: 30.356119 | I35: 0.24125 | J35: 0.044870192 | K35: 0.073653846 | L35: 0.0046153846 | M35: 0.36438942 | N35: 0.63561058 | O35: 184.21442 | P35: 331.06731 | Q35: 0.033447115 | R35: 13.242692 | S35: {=IF(A35="","", IF( (ROUND(I35,4) < INDEX('Tabela de ingredientes'!$O$1:$V$30, SWITCH(B35, "Gelatos de Leite", 7, "Sorbets", 10, "Gelatos de Leite com Fruta", 13, "Chocolate base água", 16, "Vegano", 19, "Alcoólicos", 22, "Zero", 25, "Gelatos Proteicos", 28, 7), 1)) + (ROUND(I35,4) > INDEX('Tabela de ingredientes'!$O$1:$V$30, SWITCH(B35, "Gelatos de Leite", 8, "Sorbets", 11, "Gelatos de Leite com Fruta", 14, "Chocolate base água", 17, "Vegano", 20, "Alcoólicos", 23, "Zero", 26, "Gelatos Proteicos", 29, 8), 1)) + (ROUND(J35,4) < INDEX('Tabela de ingredientes'!$O$1:$V$30, SWITCH(B35, "Gelatos de Leite", 7, "Sorbets", 10, "Gelatos de Leite com Fruta", 13, "Chocolate base água", 16, "Vegano", 19, "Alcoólicos", 22, "Zero", 25, "Gelatos Proteicos", 28, 7), 2)) + (ROUND(J35,4) > INDEX('Tabela de ingredientes'!$O$1:$V$30, SWITCH(B35, "Gelatos de Leite", 8, "Sorbets", 11, "Gelatos de Leite com Fruta", 14, "Chocolate base água", 17, "Vegano", 20, "Alcoólicos", 23, "Zero", 26, "Gelatos Proteicos", 29, 8), 2)) + (ROUND(K35,4) < INDEX('Tabela de ingredientes'!$O$1:$V$30, SWITCH(B35, "Gelatos de Leite", 7, "Sorbets", 10, "Gelatos de Leite com Fruta", 13, "Chocolate base água", 16, "Vegano", 19, "Alcoólicos", 22, "Zero", 25, "Gelatos Proteicos", 28, 7), 3)) + (ROUND(K35,4) > INDEX('Tabela de ingredientes'!$O$1:$V$30, SWITCH(B35, "Gelatos de Leite", 8, "Sorbets", 11, "Gelatos de Leite com Fruta", 14, "Chocolate base água", 17, "Vegano", 20, "Alcoólicos", 23, "Zero", 26, "Gelatos Proteicos", 29, 8), 3)) + (ROUND(L35,4) < INDEX('Tabela de ingredientes'!$O$1:$V$30, SWITCH(B35, "Gelatos de Leite", 7, "Sorbets", 10, "Gelatos de Leite com Fruta", 13, "Chocolate base água", 16, "Vegano", 19, "Alcoólicos", 22, "Zero", 25, "Gelatos Proteicos", 28, 7), 4)) + (ROUND(L35,4) > INDEX('Tabela de ingredientes'!$O$1:$V$30, SWITCH(B35, "Gelatos de Leite", 8, "Sorbets", 11, "Gelatos de Leite com Fruta", 14, "Chocolate base água", 17, "Vegano", 20, "Alcoólicos", 23, "Zero", 26, "Gelatos Proteicos", 29, 8), 4)) + (ROUND(M35,4) < INDEX('Tabela de ingredientes'!$O$1:$V$30, SWITCH(B35, "Gelatos de Leite", 7, "Sorbets", 10, "Gelatos de Leite com Fruta", 13, "Chocolate base água", 16, "Vegano", 19, "Alcoólicos", 22, "Zero", 25, "Gelatos Proteicos", 28, 7), 5)) + (ROUND(M35,4) > INDEX('Tabela de ingredientes'!$O$1:$V$30, SWITCH(B35, "Gelatos de Leite", 8, "Sorbets", 11, "Gelatos de Leite com Fruta", 14, "Chocolate base água", 17, "Vegano", 20, "Alcoólicos", 23, "Zero", 26, "Gelatos Proteicos", 29, 8), 5)) + (ROUND(N35,4) < INDEX('Tabela de ingredientes'!$O$1:$V$30, SWITCH(B35, "Gelatos de Leite", 7, "Sorbets", 10, "Gelatos de Leite com Fruta", 13, "Chocolate base água", 16, "Vegano", 19, "Alcoólicos", 22, "Zero", 25, "Gelatos Proteicos", 28, 7), 6)) + (ROUND(N35,4) > INDEX('Tabela de ingredientes'!$O$1:$V$30, SWITCH(B35, "Gelatos de Leite", 8, "Sorbets", 11, "Gelatos de Leite com Fruta", 14, "Chocolate base água", 17, "Vegano", 20, "Alcoólicos", 23, "Zero", 26, "Gelatos Proteicos", 29, 8), 6)) + (ROUND(O35,4) < INDEX('Tabela de ingredientes'!$O$1:$V$30, SWITCH(B35, "Gelatos de Leite", 7, "Sorbets", 10, "Gelatos de Leite com Fruta", 13, "Chocolate base água", 16, "Vegano", 19, "Alcoólicos", 22, "Zero", 25, "Gelatos Proteicos", 28, 7), 7)) + (ROUND(O35,4) > INDEX('Tabela de ingredientes'!$O$1:$V$30, SWITCH(B35, "Gelatos de Leite", 8, "Sorbets", 11, "Gelatos de Leite com Fruta", 14, "Chocolate base água", 17, "Vegano", 20, "Alcoólicos", 23, "Zero", 26, "Gelatos Proteicos", 29, 8), 7)) + (ROUND(P35,4) < INDEX('Tabela de ingredientes'!$O$1:$V$30, SWITCH(B35, "Gelatos de Leite", 7, "Sorbets", 10, "Gelatos de Leite com Fruta", 13, "Chocolate base água", 16, "Vegano", 19, "Alcoólicos", 22, "Zero", 25, "Gelatos Proteicos", 28, 7), 8)) + (ROUND(P35,4) > INDEX('Tabela de ingredientes'!$O$1:$V$30, SWITCH(B35, "Gelatos de Leite", 8, "Sorbets", 11, "Gelatos de Leite com Fruta", 14, "Chocolate base água", 17, "Vegano", 20, "Alcoólicos", 23, "Zero", 26, "Gelatos Proteicos", 29, 8), 8)) + IF(B35="Gelatos Proteicos", (ROUND(Q35,4)<'Tabela de ingredientes'!$W$28)+(ROUND(Q35,4)>'Tabela de ingredientes'!$W$29), 0) = 0, "Ok", "Revisar"))} -> Revisar
A36: =IFERROR(__xludf.DUMMYFUNCTION("""COMPUTED_VALUE"""),"Gelato de Cheesecake (Addolcire)") -> Gelato de Cheesecake (Addolcire) | B36: Gelatos de Leite | C36: 8 | D36: 1018 | E36: Diferente (1018 g) | F36: 17.544597 | G36: 1.0526758 | H36: 36.874667 | I36: 0.21115914 | J36: 0.10264244 | K36: 0.096149312 | L36: 0.0039292731 | M36: 0.41388016 | N36: 0.58611984 | O36: 204.08841 | P36: 267.70138 | Q36: 0.04618664 | R36: 10.708055 | S36: {=IF(A36="","", IF( (ROUND(I36,4) < INDEX('Tabela de ingredientes'!$O$1:$V$30, SWITCH(B36, "Gelatos de Leite", 7, "Sorbets", 10, "Gelatos de Leite com Fruta", 13, "Chocolate base água", 16, "Vegano", 19, "Alcoólicos", 22, "Zero", 25, "Gelatos Proteicos", 28, 7), 1)) + (ROUND(I36,4) > INDEX('Tabela de ingredientes'!$O$1:$V$30, SWITCH(B36, "Gelatos de Leite", 8, "Sorbets", 11, "Gelatos de Leite com Fruta", 14, "Chocolate base água", 17, "Vegano", 20, "Alcoólicos", 23, "Zero", 26, "Gelatos Proteicos", 29, 8), 1)) + (ROUND(J36,4) < INDEX('Tabela de ingredientes'!$O$1:$V$30, SWITCH(B36, "Gelatos de Leite", 7, "Sorbets", 10, "Gelatos de Leite com Fruta", 13, "Chocolate base água", 16, "Vegano", 19, "Alcoólicos", 22, "Zero", 25, "Gelatos Proteicos", 28, 7), 2)) + (ROUND(J36,4) > INDEX('Tabela de ingredientes'!$O$1:$V$30, SWITCH(B36, "Gelatos de Leite", 8, "Sorbets", 11, "Gelatos de Leite com Fruta", 14, "Chocolate base água", 17, "Vegano", 20, "Alcoólicos", 23, "Zero", 26, "Gelatos Proteicos", 29, 8), 2)) + (ROUND(K36,4) < INDEX('Tabela de ingredientes'!$O$1:$V$30, SWITCH(B36, "Gelatos de Leite", 7, "Sorbets", 10, "Gelatos de Leite com Fruta", 13, "Chocolate base água", 16, "Vegano", 19, "Alcoólicos", 22, "Zero", 25, "Gelatos Proteicos", 28, 7), 3)) + (ROUND(K36,4) > INDEX('Tabela de ingredientes'!$O$1:$V$30, SWITCH(B36, "Gelatos de Leite", 8, "Sorbets", 11, "Gelatos de Leite com Fruta", 14, "Chocolate base água", 17, "Vegano", 20, "Alcoólicos", 23, "Zero", 26, "Gelatos Proteicos", 29, 8), 3)) + (ROUND(L36,4) < INDEX('Tabela de ingredientes'!$O$1:$V$30, SWITCH(B36, "Gelatos de Leite", 7, "Sorbets", 10, "Gelatos de Leite com Fruta", 13, "Chocolate base água", 16, "Vegano", 19, "Alcoólicos", 22, "Zero", 25, "Gelatos Proteicos", 28, 7), 4)) + (ROUND(L36,4) > INDEX('Tabela de ingredientes'!$O$1:$V$30, SWITCH(B36, "Gelatos de Leite", 8, "Sorbets", 11, "Gelatos de Leite com Fruta", 14, "Chocolate base água", 17, "Vegano", 20, "Alcoólicos", 23, "Zero", 26, "Gelatos Proteicos", 29, 8), 4)) + (ROUND(M36,4) < INDEX('Tabela de ingredientes'!$O$1:$V$30, SWITCH(B36, "Gelatos de Leite", 7, "Sorbets", 10, "Gelatos de Leite com Fruta", 13, "Chocolate base água", 16, "Vegano", 19, "Alcoólicos", 22, "Zero", 25, "Gelatos Proteicos", 28, 7), 5)) + (ROUND(M36,4) > INDEX('Tabela de ingredientes'!$O$1:$V$30, SWITCH(B36, "Gelatos de Leite", 8, "Sorbets", 11, "Gelatos de Leite com Fruta", 14, "Chocolate base água", 17, "Vegano", 20, "Alcoólicos", 23, "Zero", 26, "Gelatos Proteicos", 29, 8), 5)) + (ROUND(N36,4) < INDEX('Tabela de ingredientes'!$O$1:$V$30, SWITCH(B36, "Gelatos de Leite", 7, "Sorbets", 10, "Gelatos de Leite com Fruta", 13, "Chocolate base água", 16, "Vegano", 19, "Alcoólicos", 22, "Zero", 25, "Gelatos Proteicos", 28, 7), 6)) + (ROUND(N36,4) > INDEX('Tabela de ingredientes'!$O$1:$V$30, SWITCH(B36, "Gelatos de Leite", 8, "Sorbets", 11, "Gelatos de Leite com Fruta", 14, "Chocolate base água", 17, "Vegano", 20, "Alcoólicos", 23, "Zero", 26, "Gelatos Proteicos", 29, 8), 6)) + (ROUND(O36,4) < INDEX('Tabela de ingredientes'!$O$1:$V$30, SWITCH(B36, "Gelatos de Leite", 7, "Sorbets", 10, "Gelatos de Leite com Fruta", 13, "Chocolate base água", 16, "Vegano", 19, "Alcoólicos", 22, "Zero", 25, "Gelatos Proteicos", 28, 7), 7)) + (ROUND(O36,4) > INDEX('Tabela de ingredientes'!$O$1:$V$30, SWITCH(B36, "Gelatos de Leite", 8, "Sorbets", 11, "Gelatos de Leite com Fruta", 14, "Chocolate base água", 17, "Vegano", 20, "Alcoólicos", 23, "Zero", 26, "Gelatos Proteicos", 29, 8), 7)) + (ROUND(P36,4) < INDEX('Tabela de ingredientes'!$O$1:$V$30, SWITCH(B36, "Gelatos de Leite", 7, "Sorbets", 10, "Gelatos de Leite com Fruta", 13, "Chocolate base água", 16, "Vegano", 19, "Alcoólicos", 22, "Zero", 25, "Gelatos Proteicos", 28, 7), 8)) + (ROUND(P36,4) > INDEX('Tabela de ingredientes'!$O$1:$V$30, SWITCH(B36, "Gelatos de Leite", 8, "Sorbets", 11, "Gelatos de Leite com Fruta", 14, "Chocolate base água", 17, "Vegano", 20, "Alcoólicos", 23, "Zero", 26, "Gelatos Proteicos", 29, 8), 8)) + IF(B36="Gelatos Proteicos", (ROUND(Q36,4)<'Tabela de ingredientes'!$W$28)+(ROUND(Q36,4)>'Tabela de ingredientes'!$W$29), 0) = 0, "Ok", "Revisar"))} -> Revisar
A37: =IFERROR(__xludf.DUMMYFUNCTION("""COMPUTED_VALUE"""),"Gelato de Tiramisù (Addolcire)") -> Gelato de Tiramisù (Addolcire) | B37: Gelatos de Leite | C37: 8 | D37: 1021 | E37: Diferente (1021 g) | F37: 12.532811 | G37: 0.75196866 | H37: 32.725837 | I37: 0.2067287 | J37: 0.084598433 | K37: 0.096033301 | L37: 0.014593536 | M37: 0.40195397 | N37: 0.59804603 | O37: 193.3428 | P37: 286.09207 | Q37: 0.045381978 | R37: 11.443683 | S37: {=IF(A37="","", IF( (ROUND(I37,4) < INDEX('Tabela de ingredientes'!$O$1:$V$30, SWITCH(B37, "Gelatos de Leite", 7, "Sorbets", 10, "Gelatos de Leite com Fruta", 13, "Chocolate base água", 16, "Vegano", 19, "Alcoólicos", 22, "Zero", 25, "Gelatos Proteicos", 28, 7), 1)) + (ROUND(I37,4) > INDEX('Tabela de ingredientes'!$O$1:$V$30, SWITCH(B37, "Gelatos de Leite", 8, "Sorbets", 11, "Gelatos de Leite com Fruta", 14, "Chocolate base água", 17, "Vegano", 20, "Alcoólicos", 23, "Zero", 26, "Gelatos Proteicos", 29, 8), 1)) + (ROUND(J37,4) < INDEX('Tabela de ingredientes'!$O$1:$V$30, SWITCH(B37, "Gelatos de Leite", 7, "Sorbets", 10, "Gelatos de Leite com Fruta", 13, "Chocolate base água", 16, "Vegano", 19, "Alcoólicos", 22, "Zero", 25, "Gelatos Proteicos", 28, 7), 2)) + (ROUND(J37,4) > INDEX('Tabela de ingredientes'!$O$1:$V$30, SWITCH(B37, "Gelatos de Leite", 8, "Sorbets", 11, "Gelatos de Leite com Fruta", 14, "Chocolate base água", 17, "Vegano", 20, "Alcoólicos", 23, "Zero", 26, "Gelatos Proteicos", 29, 8), 2)) + (ROUND(K37,4) < INDEX('Tabela de ingredientes'!$O$1:$V$30, SWITCH(B37, "Gelatos de Leite", 7, "Sorbets", 10, "Gelatos de Leite com Fruta", 13, "Chocolate base água", 16, "Vegano", 19, "Alcoólicos", 22, "Zero", 25, "Gelatos Proteicos", 28, 7), 3)) + (ROUND(K37,4) > INDEX('Tabela de ingredientes'!$O$1:$V$30, SWITCH(B37, "Gelatos de Leite", 8, "Sorbets", 11, "Gelatos de Leite com Fruta", 14, "Chocolate base água", 17, "Vegano", 20, "Alcoólicos", 23, "Zero", 26, "Gelatos Proteicos", 29, 8), 3)) + (ROUND(L37,4) < INDEX('Tabela de ingredientes'!$O$1:$V$30, SWITCH(B37, "Gelatos de Leite", 7, "Sorbets", 10, "Gelatos de Leite com Fruta", 13, "Chocolate base água", 16, "Vegano", 19, "Alcoólicos", 22, "Zero", 25, "Gelatos Proteicos", 28, 7), 4)) + (ROUND(L37,4) > INDEX('Tabela de ingredientes'!$O$1:$V$30, SWITCH(B37, "Gelatos de Leite", 8, "Sorbets", 11, "Gelatos de Leite com Fruta", 14, "Chocolate base água", 17, "Vegano", 20, "Alcoólicos", 23, "Zero", 26, "Gelatos Proteicos", 29, 8), 4)) + (ROUND(M37,4) < INDEX('Tabela de ingredientes'!$O$1:$V$30, SWITCH(B37, "Gelatos de Leite", 7, "Sorbets", 10, "Gelatos de Leite com Fruta", 13, "Chocolate base água", 16, "Vegano", 19, "Alcoólicos", 22, "Zero", 25, "Gelatos Proteicos", 28, 7), 5)) + (ROUND(M37,4) > INDEX('Tabela de ingredientes'!$O$1:$V$30, SWITCH(B37, "Gelatos de Leite", 8, "Sorbets", 11, "Gelatos de Leite com Fruta", 14, "Chocolate base água", 17, "Vegano", 20, "Alcoólicos", 23, "Zero", 26, "Gelatos Proteicos", 29, 8), 5)) + (ROUND(N37,4) < INDEX('Tabela de ingredientes'!$O$1:$V$30, SWITCH(B37, "Gelatos de Leite", 7, "Sorbets", 10, "Gelatos de Leite com Fruta", 13, "Chocolate base água", 16, "Vegano", 19, "Alcoólicos", 22, "Zero", 25, "Gelatos Proteicos", 28, 7), 6)) + (ROUND(N37,4) > INDEX('Tabela de ingredientes'!$O$1:$V$30, SWITCH(B37, "Gelatos de Leite", 8, "Sorbets", 11, "Gelatos de Leite com Fruta", 14, "Chocolate base água", 17, "Vegano", 20, "Alcoólicos", 23, "Zero", 26, "Gelatos Proteicos", 29, 8), 6)) + (ROUND(O37,4) < INDEX('Tabela de ingredientes'!$O$1:$V$30, SWITCH(B37, "Gelatos de Leite", 7, "Sorbets", 10, "Gelatos de Leite com Fruta", 13, "Chocolate base água", 16, "Vegano", 19, "Alcoólicos", 22, "Zero", 25, "Gelatos Proteicos", 28, 7), 7)) + (ROUND(O37,4) > INDEX('Tabela de ingredientes'!$O$1:$V$30, SWITCH(B37, "Gelatos de Leite", 8, "Sorbets", 11, "Gelatos de Leite com Fruta", 14, "Chocolate base água", 17, "Vegano", 20, "Alcoólicos", 23, "Zero", 26, "Gelatos Proteicos", 29, 8), 7)) + (ROUND(P37,4) < INDEX('Tabela de ingredientes'!$O$1:$V$30, SWITCH(B37, "Gelatos de Leite", 7, "Sorbets", 10, "Gelatos de Leite com Fruta", 13, "Chocolate base água", 16, "Vegano", 19, "Alcoólicos", 22, "Zero", 25, "Gelatos Proteicos", 28, 7), 8)) + (ROUND(P37,4) > INDEX('Tabela de ingredientes'!$O$1:$V$30, SWITCH(B37, "Gelatos de Leite", 8, "Sorbets", 11, "Gelatos de Leite com Fruta", 14, "Chocolate base água", 17, "Vegano", 20, "Alcoólicos", 23, "Zero", 26, "Gelatos Proteicos", 29, 8), 8)) + IF(B37="Gelatos Proteicos", (ROUND(Q37,4)<'Tabela de ingredientes'!$W$28)+(ROUND(Q37,4)>'Tabela de ingredientes'!$W$29), 0) = 0, "Ok", "Revisar"))} -> Ok
A38: =IFERROR(__xludf.DUMMYFUNCTION("""COMPUTED_VALUE"""),"Gelato de Queijo de Cabra e Pecã (Addolcire)") -> Gelato de Queijo de Cabra e Pecã (Addolcire) | B38: Gelatos de Leite | C38: 8 | D38: 1038 | E38: Diferente (1038 g) | F38: 22.825626 | G38: 1.3695376 | H38: 41.246379 | I38: 0.16324663 | J38: 0.10183044 | K38: 0.098631985 | L38: 0.0038535645 | M38: 0.36756262 | N38: 0.63243738 | O38: 150.90655 | P38: 242.82274 | Q38: 0.055867052 | R38: 9.7129094 | S38: {=IF(A38="","", IF( (ROUND(I38,4) < INDEX('Tabela de ingredientes'!$O$1:$V$30, SWITCH(B38, "Gelatos de Leite", 7, "Sorbets", 10, "Gelatos de Leite com Fruta", 13, "Chocolate base água", 16, "Vegano", 19, "Alcoólicos", 22, "Zero", 25, "Gelatos Proteicos", 28, 7), 1)) + (ROUND(I38,4) > INDEX('Tabela de ingredientes'!$O$1:$V$30, SWITCH(B38, "Gelatos de Leite", 8, "Sorbets", 11, "Gelatos de Leite com Fruta", 14, "Chocolate base água", 17, "Vegano", 20, "Alcoólicos", 23, "Zero", 26, "Gelatos Proteicos", 29, 8), 1)) + (ROUND(J38,4) < INDEX('Tabela de ingredientes'!$O$1:$V$30, SWITCH(B38, "Gelatos de Leite", 7, "Sorbets", 10, "Gelatos de Leite com Fruta", 13, "Chocolate base água", 16, "Vegano", 19, "Alcoólicos", 22, "Zero", 25, "Gelatos Proteicos", 28, 7), 2)) + (ROUND(J38,4) > INDEX('Tabela de ingredientes'!$O$1:$V$30, SWITCH(B38, "Gelatos de Leite", 8, "Sorbets", 11, "Gelatos de Leite com Fruta", 14, "Chocolate base água", 17, "Vegano", 20, "Alcoólicos", 23, "Zero", 26, "Gelatos Proteicos", 29, 8), 2)) + (ROUND(K38,4) < INDEX('Tabela de ingredientes'!$O$1:$V$30, SWITCH(B38, "Gelatos de Leite", 7, "Sorbets", 10, "Gelatos de Leite com Fruta", 13, "Chocolate base água", 16, "Vegano", 19, "Alcoólicos", 22, "Zero", 25, "Gelatos Proteicos", 28, 7), 3)) + (ROUND(K38,4) > INDEX('Tabela de ingredientes'!$O$1:$V$30, SWITCH(B38, "Gelatos de Leite", 8, "Sorbets", 11, "Gelatos de Leite com Fruta", 14, "Chocolate base água", 17, "Vegano", 20, "Alcoólicos", 23, "Zero", 26, "Gelatos Proteicos", 29, 8), 3)) + (ROUND(L38,4) < INDEX('Tabela de ingredientes'!$O$1:$V$30, SWITCH(B38, "Gelatos de Leite", 7, "Sorbets", 10, "Gelatos de Leite com Fruta", 13, "Chocolate base água", 16, "Vegano", 19, "Alcoólicos", 22, "Zero", 25, "Gelatos Proteicos", 28, 7), 4)) + (ROUND(L38,4) > INDEX('Tabela de ingredientes'!$O$1:$V$30, SWITCH(B38, "Gelatos de Leite", 8, "Sorbets", 11, "Gelatos de Leite com Fruta", 14, "Chocolate base água", 17, "Vegano", 20, "Alcoólicos", 23, "Zero", 26, "Gelatos Proteicos", 29, 8), 4)) + (ROUND(M38,4) < INDEX('Tabela de ingredientes'!$O$1:$V$30, SWITCH(B38, "Gelatos de Leite", 7, "Sorbets", 10, "Gelatos de Leite com Fruta", 13, "Chocolate base água", 16, "Vegano", 19, "Alcoólicos", 22, "Zero", 25, "Gelatos Proteicos", 28, 7), 5)) + (ROUND(M38,4) > INDEX('Tabela de ingredientes'!$O$1:$V$30, SWITCH(B38, "Gelatos de Leite", 8, "Sorbets", 11, "Gelatos de Leite com Fruta", 14, "Chocolate base água", 17, "Vegano", 20, "Alcoólicos", 23, "Zero", 26, "Gelatos Proteicos", 29, 8), 5)) + (ROUND(N38,4) < INDEX('Tabela de ingredientes'!$O$1:$V$30, SWITCH(B38, "Gelatos de Leite", 7, "Sorbets", 10, "Gelatos de Leite com Fruta", 13, "Chocolate base água", 16, "Vegano", 19, "Alcoólicos", 22, "Zero", 25, "Gelatos Proteicos", 28, 7), 6)) + (ROUND(N38,4) > INDEX('Tabela de ingredientes'!$O$1:$V$30, SWITCH(B38, "Gelatos de Leite", 8, "Sorbets", 11, "Gelatos de Leite com Fruta", 14, "Chocolate base água", 17, "Vegano", 20, "Alcoólicos", 23, "Zero", 26, "Gelatos Proteicos", 29, 8), 6)) + (ROUND(O38,4) < INDEX('Tabela de ingredientes'!$O$1:$V$30, SWITCH(B38, "Gelatos de Leite", 7, "Sorbets", 10, "Gelatos de Leite com Fruta", 13, "Chocolate base água", 16, "Vegano", 19, "Alcoólicos", 22, "Zero", 25, "Gelatos Proteicos", 28, 7), 7)) + (ROUND(O38,4) > INDEX('Tabela de ingredientes'!$O$1:$V$30, SWITCH(B38, "Gelatos de Leite", 8, "Sorbets", 11, "Gelatos de Leite com Fruta", 14, "Chocolate base água", 17, "Vegano", 20, "Alcoólicos", 23, "Zero", 26, "Gelatos Proteicos", 29, 8), 7)) + (ROUND(P38,4) < INDEX('Tabela de ingredientes'!$O$1:$V$30, SWITCH(B38, "Gelatos de Leite", 7, "Sorbets", 10, "Gelatos de Leite com Fruta", 13, "Chocolate base água", 16, "Vegano", 19, "Alcoólicos", 22, "Zero", 25, "Gelatos Proteicos", 28, 7), 8)) + (ROUND(P38,4) > INDEX('Tabela de ingredientes'!$O$1:$V$30, SWITCH(B38, "Gelatos de Leite", 8, "Sorbets", 11, "Gelatos de Leite com Fruta", 14, "Chocolate base água", 17, "Vegano", 20, "Alcoólicos", 23, "Zero", 26, "Gelatos Proteicos", 29, 8), 8)) + IF(B38="Gelatos Proteicos", (ROUND(Q38,4)<'Tabela de ingredientes'!$W$28)+(ROUND(Q38,4)>'Tabela de ingredientes'!$W$29), 0) = 0, "Ok", "Revisar"))} -> Ok
A39: =IFERROR(__xludf.DUMMYFUNCTION("""COMPUTED_VALUE"""),"Gelato de Caramelo Brûlée (Addolcire)") -> Gelato de Caramelo Brûlée (Addolcire) | B39: Gelatos de Leite | C39: 7 | D39: 1081 | E39: Diferente (1081 g) | F39: 14.92729 | G39: 0.89563737 | H39: 34.708021 | I39: 0.16933395 | J39: 0.10443108 | K39: 0.10658649 | L39: 0.0037002775 | M39: 0.3840518 | N39: 0.6159482 | O39: 165.8753 | P39: 224.66235 | Q39: 0.044098057 | R39: 8.986494 | S39: {=IF(A39="","", IF( (ROUND(I39,4) < INDEX('Tabela de ingredientes'!$O$1:$V$30, SWITCH(B39, "Gelatos de Leite", 7, "Sorbets", 10, "Gelatos de Leite com Fruta", 13, "Chocolate base água", 16, "Vegano", 19, "Alcoólicos", 22, "Zero", 25, "Gelatos Proteicos", 28, 7), 1)) + (ROUND(I39,4) > INDEX('Tabela de ingredientes'!$O$1:$V$30, SWITCH(B39, "Gelatos de Leite", 8, "Sorbets", 11, "Gelatos de Leite com Fruta", 14, "Chocolate base água", 17, "Vegano", 20, "Alcoólicos", 23, "Zero", 26, "Gelatos Proteicos", 29, 8), 1)) + (ROUND(J39,4) < INDEX('Tabela de ingredientes'!$O$1:$V$30, SWITCH(B39, "Gelatos de Leite", 7, "Sorbets", 10, "Gelatos de Leite com Fruta", 13, "Chocolate base água", 16, "Vegano", 19, "Alcoólicos", 22, "Zero", 25, "Gelatos Proteicos", 28, 7), 2)) + (ROUND(J39,4) > INDEX('Tabela de ingredientes'!$O$1:$V$30, SWITCH(B39, "Gelatos de Leite", 8, "Sorbets", 11, "Gelatos de Leite com Fruta", 14, "Chocolate base água", 17, "Vegano", 20, "Alcoólicos", 23, "Zero", 26, "Gelatos Proteicos", 29, 8), 2)) + (ROUND(K39,4) < INDEX('Tabela de ingredientes'!$O$1:$V$30, SWITCH(B39, "Gelatos de Leite", 7, "Sorbets", 10, "Gelatos de Leite com Fruta", 13, "Chocolate base água", 16, "Vegano", 19, "Alcoólicos", 22, "Zero", 25, "Gelatos Proteicos", 28, 7), 3)) + (ROUND(K39,4) > INDEX('Tabela de ingredientes'!$O$1:$V$30, SWITCH(B39, "Gelatos de Leite", 8, "Sorbets", 11, "Gelatos de Leite com Fruta", 14, "Chocolate base água", 17, "Vegano", 20, "Alcoólicos", 23, "Zero", 26, "Gelatos Proteicos", 29, 8), 3)) + (ROUND(L39,4) < INDEX('Tabela de ingredientes'!$O$1:$V$30, SWITCH(B39, "Gelatos de Leite", 7, "Sorbets", 10, "Gelatos de Leite com Fruta", 13, "Chocolate base água", 16, "Vegano", 19, "Alcoólicos", 22, "Zero", 25, "Gelatos Proteicos", 28, 7), 4)) + (ROUND(L39,4) > INDEX('Tabela de ingredientes'!$O$1:$V$30, SWITCH(B39, "Gelatos de Leite", 8, "Sorbets", 11, "Gelatos de Leite com Fruta", 14, "Chocolate base água", 17, "Vegano", 20, "Alcoólicos", 23, "Zero", 26, "Gelatos Proteicos", 29, 8), 4)) + (ROUND(M39,4) < INDEX('Tabela de ingredientes'!$O$1:$V$30, SWITCH(B39, "Gelatos de Leite", 7, "Sorbets", 10, "Gelatos de Leite com Fruta", 13, "Chocolate base água", 16, "Vegano", 19, "Alcoólicos", 22, "Zero", 25, "Gelatos Proteicos", 28, 7), 5)) + (ROUND(M39,4) > INDEX('Tabela de ingredientes'!$O$1:$V$30, SWITCH(B39, "Gelatos de Leite", 8, "Sorbets", 11, "Gelatos de Leite com Fruta", 14, "Chocolate base água", 17, "Vegano", 20, "Alcoólicos", 23, "Zero", 26, "Gelatos Proteicos", 29, 8), 5)) + (ROUND(N39,4) < INDEX('Tabela de ingredientes'!$O$1:$V$30, SWITCH(B39, "Gelatos de Leite", 7, "Sorbets", 10, "Gelatos de Leite com Fruta", 13, "Chocolate base água", 16, "Vegano", 19, "Alcoólicos", 22, "Zero", 25, "Gelatos Proteicos", 28, 7), 6)) + (ROUND(N39,4) > INDEX('Tabela de ingredientes'!$O$1:$V$30, SWITCH(B39, "Gelatos de Leite", 8, "Sorbets", 11, "Gelatos de Leite com Fruta", 14, "Chocolate base água", 17, "Vegano", 20, "Alcoólicos", 23, "Zero", 26, "Gelatos Proteicos", 29, 8), 6)) + (ROUND(O39,4) < INDEX('Tabela de ingredientes'!$O$1:$V$30, SWITCH(B39, "Gelatos de Leite", 7, "Sorbets", 10, "Gelatos de Leite com Fruta", 13, "Chocolate base água", 16, "Vegano", 19, "Alcoólicos", 22, "Zero", 25, "Gelatos Proteicos", 28, 7), 7)) + (ROUND(O39,4) > INDEX('Tabela de ingredientes'!$O$1:$V$30, SWITCH(B39, "Gelatos de Leite", 8, "Sorbets", 11, "Gelatos de Leite com Fruta", 14, "Chocolate base água", 17, "Vegano", 20, "Alcoólicos", 23, "Zero", 26, "Gelatos Proteicos", 29, 8), 7)) + (ROUND(P39,4) < INDEX('Tabela de ingredientes'!$O$1:$V$30, SWITCH(B39, "Gelatos de Leite", 7, "Sorbets", 10, "Gelatos de Leite com Fruta", 13, "Chocolate base água", 16, "Vegano", 19, "Alcoólicos", 22, "Zero", 25, "Gelatos Proteicos", 28, 7), 8)) + (ROUND(P39,4) > INDEX('Tabela de ingredientes'!$O$1:$V$30, SWITCH(B39, "Gelatos de Leite", 8, "Sorbets", 11, "Gelatos de Leite com Fruta", 14, "Chocolate base água", 17, "Vegano", 20, "Alcoólicos", 23, "Zero", 26, "Gelatos Proteicos", 29, 8), 8)) + IF(B39="Gelatos Proteicos", (ROUND(Q39,4)<'Tabela de ingredientes'!$W$28)+(ROUND(Q39,4)>'Tabela de ingredientes'!$W$29), 0) = 0, "Ok", "Revisar"))} -> Ok
A40: =IFERROR(__xludf.DUMMYFUNCTION("""COMPUTED_VALUE"""),"Gelato de Pistache (Addolcire)") -> Gelato de Pistache (Addolcire) | B40: Gelatos de Leite | C40: 9 | D40: 942 | E40: Diferente (942 g) | F40: 47.080042 | G40: 2.8248025 | H40: 61.324538 | I40: 0.15334395 | J40: 0.12164544 | K40: 0.097154989 | L40: 0.056687898 | M40: 0.42883227 | N40: 0.57116773 | O40: 135.23694 | P40: 241.8896 | Q40: 0.053704883 | R40: 9.6755839 | S40: {=IF(A40="","", IF( (ROUND(I40,4) < INDEX('Tabela de ingredientes'!$O$1:$V$30, SWITCH(B40, "Gelatos de Leite", 7, "Sorbets", 10, "Gelatos de Leite com Fruta", 13, "Chocolate base água", 16, "Vegano", 19, "Alcoólicos", 22, "Zero", 25, "Gelatos Proteicos", 28, 7), 1)) + (ROUND(I40,4) > INDEX('Tabela de ingredientes'!$O$1:$V$30, SWITCH(B40, "Gelatos de Leite", 8, "Sorbets", 11, "Gelatos de Leite com Fruta", 14, "Chocolate base água", 17, "Vegano", 20, "Alcoólicos", 23, "Zero", 26, "Gelatos Proteicos", 29, 8), 1)) + (ROUND(J40,4) < INDEX('Tabela de ingredientes'!$O$1:$V$30, SWITCH(B40, "Gelatos de Leite", 7, "Sorbets", 10, "Gelatos de Leite com Fruta", 13, "Chocolate base água", 16, "Vegano", 19, "Alcoólicos", 22, "Zero", 25, "Gelatos Proteicos", 28, 7), 2)) + (ROUND(J40,4) > INDEX('Tabela de ingredientes'!$O$1:$V$30, SWITCH(B40, "Gelatos de Leite", 8, "Sorbets", 11, "Gelatos de Leite com Fruta", 14, "Chocolate base água", 17, "Vegano", 20, "Alcoólicos", 23, "Zero", 26, "Gelatos Proteicos", 29, 8), 2)) + (ROUND(K40,4) < INDEX('Tabela de ingredientes'!$O$1:$V$30, SWITCH(B40, "Gelatos de Leite", 7, "Sorbets", 10, "Gelatos de Leite com Fruta", 13, "Chocolate base água", 16, "Vegano", 19, "Alcoólicos", 22, "Zero", 25, "Gelatos Proteicos", 28, 7), 3)) + (ROUND(K40,4) > INDEX('Tabela de ingredientes'!$O$1:$V$30, SWITCH(B40, "Gelatos de Leite", 8, "Sorbets", 11, "Gelatos de Leite com Fruta", 14, "Chocolate base água", 17, "Vegano", 20, "Alcoólicos", 23, "Zero", 26, "Gelatos Proteicos", 29, 8), 3)) + (ROUND(L40,4) < INDEX('Tabela de ingredientes'!$O$1:$V$30, SWITCH(B40, "Gelatos de Leite", 7, "Sorbets", 10, "Gelatos de Leite com Fruta", 13, "Chocolate base água", 16, "Vegano", 19, "Alcoólicos", 22, "Zero", 25, "Gelatos Proteicos", 28, 7), 4)) + (ROUND(L40,4) > INDEX('Tabela de ingredientes'!$O$1:$V$30, SWITCH(B40, "Gelatos de Leite", 8, "Sorbets", 11, "Gelatos de Leite com Fruta", 14, "Chocolate base água", 17, "Vegano", 20, "Alcoólicos", 23, "Zero", 26, "Gelatos Proteicos", 29, 8), 4)) + (ROUND(M40,4) < INDEX('Tabela de ingredientes'!$O$1:$V$30, SWITCH(B40, "Gelatos de Leite", 7, "Sorbets", 10, "Gelatos de Leite com Fruta", 13, "Chocolate base água", 16, "Vegano", 19, "Alcoólicos", 22, "Zero", 25, "Gelatos Proteicos", 28, 7), 5)) + (ROUND(M40,4) > INDEX('Tabela de ingredientes'!$O$1:$V$30, SWITCH(B40, "Gelatos de Leite", 8, "Sorbets", 11, "Gelatos de Leite com Fruta", 14, "Chocolate base água", 17, "Vegano", 20, "Alcoólicos", 23, "Zero", 26, "Gelatos Proteicos", 29, 8), 5)) + (ROUND(N40,4) < INDEX('Tabela de ingredientes'!$O$1:$V$30, SWITCH(B40, "Gelatos de Leite", 7, "Sorbets", 10, "Gelatos de Leite com Fruta", 13, "Chocolate base água", 16, "Vegano", 19, "Alcoólicos", 22, "Zero", 25, "Gelatos Proteicos", 28, 7), 6)) + (ROUND(N40,4) > INDEX('Tabela de ingredientes'!$O$1:$V$30, SWITCH(B40, "Gelatos de Leite", 8, "Sorbets", 11, "Gelatos de Leite com Fruta", 14, "Chocolate base água", 17, "Vegano", 20, "Alcoólicos", 23, "Zero", 26, "Gelatos Proteicos", 29, 8), 6)) + (ROUND(O40,4) < INDEX('Tabela de ingredientes'!$O$1:$V$30, SWITCH(B40, "Gelatos de Leite", 7, "Sorbets", 10, "Gelatos de Leite com Fruta", 13, "Chocolate base água", 16, "Vegano", 19, "Alcoólicos", 22, "Zero", 25, "Gelatos Proteicos", 28, 7), 7)) + (ROUND(O40,4) > INDEX('Tabela de ingredientes'!$O$1:$V$30, SWITCH(B40, "Gelatos de Leite", 8, "Sorbets", 11, "Gelatos de Leite com Fruta", 14, "Chocolate base água", 17, "Vegano", 20, "Alcoólicos", 23, "Zero", 26, "Gelatos Proteicos", 29, 8), 7)) + (ROUND(P40,4) < INDEX('Tabela de ingredientes'!$O$1:$V$30, SWITCH(B40, "Gelatos de Leite", 7, "Sorbets", 10, "Gelatos de Leite com Fruta", 13, "Chocolate base água", 16, "Vegano", 19, "Alcoólicos", 22, "Zero", 25, "Gelatos Proteicos", 28, 7), 8)) + (ROUND(P40,4) > INDEX('Tabela de ingredientes'!$O$1:$V$30, SWITCH(B40, "Gelatos de Leite", 8, "Sorbets", 11, "Gelatos de Leite com Fruta", 14, "Chocolate base água", 17, "Vegano", 20, "Alcoólicos", 23, "Zero", 26, "Gelatos Proteicos", 29, 8), 8)) + IF(B40="Gelatos Proteicos", (ROUND(Q40,4)<'Tabela de ingredientes'!$W$28)+(ROUND(Q40,4)>'Tabela de ingredientes'!$W$29), 0) = 0, "Ok", "Revisar"))} -> Revisar
A41: =IFERROR(__xludf.DUMMYFUNCTION("""COMPUTED_VALUE"""),"Gelato de Chocolate Branco e Frutas Vermelhas (Addolcire)") -> Gelato de Chocolate Branco e Frutas Vermelhas (Addolcire) | B41: Gelatos de Leite | C41: 9 | D41: 1000 | E41: 1.000 g (Padrão) | F41: 44.9576 | G41: 2.697456 | H41: 59.56755 | I41: 0.22851 | J41: 0.07996 | K41: 0.07869 | L41: 0.03 | M41: 0.41716 | N41: 0.58284 | O41: 236.7408 | P41: 178.34 | Q41: 0.0258 | R41: 7.1336 | S41: {=IF(A41="","", IF( (ROUND(I41,4) < INDEX('Tabela de ingredientes'!$O$1:$V$30, SWITCH(B41, "Gelatos de Leite", 7, "Sorbets", 10, "Gelatos de Leite com Fruta", 13, "Chocolate base água", 16, "Vegano", 19, "Alcoólicos", 22, "Zero", 25, "Gelatos Proteicos", 28, 7), 1)) + (ROUND(I41,4) > INDEX('Tabela de ingredientes'!$O$1:$V$30, SWITCH(B41, "Gelatos de Leite", 8, "Sorbets", 11, "Gelatos de Leite com Fruta", 14, "Chocolate base água", 17, "Vegano", 20, "Alcoólicos", 23, "Zero", 26, "Gelatos Proteicos", 29, 8), 1)) + (ROUND(J41,4) < INDEX('Tabela de ingredientes'!$O$1:$V$30, SWITCH(B41, "Gelatos de Leite", 7, "Sorbets", 10, "Gelatos de Leite com Fruta", 13, "Chocolate base água", 16, "Vegano", 19, "Alcoólicos", 22, "Zero", 25, "Gelatos Proteicos", 28, 7), 2)) + (ROUND(J41,4) > INDEX('Tabela de ingredientes'!$O$1:$V$30, SWITCH(B41, "Gelatos de Leite", 8, "Sorbets", 11, "Gelatos de Leite com Fruta", 14, "Chocolate base água", 17, "Vegano", 20, "Alcoólicos", 23, "Zero", 26, "Gelatos Proteicos", 29, 8), 2)) + (ROUND(K41,4) < INDEX('Tabela de ingredientes'!$O$1:$V$30, SWITCH(B41, "Gelatos de Leite", 7, "Sorbets", 10, "Gelatos de Leite com Fruta", 13, "Chocolate base água", 16, "Vegano", 19, "Alcoólicos", 22, "Zero", 25, "Gelatos Proteicos", 28, 7), 3)) + (ROUND(K41,4) > INDEX('Tabela de ingredientes'!$O$1:$V$30, SWITCH(B41, "Gelatos de Leite", 8, "Sorbets", 11, "Gelatos de Leite com Fruta", 14, "Chocolate base água", 17, "Vegano", 20, "Alcoólicos", 23, "Zero", 26, "Gelatos Proteicos", 29, 8), 3)) + (ROUND(L41,4) < INDEX('Tabela de ingredientes'!$O$1:$V$30, SWITCH(B41, "Gelatos de Leite", 7, "Sorbets", 10, "Gelatos de Leite com Fruta", 13, "Chocolate base água", 16, "Vegano", 19, "Alcoólicos", 22, "Zero", 25, "Gelatos Proteicos", 28, 7), 4)) + (ROUND(L41,4) > INDEX('Tabela de ingredientes'!$O$1:$V$30, SWITCH(B41, "Gelatos de Leite", 8, "Sorbets", 11, "Gelatos de Leite com Fruta", 14, "Chocolate base água", 17, "Vegano", 20, "Alcoólicos", 23, "Zero", 26, "Gelatos Proteicos", 29, 8), 4)) + (ROUND(M41,4) < INDEX('Tabela de ingredientes'!$O$1:$V$30, SWITCH(B41, "Gelatos de Leite", 7, "Sorbets", 10, "Gelatos de Leite com Fruta", 13, "Chocolate base água", 16, "Vegano", 19, "Alcoólicos", 22, "Zero", 25, "Gelatos Proteicos", 28, 7), 5)) + (ROUND(M41,4) > INDEX('Tabela de ingredientes'!$O$1:$V$30, SWITCH(B41, "Gelatos de Leite", 8, "Sorbets", 11, "Gelatos de Leite com Fruta", 14, "Chocolate base água", 17, "Vegano", 20, "Alcoólicos", 23, "Zero", 26, "Gelatos Proteicos", 29, 8), 5)) + (ROUND(N41,4) < INDEX('Tabela de ingredientes'!$O$1:$V$30, SWITCH(B41, "Gelatos de Leite", 7, "Sorbets", 10, "Gelatos de Leite com Fruta", 13, "Chocolate base água", 16, "Vegano", 19, "Alcoólicos", 22, "Zero", 25, "Gelatos Proteicos", 28, 7), 6)) + (ROUND(N41,4) > INDEX('Tabela de ingredientes'!$O$1:$V$30, SWITCH(B41, "Gelatos de Leite", 8, "Sorbets", 11, "Gelatos de Leite com Fruta", 14, "Chocolate base água", 17, "Vegano", 20, "Alcoólicos", 23, "Zero", 26, "Gelatos Proteicos", 29, 8), 6)) + (ROUND(O41,4) < INDEX('Tabela de ingredientes'!$O$1:$V$30, SWITCH(B41, "Gelatos de Leite", 7, "Sorbets", 10, "Gelatos de Leite com Fruta", 13, "Chocolate base água", 16, "Vegano", 19, "Alcoólicos", 22, "Zero", 25, "Gelatos Proteicos", 28, 7), 7)) + (ROUND(O41,4) > INDEX('Tabela de ingredientes'!$O$1:$V$30, SWITCH(B41, "Gelatos de Leite", 8, "Sorbets", 11, "Gelatos de Leite com Fruta", 14, "Chocolate base água", 17, "Vegano", 20, "Alcoólicos", 23, "Zero", 26, "Gelatos Proteicos", 29, 8), 7)) + (ROUND(P41,4) < INDEX('Tabela de ingredientes'!$O$1:$V$30, SWITCH(B41, "Gelatos de Leite", 7, "Sorbets", 10, "Gelatos de Leite com Fruta", 13, "Chocolate base água", 16, "Vegano", 19, "Alcoólicos", 22, "Zero", 25, "Gelatos Proteicos", 28, 7), 8)) + (ROUND(P41,4) > INDEX('Tabela de ingredientes'!$O$1:$V$30, SWITCH(B41, "Gelatos de Leite", 8, "Sorbets", 11, "Gelatos de Leite com Fruta", 14, "Chocolate base água", 17, "Vegano", 20, "Alcoólicos", 23, "Zero", 26, "Gelatos Proteicos", 29, 8), 8)) + IF(B41="Gelatos Proteicos", (ROUND(Q41,4)<'Tabela de ingredientes'!$W$28)+(ROUND(Q41,4)>'Tabela de ingredientes'!$W$29), 0) = 0, "Ok", "Revisar"))} -> Revisar
A42: =IFERROR(__xludf.DUMMYFUNCTION("""COMPUTED_VALUE"""),"Gelato de Whey Protein com Brownie (Addolcire)") -> Gelato de Whey Protein com Brownie (Addolcire) | B42: Gelatos de Leite | C42: 9 | D42: 939 | E42: Diferente (939 g) | F42: 38.514377 | G42: 2.3108626 | H42: 54.233756 | I42: 0.22172524 | J42: 0.096734114 | K42: 0.13752219 | L42: 0.072683706 | M42: 0.52866525 | N42: 0.47133475 | O42: 216.18743 | P42: 279.02023 | Q42: 0.094462194 | R42: 11.160809 | S42: {=IF(A42="","", IF( (ROUND(I42,4) < INDEX('Tabela de ingredientes'!$O$1:$V$30, SWITCH(B42, "Gelatos de Leite", 7, "Sorbets", 10, "Gelatos de Leite com Fruta", 13, "Chocolate base água", 16, "Vegano", 19, "Alcoólicos", 22, "Zero", 25, "Gelatos Proteicos", 28, 7), 1)) + (ROUND(I42,4) > INDEX('Tabela de ingredientes'!$O$1:$V$30, SWITCH(B42, "Gelatos de Leite", 8, "Sorbets", 11, "Gelatos de Leite com Fruta", 14, "Chocolate base água", 17, "Vegano", 20, "Alcoólicos", 23, "Zero", 26, "Gelatos Proteicos", 29, 8), 1)) + (ROUND(J42,4) < INDEX('Tabela de ingredientes'!$O$1:$V$30, SWITCH(B42, "Gelatos de Leite", 7, "Sorbets", 10, "Gelatos de Leite com Fruta", 13, "Chocolate base água", 16, "Vegano", 19, "Alcoólicos", 22, "Zero", 25, "Gelatos Proteicos", 28, 7), 2)) + (ROUND(J42,4) > INDEX('Tabela de ingredientes'!$O$1:$V$30, SWITCH(B42, "Gelatos de Leite", 8, "Sorbets", 11, "Gelatos de Leite com Fruta", 14, "Chocolate base água", 17, "Vegano", 20, "Alcoólicos", 23, "Zero", 26, "Gelatos Proteicos", 29, 8), 2)) + (ROUND(K42,4) < INDEX('Tabela de ingredientes'!$O$1:$V$30, SWITCH(B42, "Gelatos de Leite", 7, "Sorbets", 10, "Gelatos de Leite com Fruta", 13, "Chocolate base água", 16, "Vegano", 19, "Alcoólicos", 22, "Zero", 25, "Gelatos Proteicos", 28, 7), 3)) + (ROUND(K42,4) > INDEX('Tabela de ingredientes'!$O$1:$V$30, SWITCH(B42, "Gelatos de Leite", 8, "Sorbets", 11, "Gelatos de Leite com Fruta", 14, "Chocolate base água", 17, "Vegano", 20, "Alcoólicos", 23, "Zero", 26, "Gelatos Proteicos", 29, 8), 3)) + (ROUND(L42,4) < INDEX('Tabela de ingredientes'!$O$1:$V$30, SWITCH(B42, "Gelatos de Leite", 7, "Sorbets", 10, "Gelatos de Leite com Fruta", 13, "Chocolate base água", 16, "Vegano", 19, "Alcoólicos", 22, "Zero", 25, "Gelatos Proteicos", 28, 7), 4)) + (ROUND(L42,4) > INDEX('Tabela de ingredientes'!$O$1:$V$30, SWITCH(B42, "Gelatos de Leite", 8, "Sorbets", 11, "Gelatos de Leite com Fruta", 14, "Chocolate base água", 17, "Vegano", 20, "Alcoólicos", 23, "Zero", 26, "Gelatos Proteicos", 29, 8), 4)) + (ROUND(M42,4) < INDEX('Tabela de ingredientes'!$O$1:$V$30, SWITCH(B42, "Gelatos de Leite", 7, "Sorbets", 10, "Gelatos de Leite com Fruta", 13, "Chocolate base água", 16, "Vegano", 19, "Alcoólicos", 22, "Zero", 25, "Gelatos Proteicos", 28, 7), 5)) + (ROUND(M42,4) > INDEX('Tabela de ingredientes'!$O$1:$V$30, SWITCH(B42, "Gelatos de Leite", 8, "Sorbets", 11, "Gelatos de Leite com Fruta", 14, "Chocolate base água", 17, "Vegano", 20, "Alcoólicos", 23, "Zero", 26, "Gelatos Proteicos", 29, 8), 5)) + (ROUND(N42,4) < INDEX('Tabela de ingredientes'!$O$1:$V$30, SWITCH(B42, "Gelatos de Leite", 7, "Sorbets", 10, "Gelatos de Leite com Fruta", 13, "Chocolate base água", 16, "Vegano", 19, "Alcoólicos", 22, "Zero", 25, "Gelatos Proteicos", 28, 7), 6)) + (ROUND(N42,4) > INDEX('Tabela de ingredientes'!$O$1:$V$30, SWITCH(B42, "Gelatos de Leite", 8, "Sorbets", 11, "Gelatos de Leite com Fruta", 14, "Chocolate base água", 17, "Vegano", 20, "Alcoólicos", 23, "Zero", 26, "Gelatos Proteicos", 29, 8), 6)) + (ROUND(O42,4) < INDEX('Tabela de ingredientes'!$O$1:$V$30, SWITCH(B42, "Gelatos de Leite", 7, "Sorbets", 10, "Gelatos de Leite com Fruta", 13, "Chocolate base água", 16, "Vegano", 19, "Alcoólicos", 22, "Zero", 25, "Gelatos Proteicos", 28, 7), 7)) + (ROUND(O42,4) > INDEX('Tabela de ingredientes'!$O$1:$V$30, SWITCH(B42, "Gelatos de Leite", 8, "Sorbets", 11, "Gelatos de Leite com Fruta", 14, "Chocolate base água", 17, "Vegano", 20, "Alcoólicos", 23, "Zero", 26, "Gelatos Proteicos", 29, 8), 7)) + (ROUND(P42,4) < INDEX('Tabela de ingredientes'!$O$1:$V$30, SWITCH(B42, "Gelatos de Leite", 7, "Sorbets", 10, "Gelatos de Leite com Fruta", 13, "Chocolate base água", 16, "Vegano", 19, "Alcoólicos", 22, "Zero", 25, "Gelatos Proteicos", 28, 7), 8)) + (ROUND(P42,4) > INDEX('Tabela de ingredientes'!$O$1:$V$30, SWITCH(B42, "Gelatos de Leite", 8, "Sorbets", 11, "Gelatos de Leite com Fruta", 14, "Chocolate base água", 17, "Vegano", 20, "Alcoólicos", 23, "Zero", 26, "Gelatos Proteicos", 29, 8), 8)) + IF(B42="Gelatos Proteicos", (ROUND(Q42,4)<'Tabela de ingredientes'!$W$28)+(ROUND(Q42,4)>'Tabela de ingredientes'!$W$29), 0) = 0, "Ok", "Revisar"))} -> Revisar
A43: =IFERROR(__xludf.DUMMYFUNCTION("""COMPUTED_VALUE"""),"Gelato de Abóbora (Addolcire)") -> Gelato de Abóbora (Addolcire) | B43: Gelatos de Leite | C43: 8 | D43: 1000.91 | E43: Diferente (1001 g) | F43: 8.8261682 | G43: 0.52957009 | H43: 29.657424 | I43: 0.19508247 | J43: 0.068782408 | K43: 0.069726549 | L43: 0.018193444 | M43: 0.35178488 | N43: 0.64821512 | O43: 188.31523 | P43: 252.2005 | Q43: 0.029288348 | R43: 10.08802 | S43: {=IF(A43="","", IF( (ROUND(I43,4) < INDEX('Tabela de ingredientes'!$O$1:$V$30, SWITCH(B43, "Gelatos de Leite", 7, "Sorbets", 10, "Gelatos de Leite com Fruta", 13, "Chocolate base água", 16, "Vegano", 19, "Alcoólicos", 22, "Zero", 25, "Gelatos Proteicos", 28, 7), 1)) + (ROUND(I43,4) > INDEX('Tabela de ingredientes'!$O$1:$V$30, SWITCH(B43, "Gelatos de Leite", 8, "Sorbets", 11, "Gelatos de Leite com Fruta", 14, "Chocolate base água", 17, "Vegano", 20, "Alcoólicos", 23, "Zero", 26, "Gelatos Proteicos", 29, 8), 1)) + (ROUND(J43,4) < INDEX('Tabela de ingredientes'!$O$1:$V$30, SWITCH(B43, "Gelatos de Leite", 7, "Sorbets", 10, "Gelatos de Leite com Fruta", 13, "Chocolate base água", 16, "Vegano", 19, "Alcoólicos", 22, "Zero", 25, "Gelatos Proteicos", 28, 7), 2)) + (ROUND(J43,4) > INDEX('Tabela de ingredientes'!$O$1:$V$30, SWITCH(B43, "Gelatos de Leite", 8, "Sorbets", 11, "Gelatos de Leite com Fruta", 14, "Chocolate base água", 17, "Vegano", 20, "Alcoólicos", 23, "Zero", 26, "Gelatos Proteicos", 29, 8), 2)) + (ROUND(K43,4) < INDEX('Tabela de ingredientes'!$O$1:$V$30, SWITCH(B43, "Gelatos de Leite", 7, "Sorbets", 10, "Gelatos de Leite com Fruta", 13, "Chocolate base água", 16, "Vegano", 19, "Alcoólicos", 22, "Zero", 25, "Gelatos Proteicos", 28, 7), 3)) + (ROUND(K43,4) > INDEX('Tabela de ingredientes'!$O$1:$V$30, SWITCH(B43, "Gelatos de Leite", 8, "Sorbets", 11, "Gelatos de Leite com Fruta", 14, "Chocolate base água", 17, "Vegano", 20, "Alcoólicos", 23, "Zero", 26, "Gelatos Proteicos", 29, 8), 3)) + (ROUND(L43,4) < INDEX('Tabela de ingredientes'!$O$1:$V$30, SWITCH(B43, "Gelatos de Leite", 7, "Sorbets", 10, "Gelatos de Leite com Fruta", 13, "Chocolate base água", 16, "Vegano", 19, "Alcoólicos", 22, "Zero", 25, "Gelatos Proteicos", 28, 7), 4)) + (ROUND(L43,4) > INDEX('Tabela de ingredientes'!$O$1:$V$30, SWITCH(B43, "Gelatos de Leite", 8, "Sorbets", 11, "Gelatos de Leite com Fruta", 14, "Chocolate base água", 17, "Vegano", 20, "Alcoólicos", 23, "Zero", 26, "Gelatos Proteicos", 29, 8), 4)) + (ROUND(M43,4) < INDEX('Tabela de ingredientes'!$O$1:$V$30, SWITCH(B43, "Gelatos de Leite", 7, "Sorbets", 10, "Gelatos de Leite com Fruta", 13, "Chocolate base água", 16, "Vegano", 19, "Alcoólicos", 22, "Zero", 25, "Gelatos Proteicos", 28, 7), 5)) + (ROUND(M43,4) > INDEX('Tabela de ingredientes'!$O$1:$V$30, SWITCH(B43, "Gelatos de Leite", 8, "Sorbets", 11, "Gelatos de Leite com Fruta", 14, "Chocolate base água", 17, "Vegano", 20, "Alcoólicos", 23, "Zero", 26, "Gelatos Proteicos", 29, 8), 5)) + (ROUND(N43,4) < INDEX('Tabela de ingredientes'!$O$1:$V$30, SWITCH(B43, "Gelatos de Leite", 7, "Sorbets", 10, "Gelatos de Leite com Fruta", 13, "Chocolate base água", 16, "Vegano", 19, "Alcoólicos", 22, "Zero", 25, "Gelatos Proteicos", 28, 7), 6)) + (ROUND(N43,4) > INDEX('Tabela de ingredientes'!$O$1:$V$30, SWITCH(B43, "Gelatos de Leite", 8, "Sorbets", 11, "Gelatos de Leite com Fruta", 14, "Chocolate base água", 17, "Vegano", 20, "Alcoólicos", 23, "Zero", 26, "Gelatos Proteicos", 29, 8), 6)) + (ROUND(O43,4) < INDEX('Tabela de ingredientes'!$O$1:$V$30, SWITCH(B43, "Gelatos de Leite", 7, "Sorbets", 10, "Gelatos de Leite com Fruta", 13, "Chocolate base água", 16, "Vegano", 19, "Alcoólicos", 22, "Zero", 25, "Gelatos Proteicos", 28, 7), 7)) + (ROUND(O43,4) > INDEX('Tabela de ingredientes'!$O$1:$V$30, SWITCH(B43, "Gelatos de Leite", 8, "Sorbets", 11, "Gelatos de Leite com Fruta", 14, "Chocolate base água", 17, "Vegano", 20, "Alcoólicos", 23, "Zero", 26, "Gelatos Proteicos", 29, 8), 7)) + (ROUND(P43,4) < INDEX('Tabela de ingredientes'!$O$1:$V$30, SWITCH(B43, "Gelatos de Leite", 7, "Sorbets", 10, "Gelatos de Leite com Fruta", 13, "Chocolate base água", 16, "Vegano", 19, "Alcoólicos", 22, "Zero", 25, "Gelatos Proteicos", 28, 7), 8)) + (ROUND(P43,4) > INDEX('Tabela de ingredientes'!$O$1:$V$30, SWITCH(B43, "Gelatos de Leite", 8, "Sorbets", 11, "Gelatos de Leite com Fruta", 14, "Chocolate base água", 17, "Vegano", 20, "Alcoólicos", 23, "Zero", 26, "Gelatos Proteicos", 29, 8), 8)) + IF(B43="Gelatos Proteicos", (ROUND(Q43,4)<'Tabela de ingredientes'!$W$28)+(ROUND(Q43,4)>'Tabela de ingredientes'!$W$29), 0) = 0, "Ok", "Revisar"))} -> Revisar
